Workbook

Sheet Eneryg flow sharing
B2: Marked in yellow are those that are direct links to the sheets and not hard-coded values /Rud | I2: =Energy_KPI_export!I2 -> 599.12546
B4: Natural Gas CHP | G4: Biogas Plant | N4: Natural Gas CHP
B5: Utility type | C5: Input - TJ/y | D5: Output - TJ/y | H5: Input Electricity | I5: Input Heat | N5: Utility type | O5: Input - TJ/y | P5: Output - TJ/y
B6: Low pressure steam | C6: ='Natural Gas CHP'!C102 -> 0 | D6: =abs('Natural Gas CHP'!E102) -> 611.13758 | G6: kWh/y | H6: 4143.8836 | I6: 14981.733 | N6: Low pressure steam | O6: 0 | P6: 696.86051
B7: Mid pressure steam | C7: ='Natural Gas CHP'!C103 -> 0 | D7: =abs('Natural Gas CHP'!E103) -> 511.76342 | N7: Mid pressure steam | O7: 0 | P7: 583.54735
B8: High pressure steam | C8: ='Natural Gas CHP'!C104 -> 0 | D8: =abs('Natural Gas CHP'!E104) -> 444.06984 | N8: High pressure steam | O8: 0 | P8: 506.35855
B9: Cooling water | C9: ='Natural Gas CHP'!C105 -> 940.53459 | D9: =abs('Natural Gas CHP'!E105) -> 0 | N9: Cooling water | O9: 1072.4613 | P9: 0
B10: Fired Heat | C10: ='Natural Gas CHP'!C106 -> 599.12546 | D10: =abs('Natural Gas CHP'!E106) -> 0 | N10: Fired Heat | O10: 683.16348 | P10: 0
B11: Electricity - kWh/y | C11: ='Natural Gas CHP'!D109 -> 3.6239569e+08 | D11: =abs('Natural Gas CHP'!F109) -> 735819522 | N11: Electricity - kWh/y | O11: 4.1322814e+08 | P11: 8.3903132e+08
B14: Olefins Production Plant | G14: Methanol Production Plant
B15: Utility type | C15: Input - TJ/y | D15: Output - TJ/y | G15: Utility type | H15: Input - TJ/y | I15: Output - TJ/y
B16: Low pressure steam | C16: ='Olefins Production Plant'!C125 -> 11814.987 | D16: ='Olefins Production Plant'!E125 -> -4038.184 | G16: Low pressure steam | H16: 377.10549 | I16: 183.95329
B17: Mid pressure steam | C17: ='Olefins Production Plant'!C126 -> 9900.5797 | D17: ='Olefins Production Plant'!E126 -> -15225.437 | G17: Mid pressure steam | H17: 211.18307 | I17: 670.83929
B18: High pressure steam | C18: ='Olefins Production Plant'!C127 -> 0 | D18: ='Olefins Production Plant'!E127 -> -9069.094 | G18: High pressure steam | H18: 0 | I18: 708.81075
B19: Cooling water | C19: ='Olefins Production Plant'!C128 -> 20303.523 | D19: ='Olefins Production Plant'!E128 -> 0 | G19: Cooling water | H19: 4134.383 | I19: 0
B20: Very High pressure steam | C20: ='Olefins Production Plant'!C130 -> 0 | D20: ='Olefins Production Plant'!E130 -> -2979.3755 | G20: Electricity - kWh/y | H20: 1.9199038e+08 | I20: 0
B21: Electricity - kWh/y | C21: ='Olefins Production Plant'!D134 -> 2.6386888e+08 | D21: =abs('Olefins Production Plant'!F134) -> 56745852
B24: Aromatics Production Plant | G24: DME Plant
B25: Utility type | C25: Input - TJ/y | D25: Output - TJ/y | G25: Utility type | H25: Input - TJ/y | I25: Output - TJ/y
B26: Very low pressure steam | C26: 1982.3174 | D26: 1923.4683 | G26: Very low pressure steam | H26: 0 | I26: 52.06363
B27: Low pressure steam | C27: 1462.2693 | D27: 428.76889 | G27: Low pressure steam | H27: 0 | I27: 63.969345
B28: Mid pressure steam | C28: 3899.124 | D28: 0 | G28: Mid pressure steam | H28: 445.08236 | I28: 0
B29: High pressure steam | C29: 1489.0847 | D29: 0 | G29: High pressure steam | H29: 0 | I29: 0
B30: Cooling water | C30: 6917.1944 | D30: 0 | G30: Cooling water | H30: 659.34272 | I30: 0
B31: Chilled water | C31: 87.775641 | D31: 0 | G31: Electricity - kWh/y | H31: 19426831 | I31: 0
B32: Electricity - kWh/y | C32: 42665373 | D32: 0
B37: Utility type broad category | C37: Specific company-utility output | D37: Utility type | E37: Giver | F37: Receiver | G37: Net | H37: Surplus or deficit? | I37: Remainder if surplus | J37: Notes | K37: Amount being sent
B38: SELF-SHARING | C38: Self-sharing | D38: Electricity | E38: CHP | F38: CHP | G38: =C11-#REF! -> #REF! | H38: =if(G38 < 0,"Surplus","Deficit") -> #REF! | I38: =IF(G38<0,-G38,0) -> #REF! | K38: =C11 -> 3.6239569e+08
D39: Low pressure steam | E39: Olefins | F39: Olefins | G39: =C16-#REF! -> #REF! | H39: =if(G39 < 0,"Surplus","Deficit") -> #REF! | I39: =IF(G39<0,-G39,0) -> #REF! | K39: =#REF! -> #REF!
D40: Medium pressure steam | E40: Olefins | F40: Olefins | G40: =C17-#REF! -> #REF! | H40: =if(G40 < 0,"Surplus","Deficit") -> #REF! | I40: =IF(G40<0,-G40,0) -> #REF! | K40: =C17 -> 9900.5797
D41: Electricity | E41: Olefins | F41: Olefins | G41: =C20-D21 -> -56745852 | H41: =if(G41 < 0,"Surplus","Deficit") -> Surplus | I41: =IF(G41<0,-G41,0) -> 56745852 | K41: =D21 -> 56745852
D42: Very low pressure steam | E42: Aromatics | F42: Aromatics | G42: =C26-D26 -> 58.849144 | H42: =if(G42 < 0,"Surplus","Deficit") -> Deficit | I42: =IF(G42<0,-G42,0) -> 0 | K42: =D26 -> 1923.4683
D43: Low pressure steam | E43: Aromatics | F43: Aromatics | G43: =C27-D27 -> 1033.5004 | H43: =if(G43 < 0,"Surplus","Deficit") -> Deficit | I43: =IF(G43<0,-G43,0) -> 0 | K43: =D27 -> 428.76889
D44: Low pressure steam | E44: Methanol | F44: Methanol | G44: =H16-I16 -> 193.1522 | H44: =if(G44 < 0,"Surplus","Deficit") -> Deficit | I44: =IF(G44<0,-G44,0) -> 0 | K44: =I16 -> 183.95329
D45: Medium pressure steam | E45: Methanol | F45: Methanol | G45: =H17-I17 -> -459.65622 | H45: =if(G45 < 0,"Surplus","Deficit") -> Surplus | I45: =IF(G45<0,-G45,0) -> 459.65622 | K45: =H17 -> 211.18307
B46: VERY LOW PRESSURE STEAM | C46: DME VLPS output | D46: Very low pressure steam | E46: DME | F46: Aromatics | G46: =G42-I26 -> 6.7855142 | H46: =if(G46 < 0,"Surplus","Deficit") -> Deficit | I46: =IF(G46<0,-G46,0) -> 0 | K46: =I26 -> 52.06363
B47: LOW PRESSURE STEAM | C47: CHP LPS output | D47: Low pressure steam | E47: CHP | F47: Olefins | G47: =G39-#REF! -> #REF! | H47: =if(G47 < 0,"Surplus","Deficit") -> #REF! | I47: =IF(G47<0,-G47,0) -> #REF! | J47: First to methanol, then to aromatics, then final surplus to olefins | K47: =I49-K48 -> #REF!
D48: Low pressure steam | E48: CHP | F48: Aromatics | G48: =G43-#REF! -> #REF! | H48: =if(G48 < 0,"Surplus","Deficit") -> #REF! | I48: =IF(G48<0,-G48,0) -> #REF! | K48: =G48 -> #REF!
D49: Low pressure steam | E49: CHP | F49: Methanol | G49: =G44-#REF! -> #REF! | H49: =if(G49 < 0,"Surplus","Deficit") -> #REF! | I49: =IF(G49<0,-G49,0) -> #REF! | K49: =G44 -> 193.1522
C50: Olefins LPS output | D50: Low pressure steam | E50: Olefins | F50: Aromatics | G50: =C27-I39 -> #REF! | H50: =if(G50 < 0,"Surplus","Deficit") -> #REF! | I50: =IF(G50<0,-G50,0) -> #REF! | J50: After olefins self-sharing none is left, so ignore all
D51: Low pressure steam | E51: Olefins | F51: Methanol | G51: =H16-I39 -> #REF! | H51: =if(G51 < 0,"Surplus","Deficit") -> #REF! | I51: =IF(G51<0,-G51,0) -> #REF!
D52: Low pressure steam | E52: Olefins | F52: Methanol | G52: =H16-#REF! -> #REF! | H52: =if(G52 < 0,"Surplus","Deficit") -> #REF! | I52: =IF(G52<0,-G52,0) -> #REF!
C53: Aromatics LPS output | D53: Low pressure steam | E53: Aromatics | F53: Olefins | G53: =C16-I43 -> 11814.987 | H53: =if(G53 < 0,"Surplus","Deficit") -> Deficit | I53: =IF(G53<0,-G53,0) -> 0 | J53: After aromatics self-sharing none is left, so ignore all
C54: Methanol LPS output | D54: Low pressure steam | E54: Methanol | F54: Olefins | G54: =C16-I44 -> 11814.987 | H54: =if(G54 < 0,"Surplus","Deficit") -> Deficit | I54: =IF(G54<0,-G54,0) -> 0 | J54: After methanol self-sharing none is left, so ignore all
D55: Low pressure steam | E55: Methanol | F55: Aromatics | G55: =C27-I44 -> 1462.2693 | H55: =if(G55 < 0,"Surplus","Deficit") -> Deficit | I55: =IF(G55<0,-G55,0) -> 0
C56: DME LPS output | D56: Low pressure steam | E56: DME | F56: Olefins | G56: =G39-I27 -> #REF! | H56: =if(G56 < 0,"Surplus","Deficit") -> #REF! | I56: =IF(G56<0,-G56,0) -> #REF! | J56: Ignore, because all deficit
D57: Low pressure steam | E57: DME | F57: Aromatics | G57: =G43-I27 -> 969.53107 | H57: =if(G57 < 0,"Surplus","Deficit") -> Deficit | I57: =IF(G57<0,-G57,0) -> 0
D58: Low pressure steam | E58: DME | F58: Methanol | G58: =G44-I27 -> 129.18285 | H58: =if(G58 < 0,"Surplus","Deficit") -> Deficit | I58: =IF(G58<0,-G58,0) -> 0
B59: MEDIUM PRESSURE STEAM | C59: CHP MPS output | D59: Medium pressure steam | E59: CHP | F59: Olefins | G59: =C17-#REF! -> #REF! | H59: =if(G59 < 0,"Surplus","Deficit") -> #REF! | I59: =IF(G59<0,-G59,0) -> #REF! | J59: Olefins MPS output gave two surpluses, so we ignore these three rows
D60: Medium pressure steam | E60: CHP | F60: Aromatics | G60: =C28-#REF! -> #REF! | H60: =if(G60 < 0,"Surplus","Deficit") -> #REF! | I60: =IF(G60<0,-G60,0) -> #REF!
D61: Medium pressure steam | E61: CHP | F61: Methanol | G61: =H17-#REF! -> #REF! | H61: =if(G61 < 0,"Surplus","Deficit") -> #REF! | I61: =IF(G61<0,-G61,0) -> #REF!
D62: Medium pressure steam | E62: CHP | F62: DME | G62: =H28-#REF! -> #REF! | H62: =if(G62 < 0,"Surplus","Deficit") -> #REF! | I62: =IF(G62<0,-G62,0) -> #REF!
C63: Olefins MPS output | D63: Medium pressure steam | E63: Olefins | F63: Aromatics | G63: =C28-I40 -> #REF! | H63: =if(G63 < 0,"Surplus","Deficit") -> #REF! | I63: =IF(G63<0,-G63,0) -> #REF! | J63: After olefins self-sharing; methanol doesn't need any more after self-sharing, so ignore second row; first send to DME, then send remaining surplus to aromatics | K63: =I65 -> #REF!
D64: Medium pressure steam | E64: Olefins | F64: Methanol | G64: =H17-I40 -> #REF! | H64: =if(G64 < 0,"Surplus","Deficit") -> #REF! | I64: =IF(G64<0,-G64,0) -> #REF!
D65: Medium pressure steam | E65: Olefins | F65: DME | G65: =H28-I40 -> #REF! | H65: =if(G65 < 0,"Surplus","Deficit") -> #REF! | I65: =IF(G65<0,-G65,0) -> #REF! | K65: =H28 -> 445.08236
C66: Methanol MPS output | D66: Medium pressure steam | E66: Methanol | F66: Olefins | G66: =C17-I45 -> 9440.9235 | H66: =if(G66 < 0,"Surplus","Deficit") -> Deficit | I66: =IF(G66<0,-G66,0) -> 0 | J66: After methanol self-sharing; olefins doesn't need any more so ignore the first row; olefins MPS output gave two surpluses, so we ignore these three rows
D67: Medium pressure steam | E67: Methanol | F67: Aromatics | G67: =C28-I45 -> 3439.4678 | H67: =if(G67 < 0,"Surplus","Deficit") -> Deficit | I67: =IF(G67<0,-G67,0) -> 0
D68: Medium pressure steam | E68: Methanol | F68: DME | G68: =H28-I45 -> -14.573859 | H68: =if(G68 < 0,"Surplus","Deficit") -> Surplus | I68: =IF(G68<0,-G68,0) -> 14.573859
B69: HIGH PRESSURE STEAM | C69: CHP HPS output | D69: High pressure steam | E69: CHP | F69: Aromatics | G69: =C29-#REF! -> #REF! | H69: =if(G69 < 0,"Surplus","Deficit") -> #REF! | I69: =IF(G69<0,-G69,0) -> #REF! | J69: Ignore, because the olefins HPS output gave a surplus
C70: Olefins HPS output | D70: High pressure steam | E70: Olefins | F70: Aromatics | G70: =C29-#REF! -> #REF! | H70: =if(G70 < 0,"Surplus","Deficit") -> #REF! | I70: =IF(G70<0,-G70,0) -> #REF! | K70: =C29 -> 1489.0847
C71: Methanol HPS output | D71: High pressure steam | E71: Methanol | F71: Aromatics | G71: =C29-I18 -> 780.27397 | H71: =if(G71 < 0,"Surplus","Deficit") -> Deficit | I71: =IF(G71<0,-G71,0) -> 0 | J71: Ignore, because the olefins HPS output gave a surplus
B72: ELECTRICITY | C72: CHP electricity output | D72: Electricity | E72: CHP | F72: Olefins | G72: =G41-I38 -> #REF! | H72: =if(G72 < 0,"Surplus","Deficit") -> #REF! | I72: =IF(G72<0,-G72,0) -> #REF! | J72: After CHP self-sharing; first send to methanol; then to biogas because it has the lowest need; then to DME because it has the next lowest need; then to aromatics because it has the next lowest need; then finally to olefins giving a small deficit | K72: =I75-(K73+K74+K76) -> #REF!
D73: Electricity | E73: CHP | F73: Aromatics | G73: =C32-I38 -> #REF! | H73: =if(G73 < 0,"Surplus","Deficit") -> #REF! | I73: =IF(G73<0,-G73,0) -> #REF! | K73: =C32 -> 42665373
D74: Electricity | E74: CHP | F74: Biogas | G74: =H6-I38 -> #REF! | H74: =if(G74 < 0,"Surplus","Deficit") -> #REF! | I74: =IF(G74<0,-G74,0) -> #REF! | K74: =H6 -> 4143.8836
D75: Electricity | E75: CHP | F75: Methanol | G75: =H20-I38 -> #REF! | H75: =if(G75 < 0,"Surplus","Deficit") -> #REF! | I75: =IF(G75<0,-G75,0) -> #REF! | K75: =H20 -> 1.9199038e+08
D76: Electricity | E76: CHP | F76: DME | G76: =H31-I38 -> #REF! | H76: =if(G76 < 0,"Surplus","Deficit") -> #REF! | I76: =IF(G76<0,-G76,0) -> #REF! | K76: =H31 -> 19426831
C77: Olefins electricity output | D77: Electricity | E77: Olefins | F77: CHP | G77: =C11-I41 -> 3.0564984e+08 | H77: =if(G77 < 0,"Surplus","Deficit") -> Deficit | I77: =IF(G77<0,-G77,0) -> 0 | J77: After olefins self-sharing none is left, so ignore all
D78: Electricity | E78: Olefins | F78: Aromatics | G78: =C32-I41 -> -14080478 | H78: =if(G78 < 0,"Surplus","Deficit") -> Surplus | I78: =IF(G78<0,-G78,0) -> 14080478
D79: Electricity | E79: Olefins | F79: Biogas | G79: =H6-I41 -> -56741708 | H79: =if(G79 < 0,"Surplus","Deficit") -> Surplus | I79: =IF(G79<0,-G79,0) -> 56741708
D80: Electricity | E80: Olefins | F80: Methanol | G80: =H20-I41 -> 1.3524453e+08 | H80: =if(G80 < 0,"Surplus","Deficit") -> Deficit | I80: =IF(G80<0,-G80,0) -> 0
D81: Electricity | E81: Olefins | F81: DME | G81: =H31-I41 -> -37319021 | H81: =if(G81 < 0,"Surplus","Deficit") -> Surplus | I81: =IF(G81<0,-G81,0) -> 37319021

Sheet Energy_KPI_cooling_water_export
A1: Company | B1: input_cooling_water_kt_y | C1: output_cooling_water_kt_y
A2: Aromatics plant | B2: ='Aromatics Production Plant'!D147 -> 110518.64 | C2: ='Aromatics Production Plant'!F147 -> 0
A3: Biogas plant | B3: 0 | C3: 0
A4: CHP plant | B4: ='Natural Gas CHP'!D105 -> 15027.296 | C4: ='Natural Gas CHP'!F105 -> 0
A5: DME plant | B5: ='DME Plant'!D101 -> 10508.277 | C5: ='DME Plant'!F101 -> 0
A6: Methanol plant | B6: ='Methanol Production Plant'!D108 -> 65891.824 | C6: ='Methanol Production Plant'!F108 -> 0
A7: Olefins plant | B7: ='Olefins Production Plant'!D128 -> 323673.76 | C7: ='Olefins Production Plant'!F128 -> 0

Sheet Energy_KPI_export
A1: Company | B1: Very low pressure steam | C1: Low pressure steam | D1: Mid pressure steam | E1: High pressure steam | F1: Very High pressure steam | G1: Cooling water | H1: Chilled water | I1: Fired Heat | J1: Electricity - kWh/y | K1: Input_Output
A2: CHP plant | B2: {=iferror(index('Eneryg flow sharing'!$C$6:$D$11,match(B$1,'Eneryg flow sharing'!$B$6:$B$11,0),1+($K2="Output")),"")} | C2: {=iferror(index('Eneryg flow sharing'!$C$6:$D$11,match(C$1,'Eneryg flow sharing'!$B$6:$B$11,0),1+($K2="Output")),"")} -> 0 | D2: {=iferror(index('Eneryg flow sharing'!$C$6:$D$11,match(D$1,'Eneryg flow sharing'!$B$6:$B$11,0),1+($K2="Output")),"")} -> 0 | E2: {=iferror(index('Eneryg flow sharing'!$C$6:$D$11,match(E$1,'Eneryg flow sharing'!$B$6:$B$11,0),1+($K2="Output")),"")} -> 0 | F2: {=iferror(index('Eneryg flow sharing'!$C$6:$D$11,match(F$1,'Eneryg flow sharing'!$B$6:$B$11,0),1+($K2="Output")),"")} | G2: {=iferror(index('Eneryg flow sharing'!$C$6:$D$11,match(G$1,'Eneryg flow sharing'!$B$6:$B$11,0),1+($K2="Output")),"")} -> 940.53459 | H2: {=iferror(index('Eneryg flow sharing'!$C$6:$D$11,match(H$1,'Eneryg flow sharing'!$B$6:$B$11,0),1+($K2="Output")),"")} | I2: {=iferror(index('Eneryg flow sharing'!$C$6:$D$11,match(I$1,'Eneryg flow sharing'!$B$6:$B$11,0),1+($K2="Output")),"")} -> 599.12546 | J2: {=iferror(index('Eneryg flow sharing'!$C$6:$D$11,match(J$1,'Eneryg flow sharing'!$B$6:$B$11,0),1+($K2="Output")),"")} -> 3.6239569e+08 | K2: Input
A3: Olefins plant | B3: {=iferror(index('Eneryg flow sharing'!$C$16:$D$21,match(B$1,'Eneryg flow sharing'!$B$16:$B$21,0),1+($K3="Output")),"")} | C3: {=iferror(index('Eneryg flow sharing'!$C$16:$D$21,match(C$1,'Eneryg flow sharing'!$B$16:$B$21,0),1+($K3="Output")),"")} -> 11814.987 | D3: {=iferror(index('Eneryg flow sharing'!$C$16:$D$21,match(D$1,'Eneryg flow sharing'!$B$16:$B$21,0),1+($K3="Output")),"")} -> 9900.5797 | E3: {=iferror(index('Eneryg flow sharing'!$C$16:$D$21,match(E$1,'Eneryg flow sharing'!$B$16:$B$21,0),1+($K3="Output")),"")} -> 0 | F3: {=iferror(index('Eneryg flow sharing'!$C$16:$D$21,match(F$1,'Eneryg flow sharing'!$B$16:$B$21,0),1+($K3="Output")),"")} -> 0 | G3: {=iferror(index('Eneryg flow sharing'!$C$16:$D$21,match(G$1,'Eneryg flow sharing'!$B$16:$B$21,0),1+($K3="Output")),"")} -> 20303.523 | H3: {=iferror(index('Eneryg flow sharing'!$C$16:$D$21,match(H$1,'Eneryg flow sharing'!$B$16:$B$21,0),1+($K3="Output")),"")} | I3: {=iferror(index('Eneryg flow sharing'!$C$16:$D$21,match(I$1,'Eneryg flow sharing'!$B$16:$B$21,0),1+($K3="Output")),"")} | J3: {=iferror(index('Eneryg flow sharing'!$C$16:$D$21,match(J$1,'Eneryg flow sharing'!$B$16:$B$21,0),1+($K3="Output")),"")} -> 2.6386888e+08 | K3: Input
A4: Aromatics plant | B4: {=iferror(index('Eneryg flow sharing'!$C$26:$D$32,match(B$1,'Eneryg flow sharing'!$B$26:$B$32,0),1+($K4="Output")),"")} -> 1982.3174 | C4: {=iferror(index('Eneryg flow sharing'!$C$26:$D$32,match(C$1,'Eneryg flow sharing'!$B$26:$B$32,0),1+($K4="Output")),"")} -> 1462.2693 | D4: {=iferror(index('Eneryg flow sharing'!$C$26:$D$32,match(D$1,'Eneryg flow sharing'!$B$26:$B$32,0),1+($K4="Output")),"")} -> 3899.124 | E4: {=iferror(index('Eneryg flow sharing'!$C$26:$D$32,match(E$1,'Eneryg flow sharing'!$B$26:$B$32,0),1+($K4="Output")),"")} -> 1489.0847 | F4: {=iferror(index('Eneryg flow sharing'!$C$26:$D$32,match(F$1,'Eneryg flow sharing'!$B$26:$B$32,0),1+($K4="Output")),"")} | G4: {=iferror(index('Eneryg flow sharing'!$C$26:$D$32,match(G$1,'Eneryg flow sharing'!$B$26:$B$32,0),1+($K4="Output")),"")} -> 6917.1944 | H4: {=iferror(index('Eneryg flow sharing'!$C$26:$D$32,match(H$1,'Eneryg flow sharing'!$B$26:$B$32,0),1+($K4="Output")),"")} -> 87.775641 | I4: {=iferror(index('Eneryg flow sharing'!$C$26:$D$32,match(I$1,'Eneryg flow sharing'!$B$26:$B$32,0),1+($K4="Output")),"")} | J4: {=iferror(index('Eneryg flow sharing'!$C$26:$D$32,match(J$1,'Eneryg flow sharing'!$B$26:$B$32,0),1+($K4="Output")),"")} -> 42665373 | K4: Input
A5: Biogas plant | I5: ='Eneryg flow sharing'!$I$6 -> 14981.733 | J5: ='Eneryg flow sharing'!$H$6 -> 4143.8836 | K5: Input
A6: Methanol plant | B6: {=iferror(index('Eneryg flow sharing'!$H$16:$I$21,match(B$1,'Eneryg flow sharing'!$G$16:$G$21,0),1+($K6="Output")),"")} | C6: {=iferror(index('Eneryg flow sharing'!$H$16:$I$21,match(C$1,'Eneryg flow sharing'!$G$16:$G$21,0),1+($K6="Output")),"")} -> 377.10549 | D6: {=iferror(index('Eneryg flow sharing'!$H$16:$I$21,match(D$1,'Eneryg flow sharing'!$G$16:$G$21,0),1+($K6="Output")),"")} -> 211.18307 | E6: {=iferror(index('Eneryg flow sharing'!$H$16:$I$21,match(E$1,'Eneryg flow sharing'!$G$16:$G$21,0),1+($K6="Output")),"")} -> 0 | F6: {=iferror(index('Eneryg flow sharing'!$H$16:$I$21,match(F$1,'Eneryg flow sharing'!$G$16:$G$21,0),1+($K6="Output")),"")} | G6: {=iferror(index('Eneryg flow sharing'!$H$16:$I$21,match(G$1,'Eneryg flow sharing'!$G$16:$G$21,0),1+($K6="Output")),"")} -> 4134.383 | H6: {=iferror(index('Eneryg flow sharing'!$H$16:$I$21,match(H$1,'Eneryg flow sharing'!$G$16:$G$21,0),1+($K6="Output")),"")} | I6: {=iferror(index('Eneryg flow sharing'!$H$16:$I$21,match(I$1,'Eneryg flow sharing'!$G$16:$G$21,0),1+($K6="Output")),"")} | J6: {=iferror(index('Eneryg flow sharing'!$H$16:$I$21,match(J$1,'Eneryg flow sharing'!$G$16:$G$21,0),1+($K6="Output")),"")} -> 1.9199038e+08 | K6: Input
A7: DME plant | B7: {=iferror(index('Eneryg flow sharing'!$H$26:$I$32,match(B$1,'Eneryg flow sharing'!$G$26:$G$32,0),1+($K7="Output")),"")} -> 0 | C7: {=iferror(index('Eneryg flow sharing'!$H$26:$I$32,match(C$1,'Eneryg flow sharing'!$G$26:$G$32,0),1+($K7="Output")),"")} -> 0 | D7: {=iferror(index('Eneryg flow sharing'!$H$26:$I$32,match(D$1,'Eneryg flow sharing'!$G$26:$G$32,0),1+($K7="Output")),"")} -> 445.08236 | E7: {=iferror(index('Eneryg flow sharing'!$H$26:$I$32,match(E$1,'Eneryg flow sharing'!$G$26:$G$32,0),1+($K7="Output")),"")} -> 0 | F7: {=iferror(index('Eneryg flow sharing'!$H$26:$I$32,match(F$1,'Eneryg flow sharing'!$G$26:$G$32,0),1+($K7="Output")),"")} | G7: {=iferror(index('Eneryg flow sharing'!$H$26:$I$32,match(G$1,'Eneryg flow sharing'!$G$26:$G$32,0),1+($K7="Output")),"")} -> 659.34272 | H7: {=iferror(index('Eneryg flow sharing'!$H$26:$I$32,match(H$1,'Eneryg flow sharing'!$G$26:$G$32,0),1+($K7="Output")),"")} | I7: {=iferror(index('Eneryg flow sharing'!$H$26:$I$32,match(I$1,'Eneryg flow sharing'!$G$26:$G$32,0),1+($K7="Output")),"")} | J7: {=iferror(index('Eneryg flow sharing'!$H$26:$I$32,match(J$1,'Eneryg flow sharing'!$G$26:$G$32,0),1+($K7="Output")),"")} -> 19426831 | K7: Input
A8: CHP plant | B8: {=iferror(index('Eneryg flow sharing'!$C$6:$D$11,match(B$1,'Eneryg flow sharing'!$B$6:$B$11,0),1+($K8="Output")),"")} | C8: {=iferror(index('Eneryg flow sharing'!$C$6:$D$11,match(C$1,'Eneryg flow sharing'!$B$6:$B$11,0),1+($K8="Output")),"")} -> 611.13758 | D8: {=iferror(index('Eneryg flow sharing'!$C$6:$D$11,match(D$1,'Eneryg flow sharing'!$B$6:$B$11,0),1+($K8="Output")),"")} -> 511.76342 | E8: {=iferror(index('Eneryg flow sharing'!$C$6:$D$11,match(E$1,'Eneryg flow sharing'!$B$6:$B$11,0),1+($K8="Output")),"")} -> 444.06984 | F8: {=iferror(index('Eneryg flow sharing'!$C$6:$D$11,match(F$1,'Eneryg flow sharing'!$B$6:$B$11,0),1+($K8="Output")),"")} | G8: {=iferror(index('Eneryg flow sharing'!$C$6:$D$11,match(G$1,'Eneryg flow sharing'!$B$6:$B$11,0),1+($K8="Output")),"")} -> 0 | H8: {=iferror(index('Eneryg flow sharing'!$C$6:$D$11,match(H$1,'Eneryg flow sharing'!$B$6:$B$11,0),1+($K8="Output")),"")} | I8: {=iferror(index('Eneryg flow sharing'!$C$6:$D$11,match(I$1,'Eneryg flow sharing'!$B$6:$B$11,0),1+($K8="Output")),"")} -> 0 | J8: {=iferror(index('Eneryg flow sharing'!$C$6:$D$11,match(J$1,'Eneryg flow sharing'!$B$6:$B$11,0),1+($K8="Output")),"")} -> 735819522 | K8: Output
A9: Olefins plant | B9: {=iferror(index('Eneryg flow sharing'!$C$16:$D$21,match(B$1,'Eneryg flow sharing'!$B$16:$B$21,0),1+($K9="Output")),"")} | C9: {=iferror(index('Eneryg flow sharing'!$C$16:$D$21,match(C$1,'Eneryg flow sharing'!$B$16:$B$21,0),1+($K9="Output")),"")} -> -4038.184 | D9: {=iferror(index('Eneryg flow sharing'!$C$16:$D$21,match(D$1,'Eneryg flow sharing'!$B$16:$B$21,0),1+($K9="Output")),"")} -> -15225.437 | E9: {=iferror(index('Eneryg flow sharing'!$C$16:$D$21,match(E$1,'Eneryg flow sharing'!$B$16:$B$21,0),1+($K9="Output")),"")} -> -9069.094 | F9: {=iferror(index('Eneryg flow sharing'!$C$16:$D$21,match(F$1,'Eneryg flow sharing'!$B$16:$B$21,0),1+($K9="Output")),"")} -> -2979.3755 | G9: {=iferror(index('Eneryg flow sharing'!$C$16:$D$21,match(G$1,'Eneryg flow sharing'!$B$16:$B$21,0),1+($K9="Output")),"")} -> 0 | H9: {=iferror(index('Eneryg flow sharing'!$C$16:$D$21,match(H$1,'Eneryg flow sharing'!$B$16:$B$21,0),1+($K9="Output")),"")} | I9: {=iferror(index('Eneryg flow sharing'!$C$16:$D$21,match(I$1,'Eneryg flow sharing'!$B$16:$B$21,0),1+($K9="Output")),"")} | J9: {=iferror(index('Eneryg flow sharing'!$C$16:$D$21,match(J$1,'Eneryg flow sharing'!$B$16:$B$21,0),1+($K9="Output")),"")} -> 56745852 | K9: Output
A10: Aromatics plant | B10: {=iferror(index('Eneryg flow sharing'!$C$26:$D$32,match(B$1,'Eneryg flow sharing'!$B$26:$B$32,0),1+($K10="Output")),"")} -> 1923.4683 | C10: {=iferror(index('Eneryg flow sharing'!$C$26:$D$32,match(C$1,'Eneryg flow sharing'!$B$26:$B$32,0),1+($K10="Output")),"")} -> 428.76889 | D10: {=iferror(index('Eneryg flow sharing'!$C$26:$D$32,match(D$1,'Eneryg flow sharing'!$B$26:$B$32,0),1+($K10="Output")),"")} -> 0 | E10: {=iferror(index('Eneryg flow sharing'!$C$26:$D$32,match(E$1,'Eneryg flow sharing'!$B$26:$B$32,0),1+($K10="Output")),"")} -> 0 | F10: {=iferror(index('Eneryg flow sharing'!$C$26:$D$32,match(F$1,'Eneryg flow sharing'!$B$26:$B$32,0),1+($K10="Output")),"")} | G10: {=iferror(index('Eneryg flow sharing'!$C$26:$D$32,match(G$1,'Eneryg flow sharing'!$B$26:$B$32,0),1+($K10="Output")),"")} -> 0 | H10: {=iferror(index('Eneryg flow sharing'!$C$26:$D$32,match(H$1,'Eneryg flow sharing'!$B$26:$B$32,0),1+($K10="Output")),"")} -> 0 | I10: {=iferror(index('Eneryg flow sharing'!$C$26:$D$32,match(I$1,'Eneryg flow sharing'!$B$26:$B$32,0),1+($K10="Output")),"")} | J10: {=iferror(index('Eneryg flow sharing'!$C$26:$D$32,match(J$1,'Eneryg flow sharing'!$B$26:$B$32,0),1+($K10="Output")),"")} -> 0 | K10: Output
A11: Biogas plant | K11: Output
A12: Methanol plant | B12: {=iferror(index('Eneryg flow sharing'!$H$16:$I$21,match(B$1,'Eneryg flow sharing'!$G$16:$G$21,0),1+($K12="Output")),"")} | C12: {=iferror(index('Eneryg flow sharing'!$H$16:$I$21,match(C$1,'Eneryg flow sharing'!$G$16:$G$21,0),1+($K12="Output")),"")} -> 183.95329 | D12: {=iferror(index('Eneryg flow sharing'!$H$16:$I$21,match(D$1,'Eneryg flow sharing'!$G$16:$G$21,0),1+($K12="Output")),"")} -> 670.83929 | E12: {=iferror(index('Eneryg flow sharing'!$H$16:$I$21,match(E$1,'Eneryg flow sharing'!$G$16:$G$21,0),1+($K12="Output")),"")} -> 708.81075 | F12: {=iferror(index('Eneryg flow sharing'!$H$16:$I$21,match(F$1,'Eneryg flow sharing'!$G$16:$G$21,0),1+($K12="Output")),"")} | G12: {=iferror(index('Eneryg flow sharing'!$H$16:$I$21,match(G$1,'Eneryg flow sharing'!$G$16:$G$21,0),1+($K12="Output")),"")} -> 0 | H12: {=iferror(index('Eneryg flow sharing'!$H$16:$I$21,match(H$1,'Eneryg flow sharing'!$G$16:$G$21,0),1+($K12="Output")),"")} | I12: {=iferror(index('Eneryg flow sharing'!$H$16:$I$21,match(I$1,'Eneryg flow sharing'!$G$16:$G$21,0),1+($K12="Output")),"")} | J12: {=iferror(index('Eneryg flow sharing'!$H$16:$I$21,match(J$1,'Eneryg flow sharing'!$G$16:$G$21,0),1+($K12="Output")),"")} -> 0 | K12: Output
A13: DME plant | B13: {=iferror(index('Eneryg flow sharing'!$H$26:$I$32,match(B$1,'Eneryg flow sharing'!$G$26:$G$32,0),1+($K13="Output")),"")} -> 52.06363 | C13: {=iferror(index('Eneryg flow sharing'!$H$26:$I$32,match(C$1,'Eneryg flow sharing'!$G$26:$G$32,0),1+($K13="Output")),"")} -> 63.969345 | D13: {=iferror(index('Eneryg flow sharing'!$H$26:$I$32,match(D$1,'Eneryg flow sharing'!$G$26:$G$32,0),1+($K13="Output")),"")} -> 0 | E13: {=iferror(index('Eneryg flow sharing'!$H$26:$I$32,match(E$1,'Eneryg flow sharing'!$G$26:$G$32,0),1+($K13="Output")),"")} -> 0 | F13: {=iferror(index('Eneryg flow sharing'!$H$26:$I$32,match(F$1,'Eneryg flow sharing'!$G$26:$G$32,0),1+($K13="Output")),"")} | G13: {=iferror(index('Eneryg flow sharing'!$H$26:$I$32,match(G$1,'Eneryg flow sharing'!$G$26:$G$32,0),1+($K13="Output")),"")} -> 0 | H13: {=iferror(index('Eneryg flow sharing'!$H$26:$I$32,match(H$1,'Eneryg flow sharing'!$G$26:$G$32,0),1+($K13="Output")),"")} | I13: {=iferror(index('Eneryg flow sharing'!$H$26:$I$32,match(I$1,'Eneryg flow sharing'!$G$26:$G$32,0),1+($K13="Output")),"")} | J13: {=iferror(index('Eneryg flow sharing'!$H$26:$I$32,match(J$1,'Eneryg flow sharing'!$G$26:$G$32,0),1+($K13="Output")),"")} -> 0 | K13: Output

Sheet Natural Gas CHP
B3: Natural gas CHP
B4: Process datasheet (Mass & Energy Balance)
B6: Production capacity | D6: 50 MW electricity and 120 ton/h of steam
B7: Operating hours per year | D7: 8000 h/y
B9: Overall Process Description
B10: This process description presents a cogeneration plant, also called combined heat and power plant (CHP), which uses natural gas to produce 50 MW electricity and 120 ton/h of steam. A cogeneration is a system that recaptures otherwise wasted thermal energy, usually from a heat engine (such as a steam turbine, gas turbine, or diesel engine) to produce electricity and use it for industrial processes, space conditioning, or as an energy source for another system component. This “cascading” of energy use is what distinguishes cogeneration systems from conventional separate electric and thermal energy systems (e.g., a powerplant and an industrial boiler), or from simple heat recovery strategies [1]. Most cogeneration systems can be described either as “topping” systems or “bottoming” systems, depending on whether the electrical or thermal energy is produced first. In a topping system—the most common cogeneration mode— electricity is produced first. The thermal energy that is exhausted is captured and used for such purposes as industrial processes, space heating and cooling, water heating, or even producing more electricity. Topping systems would be used in residential/commercial and most industrial cogeneration applications. In a bottoming system, high-temperature thermal energy is produced first for applications such as steel reheat furnaces, glass kilns, or aluminum remelt furnaces. Heat is extracted from the hot exhaust waste stream and transferred to a working fluid, generally through a waste heat recovery boiler. The fluid is vaporized and used to drive a turbine (Rankine cycle) to produce electrical energy. Bottoming cycles are used mostly in industries where high-temperature waste heat is available, and thus are limited to a few industrial processes. Further, they tend to have a higher capital cost than topping systems [1,2]. Topping systems can be further classified as combined cycle CHP plant, steam turbine CHP plant, internal combustion engine and gas turbine. When the emphasis is on the generation of electric power within the plant with high efficiency, the gas and steam cycles are combined into one arrangement. This arrangement uses a gas turbine to generate electricity from the fuel, in which, natural gas is added along with a stream of air, which combusts and expands through this turbine causing a generator to spin a magnet, producing electricity. From the process, there is waste heat that is recovered from the flue-gas through a heat recovery steam generator (HRSG) [2].Due to this arrangement, combined cycle plants are more efficient because they make use of the hot exhaust gases that would otherwise be dispelled from the system. These exhaust gases are used to boil water into steam—which can then spin another turbine and generate more electricity [3]. The thermal efficiency of the combined cycle can get up to 60% [4,5]. The advantages of a combined cycle are [3]: -Higher thermal efficiency -Lower capital investment -Faster starting and peaking times -Less thermal pollution (less energy discharge to cooling water per kWh) -Wide range of flexibility of power generation (thermal, mechanical, and electrical) In the current process, a cogeneration plant is presented. The CHP is composed of a gas turbine, a HRSG and a steam turbine.
B18: Process Diagram description
B19: The cogeneration plant is composed of a single shaft gas turbine, a heat recovery steam generator (HRSG), and a steam turbine [6,7]. The flow diagram presented above is described as follows. The cogeneration involves compression of air, the subsequent heating of this gas by burning a fuel without a change in pressure, followed by the expansion of the hot, pressurized gas. The compression process consumes power, while the expansion process extracts power from the gas. Some of the power from the expansion process is used to drive the compression process and the rest is used as useable power output [8]. The exhaust gases from the gas turbine are mixed and combusted with more natural gas, thus resulting in the increase in its temperature. The hot gases from the secondary combustion are carried out to the HRSG system and used to produce steam at different pressures[9]. The detailed description of the process is as follows: The single shaft gas turbine uses atmospheric air (15 °C, 1.02 bar) in excess to ensure complete combustion of the natural gas. For natural gas-fired burners, the stoichiometric air required is 9.4-11 ft.3 / 1.0 ft.3 of natural gas or approximately an air-to-gas ratio of approximately 24:1 (mol) [10]. In this case, the air flowrate is adjusted to maintain the combustion temperature below 1260 °C and reach an oxygen content of 13-15 mol% in the exhaust gas as required for the turbine and second burner [11,12]. A maximum turbine inlet temperature of over 1050 °C is preferred for thermal efficiency [13]. The air is then compressed in a multi-stage compressor with 15 stages and a compression ratio of 19.8:1, with equal compression ratio of 1.21 in each stage [7,14–16]. Isentropic efficiencies are taken to be constant, at 83% for the compressors and 90% for both the gas and steam turbines [17,18]. An intercooler is provided between each two stages of compression to cool air before it enters the next stage of compression[19]. The lower density of cool air makes it easier to compress than hot air. Ideally, the air should be as close to the ambient air temperature as possible. Typically, the intercooler is able to cool the compressed air within 20-30 degrees of the ambient air temperature[20]. The air is cooled to 40 °C in the intercooler [17,21] and it is used for the combustion of the natural gas. The natural gas (15 °C, 1.02 bar) composed mainly of CH4 and other components in lower concentrations (C2H6, C3H8, N2 and CO2) is defined and compressed to 20 bar to maintain well pressures and enable the burner to operate at the compressed air pressure [22]. Moreover, the compressed natural gas is heated to 300 °C before combustion. Increasing the inlet gas temperature from 240°C, abruptly increases the flame luminosity. This luminosity increase enhances the boiler efficiency and also causes significant reduction in flame temperature and NO emission. The results show that increasing the inlet gas temperature from 240°C to 300°C increases the flame luminous radiation by 60% and boiler efficiency by 20% [23]. In the burner, at these conditions, combustion temperatures of natural gas on air of 974 °C are reached. The hot exhaust gas is then sent to the turbine section, which consists of a high-efficiency 3-stage turbine operating at pressure ratios of around 1.5-5 [5, 14,24,25]. The industrial gas turbines have a lower pressure ratio and higher exhaust temperature to promote combined-cycle performance[26]. Such high exhaust discharge temperatures permit direct use of the exhaust[27]. For instance, maintaining the hot exhaust gas temperature is important to exchange heat in the countercurrent heat exchanger between the air and the exhaust gas [8]. By doing so, an increase in the air temperature for the first burner is achieved, and the gas turbine exhaust gases are conditioned to 500 °C, which is the final temperature of the turbine discharge exhaust gases and the required temperature for the second burner (supplementary firing system) [12]. More specifically, the exhaust gas of a gas turbine has an oxygen concentration of 13-15 wt%, temperature of 500- 600 °C, and in the exhaust supplementary firing system, only this exhaust gas is used as oxygen source for combustion. This supplementary firing burner helps a waste heat boiler increase output by reheating gas turbine exhaust with no additional air [12]. The reheated gas turbine exhaust gas is sent to a heat recovery steam generator (HRSG) section, in which it goes through a series of countercurrent heat exchangers to recover the heat from the turbine exhaust gasand convertswater into useful thermal energy in the form of steam. The current process consists of 3 heat recovery heat exchangers to produce high pressure-high temperature steam (HP), medium pressure (MP) steam and low pressure (LP)steam. HP and MP steam are also used to create additional power using steam turbines. The HRSG exhaust temperature is of around 160 °C, as reported for different HRSG systems [28]. Overall, the HRSG arrangement is composed of countercurrent heat exchangers to achieve the required steam temperatures and a series of pumps and turbines to adjust the pressure to produce the required HP, MP and LP steam [17,29,30], while producing electricity. Overall, the main products of the process are: electricity, HP, MP and LP steam. The main waste stream of the process is composed of exhaust flue gases like N2, O2, H2O and CO2 .
L36: LEGENDS
L37: FS- Feedstock/Raw material
L38: PS- Product
L39: WS-Waste
N41: LEGENDS
N42: FS- Feedstock/Raw material
N43: PS- Product
N44: WS-Waste
G65: Figure 1. Process Flow Diagram- CHP for electricity and steam production
B67: Mass Balances
B70: Raw materials | F70: Products | J70: Balance check
B71: Stream | C71: Composition (% mass) | D71: Flow kt/y | F71: Stream | G71: Composition (% mass) | H71: Flow kt/y | J71: Total inputs/outputs
B72: FS-AIR | C72: 23.3% O2, 76.7% N2 | D72: 3924.048 | F72: PS-LPS | G72: 100 % H2O | H72: 320 | J72: Raw materials (FS) | K72: =SUM(D72:D75) -> 4996.348
B73: FS-NG1 | C73: 70.5% CH4, 2.38% CO2, 21.78 N2, 4.88% N-C2A, 0.47% NC3-A | D73: 105 | F73: PS-MPS | G73: 100 % H2O | H73: 320 | J73: Products (PS) | K73: =SUM(H72:H74) -> 960
B74: FS-NG2 | C74: 70.5% CH4, 2.38% CO2, 21.78 N2, 4.88% N-C2A, 0.47% NC3-A | D74: 7.3 | F74: PS-HPS | G74: 100 % H2O | H74: 320 | J74: Waste Streams (WS) | K74: =H75 -> 4036.295
B75: FS-WATER | C75: 100 % H2O | D75: 960 | F75: WS-FLUEG | G75: 75.2% N2, 5.9% CO2, 14.3% O2, 4.7% H2O | H75: 4036.295
J76: Balance check | K76: =K72-K73-K74 -> 0.053
J77: Percent error (%) | K77: =(K76/K72)*100 -> 0.0010607748
B81: Energy Balances
K82: Utility process conditions
B83: Utility type | C83: Input - TJ/y | D83: Input - kt/y | E83: Output - TJ/y | F83: Output - kt/y | G83: Net - TJ/y | H83: Net - kt/y | I83: Remark | K83: Utility type | L83: Inlet temperature ( °C ) | M83: Outlet temperature ( °C ) | N83: Inlet pressure (bar) | O83: Outlet pressure (bar) | P83: Heat capacity/latent heat/lower heating value | Q83: Unit
B84: Low pressure steam | C84: 0 | D84: 0 | E84: -722.24 | F84: -320 | G84: -722.24 | H84: -320 | I84: Net Generation | K84: Very Low pressure steam | L84: - | M84: - | N84: - | O84: - | P84: - | Q84: -
B85: Mid pressure steam | C85: 0 | D85: 0 | E85: -604.8 | F85: -320 | G85: -604.8 | H85: -320 | I85: Net Generation | K85: Low pressure steam | L85: 155 | M85: 155 | N85: 5.5 | O85: 5.5 | P85: 2096.7716 | Q85: KJ/kg
B86: High pressure steam | C86: 0 | D86: 0 | E86: -524.8 | F86: -320 | G86: -524.8 | H86: -320 | I86: Net Generation | K86: Mid pressure steam | L86: 214 | M86: 214 | N86: 21 | O86: 21 | P86: 1879.6128 | Q86: KJ/kg
B87: Cooling water | C87: 1111.5201 | D87: 17759.2 | E87: 0 | F87: 0 | G87: 1111.5201 | H87: 17759.2 | K87: High pressure steam | L87: 265 | M87: 265 | N87: 51 | O87: 51 | P87: 1632.4494 | Q87: KJ/kg
B88: Fired Heat | C88: 708.04413 | D88: NA | E88: 0 | F88: NA | G88: 708.04413 | H88: NA | K88: Fired Heat | L88: 1000 | M88: 750 | N88: 2 | O88: 2 | P88: - | Q88: -
B89: Electricity | C89: 1407.1023 | D89: 48857.7 | E89: -2857.022 | F89: -99202,2 | G89: -1449.9197 | H89: -50344,5 | I89: Net Generation, kt/y values are kW | K89: Cooling water | L89: 25 | M89: 40 | N89: 1.02 | O89: 1.02 | P89: =62.74243314036/(M89-L89) -> 4.1828289 | Q89: KJ/kg.K
B90: *NA- Not Applicable | G90: =SUM(G84:G89) -> -1482.1955 | H90: =SUM(H84:H89) -> 16799.2
C92: Value | D92: Unit | E92: Remark
B93: TOTAL Energy requirements (kWh/y) from the other 5 plants in our system | C93: =SUM('Olefins Production Plant'!D134,'Aromatics Production Plant'!D153,'Biogas Plant'!C96,'Biogas Plant'!D96,'Methanol Production Plant'!D113,'DME Plant'!D106) -> 517970587 | D93: kWh/y | E93: Summed electricity inputs only (including the thermal and electric inputs for the biogas plant)
B94: Original production capacity (mW) | C94: 50 | D94: MW | E94: MW to kW = multiply by 1000
B95: Our assumption of operating hours per year | C95: 8765.82 | D95: h/y
B96: Production capacity, scaled to our assumption of kWh/y | C96: =C94*1000*C95 -> 438291000 | D96: kWh/y | E96: At the top of this sheet, they assume production capacity is 8000 h/y, but we're assuming it's the full capacity of a year, so 8765.82 h/y, assuming the average year of 365.25 days, accounting for gap years.
B97: Scaling factor | C97: =C96/C93 -> 0.84616967 | D97: none
B99: Energy Balances - SCALED | C99: Normalization factor | D99: 320 | E99: Scaling factor | F99: =C97 -> 0.84616967
B101: Utility type | C101: Input - TJ/y | D101: Input - kt/y | E101: Output - TJ/y | F101: Output - kt/y | G101: Net - TJ/y | H101: Net - kt/y | I101: Remark
B102: Low pressure steam | C102: =C84*$F$99 -> 0 | D102: =D84*$F$99 -> 0 | E102: =E84*$F$99 -> -611.13758 | F102: =F84*$F$99 -> -270.77429 | G102: =C102+E102 -> -611.13758 | H102: =D102+F102 -> -270.77429 | I102: Net Generation
B103: Mid pressure steam | C103: =C85*$F$99 -> 0 | D103: =D85*$F$99 -> 0 | E103: =E85*$F$99 -> -511.76342 | F103: =F85*$F$99 -> -270.77429 | G103: =C103+E103 -> -511.76342 | H103: =D103+F103 -> -270.77429 | I103: Net Generation
B104: High pressure steam | C104: =C86*$F$99 -> 0 | D104: =D86*$F$99 -> 0 | E104: =E86*$F$99 -> -444.06984 | F104: =F86*$F$99 -> -270.77429 | G104: =C104+E104 -> -444.06984 | H104: =D104+F104 -> -270.77429 | I104: Net Generation
B105: Cooling water | C105: =C87*$F$99 -> 940.53459 | D105: =D87*$F$99 -> 15027.296 | E105: =E87*$F$99 -> 0 | F105: =F87*$F$99 -> 0 | G105: =C105+E105 -> 940.53459 | H105: =D105+F105 -> 15027.296
B106: Fired Heat | C106: =C88*$F$99 -> 599.12546 | D106: NA | E106: =E88*$F$99 -> 0 | F106: NA | G106: =C106+E106 -> 599.12546 | H106: NA
B107: Electricity | C107: =C89*$F$99 -> 1190.6473 | D107: =D89*$F$99 -> 41341.904 | E107: =E89*$F$99 -> -2417.5254 | F107: =F89*$F$99 -> -83941.893 | G107: =C107+E107 -> -1226.8781 | H107: =D107+F107 -> -42599.989 | I107: Net Generation, kt/y is kW
B108: *NA- Not Applicable | G108: =SUM(G102:G107) -> -1254.1888 | H108: =SUM(H102:H107) -> -28385.015
B109: Electricity (kWh/y) | D109: =D107*C95 -> 3.6239569e+08 | F109: =F107*C95 -> -735819522
B111: Total energy | C111: =SUM(C102:C107) -> 2730.3073 | E111: =SUM(E102:E107) -> -3984.4962
B113: Disclaimer
B114: This process datasheet is part of the "Unravelling the impacts of using alternative raw materials in industrial clusters"
B115: Project Leader: Prof. dr. ir. Andrea Ramirez Ramirez. Energy & Industry, Faculty of Technology, Policy and Management, Delft University of Technology, The Netherlands.
B116: The affiliation of the process modelers and reviewers is: Energy & Industry, Faculty of Technology, Policy and Management, Delft University of Technology, The Netherlands.
B118: No. | C118: References
B119: [1] | C119: U.S. Technology Assessment Office, Industrial and Commercial Cogeneration, U.S. Government Printing Office, 1984, pp. 117–67.
B120: [2] | C120: L. Thierry, J.F. Ferrería de laFuente, F. Neuwahl, M. Canova, A. Pinasseau, I. Jankov, T. Brinkmann, S. Roudier, L.D. Sancho, BAT Reference Document for Large Combustion Plants, 2016.
B121: [3] | C121: A. Kaya, M.A. Keyes, Energy Convers. Manag. 33(4) (1992) 225–33. 10.1016/0196-8904(92)90112-A.
B122: [4] | C122: S. Green, PEI Power Eng. Int. (2000) 28. 10.1533/9780857096180.1.
B123: [5] | C123: A. Gunschera, Interactive Gas Turbine Portfolio Brochure - web version (February 2019), 2019.
B124: [6] | C124: Combined heat and power plant Alco Bio Fuel | Waterleau. Available at: https://www.waterleau.com/en/references/combined-heat-and-power-plant-alco-bio-fuel-1. Accessed March 9, 2021.
B125: [7] | C125: SGT-800 | Industrial Gas Turbine | Gas Turbines | Manufacturer | Siemens Energy Global. Available at: https://www.siemens-energy.com/global/en/offerings/power-generation/gas-turbines/sgt-800.html. Accessed March 24, 2021.
B126: [8] | C126: R. Kurz, C. Meher-Homji, B. Fellow, K. Brun, 43rd Turbomachinery & 30th Pump Users Symposia , 2014, pp.1-36.
B127: [9] | C127: Gas Turbine Combined Cycle - an overview | ScienceDirect Topics. Available at: https://www.sciencedirect.com/topics/engineering/gas-turbine-combined-cycle. Accessed March 24, 2021.
B128: [10] | C128: What is the Air Fuel Ratio Effect on Combustion Efficiency? Available at: https://sagemetering.com/combustion-efficiency/air-fuel-ratio-effect-on-combustion-efficiency/. Accessed March 8, 2021.
B129: [11] | C129: How Gas Turbine Power Plants Work | Department of Energy. Available at: https://www.energy.gov/fe/how-gas-turbine-power-plants-work. Accessed March 24, 2021.
... B151: [33] | C151: I. Dincer,, Y. Bicer, Integrated Energy Systems for Multigeneration, Elsevier, 2020, pp. 85–142.

Sheet Olefins Production Plant
B3: LOW OLEFINS PRODUCTION
B4: Process datasheet (Mass & Energy Balance)
B6: Production capacity | D6: Ethylene 876 kt/y, propylene 404 kt/y, acetylene 17 kt/y, butene 93 kt/y, butadiene 116 kt/y
B7: Operating hours per year | D7: 8000
B9: Overall Process Description
B10: The lower olefins are the primary feedstock for most plastics, polymers and chemicals and they comprise mainly ethylene, propylene, acetylene, butene and butadiene [1]. Steam cracking is currently the most commonly applied technology for the production of lower olefins. Steam cracking involves the high temperature pyrolysis (or cracking) of mainly saturated hydrocarbons in the presence of steam [1, 2]. The range of saturated hydrocarbons that can be used as feedstock for steam cracking is potentially wide. From the different feedstock alternatives, naphtha from crude oil refining is far the most important feedstock [1]. Hence, in this datasheet a model for steam cracking of naphtha feedstock is presented. During the steam cracking of naphtha, a wide range of lower hydrocarbons are produced mainly hydrogen, methane, ethylene, ethane, acetylene, propylene, propane, butene, butadiene, benzene, other non-aromatics and other aromatics [1, 3]. Thus, after steam cracking, the hydrocarbon mixture goes to the downstream purification section to separate the individual components. The downstream purification step consists of primary fractionation, gas clean-up, demethanizer, deethanize , acetylene extraction, C2-C2 splitter, depropanizer, C3-C3 splitter, debutanizer, butadiene extraction and aromatic extraction [1,2].
B18: Process Diagram description
B19: Naphtha feed at storage conditions is first pumped (O1-P1) and preheated (O1-E1) to 5 bar and 350 °C and is then mixed with superheated steam, at a steam to naphtha ratio of 0.5 (mass basis) [2]. The mixture is then heated to 500 °C and it enters the cracker furnace (O1-R1) operating at about 850 °C to ensure cracking of naphtha to lower olefins. The reaction being highly endothermic requires heat, which is supplied by burning off-gases produced within the olefin plant. The hot flue-gas from the furnace is used to preheat the feed and produce steam required for the process [2]. The hot olefin mixture from the furnace has an outlet pressure of 5 bar [3] and it is cooled to about 250 °C [1] (producing steam) before entering the quench tower. In the quench tower (O1-T1), the gas mixture is cooled down using recirculating quench liquid [1]. The mixture is then sent to a primary distillation tower (O1-T2) to remove heavy C9+ compounds like napthalene. The cooled olefin mixture is then compressed to about 30 bar using multistage compressor in order to facilitate the subsequent separation of different olefins [1]. During the compression, some of the BTX compounds get liquefied and are collected in a knock-out drum and sent to the benzene section for further processing [1]. As the cracked gas contains some CO and H2S [1], the gas has to be cleaned in order to prevent downstream processing problems like plugging and catalyst poisoning. Hence, a caustic scrubber (O1-T3) is typically used to remove unwanted gases. The scrubbing reactions are as follows: 2 NaOH + H2S → Na2S + 2 H2O CO + NaOH → HCO2Na (Sodium formate) During the scrubbing process some heavy components like benzene, toluene, p-xylene and styrene get removed from the gas and are recovered through phase separators, and then sent to the BTX section for further processing. The gas is then dried with a molecular sieve (O1-SP3) to remove any traces of water and it is sent to the downstream product separation section [2]. The downstream product separation section consists mainly of demethanizer, deethanizer, acetylene extraction, depropanizer, C3-C3 splitter, debutanizer, butadiene extraction and benzene extraction. In this section, the dried gas from the molecular sieve is first cooled in a cryogenic cooler (O1-E7) to -50 °C [2] and then fed to the demethanizer (O1-T4) operating at 30 bar [3]. In the demethanizer, methane and all the components lighter than methane are separated from the top. The gases from the demethanizer overhead are used for cryogenic cooling within the system and expanded to atmospheric conditions before being used as fuel gas in the system. The bottom stream enters the deethanizer column (O1-T5) operating at 25 bar [3] in which ethane and lighter components are removed from top. The deethanizer overhead contains mainly ethane, ethylene and acetylene and it is sent to the acetylene extraction section [2]. The bottom of the deethanizer is sent to the depropanizer (O1-T6) column operating at 20 bar [3]. In the depropanizer, propane and lighter components are removed from the top. The overhead contains mainly propylene and propane with methyl acetylene as impurity. This overhead C3 stream is sent to a hydrogenation reactor (O1-R2) to selectively hydrogenate methyl acetylene to propylene [3, 6]. The reaction is as follows: Methyl acetylene + H2 → Propylene From the reactor, the product stream goes to a C3-C3 splitter or propylene-propane splitter (O1-T7) working at 16 bar in which propylene product is obtained at the top and propane at the bottom [2]. The propylene product can be used to produce chemicals like propylene oxide and polypropylene. The bottom of the depropanizer is sent to the debutanizer column (O1-T8) operating at 15 bar. In the debutanizer, C4 components are removed from top and the bottom product is called pyrolysis gasoline or pygas. The overhead mixture from deethanizer column is sent to the acetylene extraction section in which acetylene is separated from ethylene using N-N-Dimethylformamide (DMF) [7]. In the acetylene extraction section, acetylene and ethane are selectively extracted at about 20 bar using DMF in O1-T9. This mixture is then sent to a stripper (O1-T10) operating at 1.02 bar with additional DMF fed to it. This column mainly removes dissolved ethane as top product, which can be used as fuel gas for furnace outside the system, and recovers acetylene at as bottom product. The bottom product is sent to the solvent regeneration column (O1-T11) to get acetylene product from the top and the regenerated solvent is recycled back [7]. The acetylene can be used for the production of vinyl esters and ethylene for a number of chemicals like ethylbenzene, ethylene dichloride and ethylene oxide [2]. The overhead of debutanizer mainly contains a mixture of butane, butene and butadiene. As butadiene forms an azeotrope with butane , extractive distillation with N-methylpyrrolidone (NMP) solvent is used for separation. A two stage extraction technique is used to separate the mixture. In the first column (O1-T15), the butene rich stream is separated from butadiene. The extract is sent to a rectification column (O1-T16) to recover the solvent. After rectification, in the third column or after washer (O1-T17) butadiene is separated from vinyl acetylene impurity [8, 9]. The vinyl acetate is recovered from solvent in O1-T18 and solvent is recycled back. The NMP solvent used contains 10% water to increase the selectivity of solvent and the solvent recovered are recycled back to the column with 10% water by adding make-up water [8]. The butadiene (BDI) product is sent to a decanter to remove excess water and pure BDI with 99 wt.% purity is obtained [8]. The butadiene produced can be used for Nylon 6,6 production and the butene can be used for isoprene production. The pygas recovered at the bottom of the debutanizer contains a mixture rich in BTX (Benzene, Toluene, Xylene) and it is blended with import pygas and heart-cut reformate. The resulting BTX mixture is first prefractionated in O1-T12 to remove as bottom product C7+ components which are known as pygas tail. The top product contains mainly C6 components and this mixture undergoes extractive distillation in O1-T13 with N-formylmorpholine (NFM) solvent. The non-aromatics stream is obtained as overhead raffinate and it is send to refinery for further usage. The benzene rich solvent is sent to a stripper column (O1-T14) operating at vacuum conditions to obtain pure benzene and the solvent is recycled back [13]. Overall, the main by-products of the process are: effluent water, flue-gas and off-gas. The main products of the process are: Ethylene, Propylene, Acetylene, Butene, Butadiene, Benzene and debenzenised pygas (pygas tail).
K36: LEGENDS
K37: FS- Feedstock/Raw material
K38: PS- Product
K39: WS-Waste
F72: Figure 1. Process Flow Diagram- Lower Olefins Production
B76: Mass Balances
B79: Raw materials | H79: Products | O79: Balance check
B80: Stream | C80: Composition (% mass) | D80: Flow kt/y | E80: Temperature ( °C ) | F80: Pressure (bar) | H80: Stream | I80: Composition (% mass) | J80: Flow kt/y | K80: Temperature ( °C ) | L80: Pressure (bar) | O80: Total inputs/outputs
B81: Naphtha | C81: ASTM D86 (IBP=26 C, FBP=183 C) | D81: 3000 | E81: 40 | F81: 1.02 | H81: Ethylene | I81: 99.99% Ethylene, 0.01% ethane | J81: 876.1176 | K81: -27 | L81: 20 | O81: Raw materials (FS) | P81: =SUM(D81:D92) -> 28767.139
B82: Steam | C82: 100% water | D82: 1500 | E82: 156 | F82: 5.5 | H82: Propylene | I82: 99.95% Propylene, 0.04% ethane, 0.01% propane | J82: 493.8954 | K82: 38 | L82: 16 | O82: Products (PS) | P82: =SUM(J81:J88) -> 2783.3348
B83: Combustion air | C83: 23% O2, 77% N2 | D83: 23311.12 | E83: 15 | F83: 1.02 | H83: Acetylene | I83: 99.62% acetylene, 0.02% propylene, 0.36% DMF | J83: 17.06651 | K83: 4 | L83: 1.02 | O83: Waste Streams (WS) | P83: =SUM(J94:J101) -> 25983.748
B84: NaOH | C84: 50% water, 50% NaOH | D84: 17.53785 | E84: 40 | F84: 1.02 | H84: Butene mixture | I84: 92% butene, 5% butane, 2.8% BDI, 0.2% water | J84: 92.55048 | K84: 30 | L84: 3
B85: Dilution water | C85: 100% water | D85: 146.5753 | E85: 15 | F85: 1.02 | H85: Butadiene | I85: 99.07% BDI, 0.71% butene, 0.11% water, 0.09% vinyl acetylene, 0.02% NMP | J85: 116.3208 | K85: 42 | L85: 8 | O85: Balance check | P85: =P81-P82-P83 -> 0.0558422
B86: NFM solvent | C86: 100% NFM | D86: 0.0313159 | E86: 15 | F86: 1.02 | H86: C9+ stream | I86: 0.02% H2O, 0.36% ethylene, 0.26% propylene, 2.2% Benzene, 0.11% BDI-13, 0.03% Acetylene, 0.08% Butene, 0.08% Methane, 0.05% ethane, 0.06% methyl acetylene, 12.06% p-xylene, 0.04% propylmercaptan, 60.11% naphthalene, 2.35% toluene, 3.63% ethyl benzene, 0.02% vinyl acetylene, 18.17% styrene, 0.37% cyclopentadiene | J86: 220.5914 | K86: 41 | L86: 2 | O86: Percent error (%) | P86: =(P85/P81)*100 -> 0.00019411802
B87: DMF solvent | C87: 100% DMF | D87: 0.081866 | E87: 15 | F87: 1.02 | H87: Benzene | I87: 99.995% benzene, 0.002% propylmercaptan, 0.001% methyhexane, 0.002% cyclohexane | J87: 672.5194 | K87: 95 | L87: 1.02
B88: Make-up water | C88: 100% water | D88: 1.498871 | E88: 15 | F88: 1.02 | H88: Non aromatic stream | I88: 7.52% benzene, 0.09% BDI-13, 0.06% butene, 6.7% propylene mercaptan, 0.02% vinyl acetylene, 56.45% cyclopentadiene, 27.76% hexane, 1.38% cyclohexane, 0.02% NFM | J88: 294.2732 | K88: 77 | L88: 2
B89: Make-up NMP | C89: 100% NMP | D89: 0.0262123 | E89: 15 | F89: 1.02
B90: H2 gas | C90: 99.87% H2, 0.13% N2 | D90: 1.143171 | E90: 40 | F90: 16
B91: Pygas import | C91: 70% benzene, 15% Cyclopentadiene, 10% Toluene, 5% hexane | D91: 372.2084 | E91: 15 | F91: 1.02
B92: HC Reformate import | C92: 50% benzene, 15% hexane, 10% 2-methyhexane, 10% 3-methyl heptane 5% o-xylene, 5% toluene, 3% ethylbenzene, 1% cyclohexane, 1% Cumene | D92: 416.9161 | E92: 15 | F92: 1.02 | H92: Waste streams
H93: Stream | I93: Concentration (wt %) | J93: Flow kt/y | K93: Temperature ( °C ) | L93: Pressure (bar)
H94: Flue gas | I94: 74.5% N2, 11.35% O2, 6.4% water, 7.74% CO2, 0.01% propyl mercaptan | J94: 23996.62 | K94: 200 | L94: 1.02
H95: Effluent | I95: 79.65% water, 0.62% ethylene, 1.23% propylene, 0.08% benzene, 0.01% acetylene, 0.87% butene, 0.07% butane, 0.05% methane, 0.13% ethane, 0.03% propane, 0.08% methyl acetylene, 4.1% propyl mercaptan, 0.02% toluene, 0.06% vinyl acetylene, 4.01% cyclopentadiene, 5.22% Na2S, 3.77% sodium formate | J95: 113.641 | K95: 40 | L95: 1.02
H96: Dirty water (WS-DW) | I96: 99.81% water, 0.02% ethylene, 0.01% propylene, 0.05% benzene, 0.1% propyl mercaptan, 0.01% cyclopentadiene | J96: 1470.525 | K96: 40 | L96: 2
H97: Water | I97: 100% water | J97: 91.84616 | K97: 6 | L97: 2
H98: Propane rich fuel gas | I98: 98.69% propane, 0.61% propylene, 0.39% BDI-13, 0.31% butene | J98: 10.58474 | K98: 46 | L98: 16
H99: Vinyl acetylene | I99: 94.35% vinyl acetylene, 0.35% water, 4.35% BDI-13, 0.53% butene, 0.42% Cyclopentadiene | J99: 4.957122 | K99: 38 | L99: 3
H100: Waste water | I100: 99.56% water, 0.09% BDI-13, 0.35% NMP | J100: 1.125432 | K100: 42 | L100: 2
H101: C7+ stream/Pygas tail | I101: 1.41% water, 0.3% benzene, 7.08% o-xylene, 2.62% p-xylene, 51.58% toluene, 6.01% ethylbenzene, 1.17% styrene, 0.04% Na2S, 0.03% HCOONA, 14.15% methylhexane, 14.15% methyl heptane, 0.04% cyclohexane, 1.42% cumene | J101: 294.449 | K101: 176 | L101: 5
B112: Energy Balances
B114: Utility type | C114: Input - TJ/y | D114: Input - kt/y | E114: Output - TJ/y | F114: Output - kt/y | G114: Net - TJ/y | H114: Net - kt/y | I114: Remark | K114: Utility process conditions
B115: Low pressure steam | C115: 7780.4913 | D115: 3711 | E115: -2659.2543 | F115: -1268 | G115: 5121.237 | H115: =D115+F115 -> 2443 | K115: Utility type | L115: Inlet temperature ( °C ) | M115: Outlet temperature ( °C ) | N115: Inlet pressure (bar) | O115: Outlet pressure (bar) | P115: Heat capacity/latent heat/lower heating value | Q115: Unit
B116: Mid pressure steam | C116: 6519.8017 | D116: 3469 | E116: -10026.365 | F116: -5334 | G116: -3506.5635 | H116: =D116+F116 -> -1865 | I116: Generation | K116: Low pressure steam | L116: 155 | M116: 155 | N116: 5.5 | O116: 5.5 | P116: 2096.7716 | Q116: KJ/kg
B117: High pressure steam | C117: 0 | D117: 0 | E117: -5972.2457 | F117: -3658 | G117: -5972.2457 | H117: =D117+F117 -> -3658 | I117: Generation | K117: Mid pressure steam | L117: 214 | M117: 214 | N117: 21 | O117: 21 | P117: 1879.6128 | Q117: KJ/kg
B118: Cooling water | C118: 13370.423 | D118: 213148 | E118: 0 | F118: 0 | G118: 13370.423 | H118: =D118+F118 -> 213148 | K118: High pressure steam | L118: 265 | M118: 265 | N118: 51 | O118: 51 | P118: 1632.4494 | Q118: KJ/kg
B119: Electricity | C119: 571 | D119: 19823 | E119: -122.77065 | F119: -4263 | G119: =C119+E119 -> 448.22935 | H119: 15560 | I119: kt/y value is kW | K119: Very High pressure steam | L119: 500 | M119: 311 | N119: 100 | O119: 100 | P119: 1967 | Q119: KJ/kg
B120: Very High pressure steam | C120: 0 | D120: 0 | E120: -1962 | F120: -998 | G120: -1962 | H120: -998 | I120: Generation | K120: Cooling water | L120: 25 | M120: 40 | N120: 1.02 | O120: 1.02 | P120: =62.74243314036/(M120-L120) -> 4.1828289 | Q120: KJ/kg.K
G121: =SUM(G115:G120) -> 7499.0806 | H121: =SUM(H115:H120) -> 224630
B122: Energy Balances - SCALED | C122: Normalization factor | D122: 876 | E122: Scaling factor | F122: 1.51854 | G122: h/y | H122: 8765.82
B124: Utility type | C124: Input - TJ/y | D124: Input - kt/y | E124: Output - TJ/y | F124: Output - kt/y | G124: Net - TJ/y | H124: Net - kt/y | I124: Remark | K124: Utility process conditions
B125: Low pressure steam | C125: =C115*F122 -> 11814.987 | D125: =D115*$F$122 -> 5635.3019 | E125: =E115*$F$122 -> -4038.184 | F125: =F115*$F$122 -> -1925.5087 | G125: =C125+E125 -> 7776.8032 | H125: =D125+F125 -> 3709.7932 | K125: Utility type | L125: Inlet temperature ( °C ) | M125: Outlet temperature ( °C ) | N125: Inlet pressure (bar) | O125: Outlet pressure (bar) | P125: Heat capacity/latent heat/lower heating value | Q125: Unit
B126: Mid pressure steam | C126: =C116*F122 -> 9900.5797 | D126: =D116*$F$122 -> 5267.8153 | E126: =E116*$F$122 -> -15225.437 | F126: =F116*$F$122 -> -8099.8924 | G126: =C126+E126 -> -5324.8569 | H126: =D126+F126 -> -2832.0771 | I126: Generation | K126: Low pressure steam | L126: 155 | M126: 155 | N126: 5.5 | O126: 5.5 | P126: 2096.7716 | Q126: KJ/kg
B127: High pressure steam | C127: =C117*F122 -> 0 | D127: =D117*$F$122 -> 0 | E127: =E117*$F$122 -> -9069.094 | F127: =F117*$F$122 -> -5554.8193 | G127: =C127+E127 -> -9069.094 | H127: =D127+F127 -> -5554.8193 | I127: Generation | K127: Mid pressure steam | L127: 214 | M127: 214 | N127: 21 | O127: 21 | P127: 1879.6128 | Q127: KJ/kg
B128: Cooling water | C128: =C118*F122 -> 20303.523 | D128: =D118*$F$122 -> 323673.76 | E128: =E118*$F$122 -> 0 | F128: =F118*$F$122 -> 0 | G128: =C128+E128 -> 20303.523 | H128: =D128+F128 -> 323673.76 | K128: High pressure steam | L128: 265 | M128: 265 | N128: 51 | O128: 51 | P128: 1632.4494 | Q128: KJ/kg
B129: Electricity | C129: =C119*F122 -> 867.08634 | D129: =D119*$F$122 -> 30102.018 | E129: =E119*$F$122 -> -186.43215 | F129: =F119*$F$122 -> -6473.536 | G129: =C129+E129 -> 680.65419 | H129: =D129+F129 -> 23628.482 | I129: kt/y value is kW | K129: Very High pressure steam | L129: 500 | M129: 311 | N129: 100 | O129: 100 | P129: 1967 | Q129: KJ/kg
B130: Very High pressure steam | C130: =C120*F122 -> 0 | D130: =D120*$F$122 -> 0 | E130: =E120*$F$122 -> -2979.3755 | F130: =F120*$F$122 -> -1515.5029 | G130: =C130+E130 -> -2979.3755 | H130: =D130+F130 -> -1515.5029 | I130: Generation | K130: Cooling water | L130: 25 | M130: 40 | N130: 1.02 | O130: 1.02 | P130: =62.74243314036/(M130-L130) -> 4.1828289 | Q130: KJ/kg.K
G131: =SUM(G125:G130) -> 11387.654 | H131: =SUM(H125:H130) -> 341109.64
C132: =SUM(C125:C130) -> 42886.176 | E132: =SUM(E125:E130) -> -31498.522
B134: Electricity - kWh/y | D134: =D129*H122 -> 2.6386888e+08 | F134: =F129*H122 -> -56745852 | H134: =D134+F134 -> 2.0712302e+08 | I134: kWh/y
B137: Breakdown of requirements
B138: Very Low pressure steam | I138: Electricity
B139: Unit name | C139: Unit description | D139: Duty - MJ/hr | E139: Duty - TJ/y | F139: Mass - ktonne/y | G139: Remark | I139: Unit name | J139: Unit description | K139: Power - KW | L139: Energy- GWh/y | M139: Energy- TJ/y | N139: Remark
B140: - | C140: - | D140: - | E140: - | F140: - | G140: - | I140: ACET-EXT.O1-P3 | J140: ='[1]Inputs and assumptions'!C196 -> #REF! | K140: 85.668654 | L140: =K140*'[1]Inputs and assumptions'!$E$25/1000000 -> #REF! | M140: =L140*60*60/1000 -> #REF! | N140: -
I141: BENZENE.O1-P6 | J141: ='[1]Inputs and assumptions'!C203 -> #REF! | K141: 1.3253342 | L141: =K141*'[1]Inputs and assumptions'!$E$25/1000000 -> #REF! | M141: =L141*60*60/1000 -> #REF! | N141: -
B142: Low pressure steam | I142: BENZENE.O1-P7 | J142: ='[1]Inputs and assumptions'!C205 -> #REF! | K142: 3.7869107 | L142: =K142*'[1]Inputs and assumptions'!$E$25/1000000 -> #REF! | M142: =L142*60*60/1000 -> #REF! | N142: -
B143: Unit name | C143: Unit description | D143: Duty - MJ/hr | E143: Duty - TJ/y | F143: Mass - ktonne/y | G143: Remark | I143: BENZENE.O1-C5 | J143: ='[1]Inputs and assumptions'!C201 -> #REF! | K143: 1398.8563 | L143: =K143*'[1]Inputs and assumptions'!$E$25/1000000 -> #REF! | M143: =L143*60*60/1000 -> #REF! | N143: -
B144: ACET-EXT.O1-T9 | C144: ='[1]Inputs and assumptions'!C188 -> #REF! | D144: 119018.33 | E144: =D144*'[1]Inputs and assumptions'!$E$25/1000000 -> #REF! | F144: 454.10128 | G144: - | I144: SCRUB.O1-P2 | J144: ='[1]Inputs and assumptions'!C155 -> #REF! | K144: 21.484462 | L144: =K144*'[1]Inputs and assumptions'!$E$25/1000000 -> #REF! | M144: =L144*60*60/1000 -> #REF! | N144: -
B145: BENZENE.O1-T13 | C145: ='[1]Inputs and assumptions'!C199 -> #REF! | D145: 199902.47 | E145: =D145*'[1]Inputs and assumptions'!$E$25/1000000 -> #REF! | F145: 762.70573 | I145: SPLITTER.O1-C3 | J145: ='[1]Inputs and assumptions'!C177 -> #REF! | K145: -4262.87 | L145: =K145*'[1]Inputs and assumptions'!$E$25/1000000 -> #REF! | M145: =L145*60*60/1000 -> #REF! | N145: Value taken as negative as it is a turbine
B146: BENZENE.O1-T19 | C146: ='[1]Inputs and assumptions'!C228 -> #REF! | D146: 8991.3405 | E146: =D146*'[1]Inputs and assumptions'!$E$25/1000000 -> #REF! | F146: 34.305464 | I146: O1-P1 | J146: ='[1]Inputs and assumptions'!C141 -> #REF! | K146: 74.187368 | L146: =K146*'[1]Inputs and assumptions'!$E$25/1000000 -> #REF! | M146: =L146*60*60/1000 -> #REF! | N146: -
B147: SPLITTER.O1-E12 | C147: ='[1]Inputs and assumptions'!C182 -> #REF! | D147: 2420.6656 | E147: =D147*'[1]Inputs and assumptions'!$E$25/1000000 -> #REF! | F147: 9.2357815 | I147: O1-P4 | J147: ='[1]Inputs and assumptions'!C163 -> #REF! | K147: 9.3151609 | L147: =K147*'[1]Inputs and assumptions'!$E$25/1000000 -> #REF! | M147: =L147*60*60/1000 -> #REF! | N147: -
B148: SPLITTER.O1-T4 | C148: ='[1]Inputs and assumptions'!C174 -> #REF! | D148: 64358.63 | E148: =D148*'[1]Inputs and assumptions'!$E$25/1000000 -> #REF! | F148: 245.55323 | I148: O1-P5 | J148: ='[1]Inputs and assumptions'!C164 -> #REF! | K148: 10.876842 | L148: =K148*'[1]Inputs and assumptions'!$E$25/1000000 -> #REF! | M148: =L148*60*60/1000 -> #REF! | N148: -
B149: SPLITTER.O1-T5 | C149: ='[1]Inputs and assumptions'!C183 -> #REF! | D149: 85875.541 | E149: =D149*'[1]Inputs and assumptions'!$E$25/1000000 -> #REF! | F149: 327.64862 | I149: O1-C2 | J149: ='[1]Inputs and assumptions'!C158 -> #REF! | K149: 10431.36 | L149: =K149*'[1]Inputs and assumptions'!$E$25/1000000 -> #REF! | M149: =L149*60*60/1000 -> #REF! | N149: -
B150: SPLITTER.O1-T6 | C150: ='[1]Inputs and assumptions'!C184 -> #REF! | D150: 48438.782 | E150: =D150*'[1]Inputs and assumptions'!$E$25/1000000 -> #REF! | F150: 184.81281 | I150: O1-C1 | J150: ='[1]Inputs and assumptions'!C153 -> #REF! | K150: 7385.7851 | L150: =K150*'[1]Inputs and assumptions'!$E$25/1000000 -> #REF! | M150: =L150*60*60/1000 -> #REF! | N150: -
B151: SPLITTER.O1-T7 | C151: ='[1]Inputs and assumptions'!C186 -> #REF! | D151: 374004.19 | E151: =D151*'[1]Inputs and assumptions'!$E$25/1000000 -> #REF! | F151: 1426.9716 | I151: O1-P8 | J151: ='[1]Inputs and assumptions'!C211 -> #REF! | K151: 8.6875115 | L151: =K151*'[1]Inputs and assumptions'!$E$25/1000000 -> #REF! | M151: =L151*60*60/1000 -> #REF! | N151: -
B152: O1-E18 | C152: ='[1]Inputs and assumptions'!C173 -> #REF! | D152: -332406.78 | E152: =D152*'[1]Inputs and assumptions'!$E$25/1000000 -> #REF! | F152: -1268.2613 | I152: O1-P9 | J152: ='[1]Inputs and assumptions'!C217 -> #REF! | K152: 0.035371928 | L152: =K152*'[1]Inputs and assumptions'!$E$25/1000000 -> #REF! | M152: =L152*60*60/1000 -> #REF! | N152: -
B153: O1-T15 | C153: ='[1]Inputs and assumptions'!C206 -> #REF! | D153: 69551.454 | E153: =D153*'[1]Inputs and assumptions'!$E$25/1000000 -> #REF! | F153: 265.52247 | I153: O1-C4 | J153: ='[1]Inputs and assumptions'!C210 -> #REF! | K153: 391.58382 | L153: =K153*'[1]Inputs and assumptions'!$E$25/1000000 -> #REF! | M153: =L153*60*60/1000 -> #REF! | N153: -
K154: =SUM(K140:K153) -> 15560.083 | M154: =SUM(M140:M153) -> #REF!
I155: Cooling water
B156: Mid pressure steam | I156: Unit name | J156: Unit description | K156: Duty - MJ/hr | L156: Duty - TJ/y | M156: Mass - ktonne/y | N156: Remark
B157: Unit name | C157: Unit description | D157: Duty - MJ/hr | E157: Duty - TJ/y | F157: Mass - ktonne/y | G157: Remark | I157: BENZENE.O1-T12 | J157: ='[1]Inputs and assumptions'!C198 -> #REF! | K157: 460121.84 | L157: =K157*'[1]Inputs and assumptions'!$E$25/1000000 -> #REF! | M157: 58668.026 | N157: -
B158: ACET-EXT.O1-T11 | C158: ='[1]Inputs and assumptions'!C190 -> #REF! | D158: 34228.023 | E158: =D158*'[1]Inputs and assumptions'!$E$25/1000000 -> #REF! | F158: 145.68117 | G158: - | I158: BENZENE.O1-T13 | J158: ='[1]Inputs and assumptions'!C199 -> #REF! | K158: 223108.94 | L158: =K158*'[1]Inputs and assumptions'!$E$25/1000000 -> #REF! | M158: 28447.598 | N158: -
B159: BENZENE.O1-T12 | C159: ='[1]Inputs and assumptions'!C198 -> #REF! | D159: 526739.98 | E159: =D159*'[1]Inputs and assumptions'!$E$25/1000000 -> #REF! | F159: 2241.9084 | G159: - | I159: BENZENE.O1-T14 | J159: ='[1]Inputs and assumptions'!C200 -> #REF! | K159: 4546.7209 | L159: =K159*'[1]Inputs and assumptions'!$E$25/1000000 -> #REF! | M159: 579.73153 | N159: -
B160: BENZENE.O1-T14 | C160: ='[1]Inputs and assumptions'!C200 -> #REF! | D160: 37172.001 | E160: =D160*'[1]Inputs and assumptions'!$E$25/1000000 -> #REF! | F160: 158.21131 | G160: - | I160: SCRUB.O1-E23 | J160: ='[1]Inputs and assumptions'!C225 -> #REF! | K160: 825.16678 | L160: =K160*'[1]Inputs and assumptions'!$E$25/1000000 -> #REF! | M160: 105.21323 | N160: -
B161: SPLITTER.O1-T8 | C161: ='[1]Inputs and assumptions'!C187 -> #REF! | D161: 17563.825 | E161: =D161*'[1]Inputs and assumptions'!$E$25/1000000 -> #REF! | F161: 74.755079 | G161: - | I161: O1-T6 | J161: ='[1]Inputs and assumptions'!C184 -> #REF! | K161: 30410.564 | L161: =K161*'[1]Inputs and assumptions'!$E$25/1000000 -> #REF! | M161: 3877.5116 | N161: -
B162: O1-E4 | C162: ='[1]Inputs and assumptions'!C147 -> #REF! | D162: -206709.14 | E162: =D162*'[1]Inputs and assumptions'!$E$25/1000000 -> #REF! | F162: -879.79454 | G162: - | I162: O1-T8 | J162: ='[1]Inputs and assumptions'!C187 -> #REF! | K162: 10922.883 | L162: =K162*'[1]Inputs and assumptions'!$E$25/1000000 -> #REF! | M162: 1392.7267 | N162: -
B163: O1-E17 | C163: ='[1]Inputs and assumptions'!C172 -> #REF! | D163: -1046586.5 | E163: =D163*'[1]Inputs and assumptions'!$E$25/1000000 -> #REF! | F163: -4454.477 | G163: - | I163: O1-E5 | J163: ='[1]Inputs and assumptions'!C149 -> #REF! | K163: 137562.53 | L163: =K163*'[1]Inputs and assumptions'!$E$25/1000000 -> #REF! | M163: 17539.967 | N163: -
B164: O1-T16 | C164: ='[1]Inputs and assumptions'!C209 -> #REF! | D164: 140495.77 | E164: =D164*'[1]Inputs and assumptions'!$E$25/1000000 -> #REF! | F164: 598.5321 | G164: - | I164: O1-E22 | J164: ='[1]Inputs and assumptions'!C221 -> #REF! | K164: 26236.472 | L164: =K164*'[1]Inputs and assumptions'!$E$25/1000000 -> #REF! | M164: 3345.2922 | N164: -
B165: O1-T17 | C165: ='[1]Inputs and assumptions'!C212 -> #REF! | D165: 53721.639 | E165: =D165*'[1]Inputs and assumptions'!$E$25/1000000 -> #REF! | F165: 228.86187 | G165: - | I165: O1-T2 | J165: ='[1]Inputs and assumptions'!C151 -> #REF! | K165: 558923.32 | L165: =K165*'[1]Inputs and assumptions'!$E$25/1000000 -> #REF! | M165: 71265.75 | N165: -
B166: O1-T18 | C166: ='[1]Inputs and assumptions'!C213 -> #REF! | D166: 5053.9771 | E166: =D166*'[1]Inputs and assumptions'!$E$25/1000000 -> #REF! | F166: 21.530666 | G166: - | I166: O1-C1 | J166: ='[1]Inputs and assumptions'!C153 -> #REF! | K166: 67650.475 | L166: =K166*'[1]Inputs and assumptions'!$E$25/1000000 -> #REF! | M166: 8625.8018 | N166: -
I167: O1-E20 | J167: ='[1]Inputs and assumptions'!C214 -> #REF! | K167: 6054.5605 | L167: =K167*'[1]Inputs and assumptions'!$E$25/1000000 -> #REF! | M167: 773.88748 | N167: -
B168: High pressure steam | I168: O1-T16 | J168: ='[1]Inputs and assumptions'!C209 -> #REF! | K168: 94708.966 | L168: =K168*'[1]Inputs and assumptions'!$E$25/1000000 -> #REF! | M168: 12105.599 | N168: -
B169: Unit name | C169: Unit description | D169: Duty - MJ/hr | E169: Duty - TJ/y | F169: Mass - ktonne/y | G169: Remark | I169: O1-T17 | J169: ='[1]Inputs and assumptions'!C212 -> #REF! | K169: 41408.445 | L169: =K169*'[1]Inputs and assumptions'!$E$25/1000000 -> #REF! | M169: 5292.7834 | N169: -
B170: O1-E3 | C170: ='[1]Inputs and assumptions'!C146 -> #REF! | D170: -746530.71 | E170: =D170*'[1]Inputs and assumptions'!$E$25/10^6 -> #REF! | F170: -3658.4568 | G170: - | I170: O1-T18 | J170: ='[1]Inputs and assumptions'!C213 -> #REF! | K170: 8822.0545 | L170: =K170*'[1]Inputs and assumptions'!$E$25/1000000 -> #REF! | M170: 1127.6256 | N170: -
B172: Very High pressure steam | I172: Refrigerant-1
B173: Unit name | C173: Unit description | D173: Duty - MJ/hr | E173: Duty - TJ/y | F173: Mass - ktonne/y | G173: Remark | I173: Unit name | J173: Unit description | K173: Duty - MJ/hr | L173: Duty - TJ/y | M173: Mass - ktonne/y | N173: Remark
B174: O1-E16 | C174: ='[1]Inputs and assumptions'!C171 -> #REF! | D174: -245273.72 | E174: =D174*'[1]Inputs and assumptions'!$E$25/10^6 -> #REF! | F174: -997.69987 | G174: - | I174: SPLITTER.O1-T4 | J174: ='[1]Inputs and assumptions'!C174 -> #REF! | K174: 48526.698 | L174: =K174*'[1]Inputs and assumptions'!$E$25/1000000 -> #REF! | M174: 741.03058 | N174: -
I176: Refrigerant-2
I177: Unit name | J177: Unit description | K177: Duty - MJ/hr | L177: Duty - TJ/y | M177: Mass - ktonne/y | N177: Remark
I178: ACET-EXT.O1-T9 | J178: ='[1]Inputs and assumptions'!C188 -> #REF! | K178: 117457.01 | L178: =K178*'[1]Inputs and assumptions'!$E$25/1000000 -> #REF! | M178: 1928.5997 | N178: -
I179: ACET-EXT.O1-T10 | J179: ='[1]Inputs and assumptions'!C189 -> #REF! | K179: 177717.42 | L179: =K179*'[1]Inputs and assumptions'!$E$25/1000000 -> #REF! | M179: 2918.053 | N179: -
I180: HS-13 | J180: Heat stream | K180: =(4132344/1000)*4.184*3600/1000 -> 62243.018 | L180: =K180*'[1]Inputs and assumptions'!$E$25/1000000 -> #REF! | M180: =1000*L180/(-N118) -> #REF! | N180: The heat stream is manually provided to get the required temperature. Hence the mass flow is manually calculated
I184: Refrigerant-3
...

Sheet Aromatics Production Plant
B3: AROMATICS PLANT
B4: Process datasheet (Mass & Energy Balance)
B6: Production capacity | D6: Benzene 892 kt/y, o-xylene production 186 kt/y, p-xylene 754 kt/y
B7: Operating hours per year | D7: 8000 h/y
B9: Overall Process Description
B10: Aromatics are a category of compounds based on benzene rings at their cores. Aromatics plants produce chemicals like benzene, toluene, xylenes, ethylbenzene, cyclohexane, styrene, nitrobenzene (with some exceptions, like furans). The primary source of aromatics is the crude from the catalytic reforming process, also called reformate, which is used after the lighter (C4-C5) compounds have been removed. Another source of aromatics is the naphtha obtained as an outcome of the steam cracking process, called pyrolysis gas or pygas. The pygas obtained from crackers has a higher content of sulphur compounds compared to the reformate [2]. Thus, a desulphurization step is required as a pre-treatment to avoid catalyst poisoning. Moreover, a hydrofining process is required to hydrogenate (di)olefins and unsaturated aromatics from the pygas and reformate [6]. Overall, the pre-treatment section comprises pre-distillation to remove heavy compounds (C9+), and hydrogenation and stabilizing sections to remove sulphur compounds [6]. After the pre-treatment, the gas mix goes to a sulfolane extraction unit (SEU) to separate the aromatics from the non-aromatics using extractive distillation, since a normal distillation will not be efficient to separate these close boiling compounds. The distillate product contains light component and non-aromatics (like methylheptane) and some sulfolane and thus, it is sent to water stripping to recover the remaining solvent and non-aromatics. On the other hand, the bottom product from the extraction column is sent to a solvent regeneration column, where pure sulfolane is recovered and used back in the extraction process. The concentrated BTX (Benzene, toluene and xylenes) is now sent to clay pre-treatment to remove the remaining olefins and light compounds, and is further sent to the fractionation section [6]. In the fractionation section, each individual aromatic component is subsequently separated in a distillation column- starting with benzene, followed by toluene and finally in the third column the xylenes are recovered. The further the toluene disproportionation to produce benzene and xylenes (selectively para-xylene) is addressed, as well as the isomerization of meta-xylene to produce ortho- and para-xylenes. Para- and Ortho- xylenes are the end products of the Xylene separation unit.
B18: Process Diagram description
B19: The aromatics plant consists of several sections including pre-distillation, hydrogenation, desulfurization, BTX extraction using sulfonale as solvent, clay treatment, BTX fractionation into benzene, toluene and xylenes. These sections are followed by toluene disproportionation into benzene and xylenes and finally the xylenes cryztallization, isomerization and separation section. All of these processes take place over a wide range of temperature and pressures. For instance, it goes from pre-distillation in vacuum (0.2-1.02 bar) to toluene disproportionation at high pressures (30 bar), from xylenes isomerization at high temperatures (400˚C) to crystallization using refrigerants (-15˚C). Pre-distillation section: The reformate and pygas enter the process at 25˚C and 1,02 bar and are mixed with the C7+ fraction to be pre-treated together (feed conditioning process). For this, the mixed feed is first heated to 116˚ C and then sent to an atmospheric pre-distillation step to remove the C9+ components like 1,2,4-Trimethylbenzene and dicyclopentadiene. A second distillation column operating under vacuum (0 .2 bar) is used to avoid the polymerization reactions and improve the separation of the C9+ components from the aromatic mix [6]. Hydrotreating section: The mixture free of C9+ components is subsequently hydrogenated, in which the diolefins and unsaturated aromatics (isoprene, styrene, butadiene, etc.) are treated with hydrogen to create saturated hydrocarbons. A trickle bed reactor with nickel or palladium-based catalysts working at 400˚ C and 26 bar is used for the hydrogenation process [6], [8]. Part of the reactor effluent is recycled back to the hydrotreating step to keep the reactor temperature down. The recycled stream is cooled down to 120 ˚C and mixed with the main feed and fresh hydrogen before entering the hydrotreating reactor. The reactor system is normally designed for a ratio of recycled to fresh feed of between 2:1 and 3:1 [6]. The remaining part of the effluent, is sent to the second hydrogenation step. The feed to the second reactor is mixed with recycled hydrogen and raised to the required feed temperature of 275 ˚C. In this step, the sulphur compounds are reduced mainly to H2S over cobalt/molybdenum catalyst [6]. This unit also reduces the olefins to paraffins over nickel/molybdenum catalyst. The reactor effluent is cooled down through heat transfer with the reactor’s inlet flow, and is sent to a hot vapour-liquid separator drum. The vapour from this drum is further cooled down to -36˚ C and sent to a cold vapour-liquid separator drum from which the gas consisting of hydrogen and lighter hydrocarbons is sent to the compressor and recycled and mixed with the 2nd reactor feed [6], [8], [9]. A recycle gas purge is maintained to avoid accumulation of light hydrocarbons in the hydrogen-rich stream. From the vapour-liquid separators, the liquid streams are collected and distilled at ambient conditions to remove H2S, which is recovered as distillate and vented out as raffinate [6]. The bottom stream is sent to extraction section for non-aromatics separation. Sulfonale extraction section: Since the aromatics and non-aromatics have close boiling points, it is not possible to separate them effectively by asimple distillation process. Instead, a 99% sulfolane solvent is used to extract the aromatics and separate the non-aromatics in a single column [10]. The sulfolane extraction unit operates at 2 bar and between 125-180˚C. The distillate from the extraction column goes to a raffinate wash column, where the excess sulfolane solvent is washed down with water and the non-aromatic distillate is vented from the top as a gasoline product [1]. The sulfolane-water stream from the wash column is sent to a decanter, where the remaining non-aromatics are removed from the water and sulfonale[11]. On the other hand, the bottom stream from the sulfonale extraction column is sent to a solvent recovery column operating under vacuum (0,4 bar) to recover the sulfolane solvent and concentrate the aromatics product stream. The solvent-rich stream is mixed with the solvent from the decanter and then pumped back to the extraction column[11]. The concentrated BTX obtained as a distillate from this unit, after been hydrotreated and distilled to remove the dienes and at least 70% of the olefins, it is clay treated to remove the remaining olefins. The clay treating is carried out at a temperature of 100 °C and at a pressure of 7.9 bar [12]. BTX Separation: This distillate, rich in aromatics, is then fractionated in a series of distillation columns to recover Benzene (Purity 99.99%), Toluene and Xylenes at vacuum conditions (0.5-0.8 bar)[6]. Toluene Disproportionation: The toluene obtained from the second column is mixed with hydrogen. The hydrogen-to-toluene ratio is about 1 to 1.5. The mixed stream is heated against reactor effluent and through a process furnace. The heated vapor stream flows to the reactor, which produces the benzene and xylenes (majorly p-xylene, with >96% selectivity) in a disproportionation reaction operated at 400˚C and 30 bar [1], [13]–[15]. The toluene disproportionation reactions are mildly exothermic and thus, the reactor effluent is cooled and sent to a separator, where the hydrogen-rich vapor phase is separated from the liquid stream. A small portion of the vapor phase is purged to control recycle hydrogen purity. The recycled hydrogen is then compressed, mixed with makeup hydrogen and returned to the reactor [14], [15]. About 50% Toluene is disproportionated to benzene and (mixed) xylenes [6]. The reaction mixture is then recycled back to the beginning of the fractionation to separate out benzene and xylenes. Xylenes Loop: The xylenes mixture from the bottom of the last column of the BTX fractionation section is pumped to the xylenes separation section. In this section, ortho-xylene is recovered in a first column as a bottoms product (mole purity of 99.5%), leaving the meta and para xylenes (along with ethylbenzene) in the distillate[16]. This distillate, is then cooled to 20 ˚C and sent to a crystallizer unit operating at -15 ˚C to separate out para-xylene from the stream [6], [17]. Para-xylene has the highest melting point among the xylenes (13,3˚C, compared to -25,2˚C for o-xylene and -47,9 ˚C for m-xylene) and can be removed from the mixture by crystallization, which has certain advantages over zeolites adsorption process [6][18][19]. A product mass purity of about 99,5% para-xylene is obtained from this separation [18]. The remaining raffinate stream is further sent to a Liquid Isoformer Unit (LIU) in gas phase under hydrogen pressure, where the meta-xylene is converted to ortho- and para-xylenes at >400˚C [1]. In essence, an equilibrium between the compositions of xylenes from before the crystallization unit is obtained in the isoformer unit [6]. As a side reaction of the isoformer, ethylbenzene is converted to benzene and ethane in a hydrogen-rich environment [1]. At least 50% conversion of ethyl benzene in the feed which is isomerized [20]. After the isomerization, the reactor effluent is passed to a separator where the liquid phase comprising benzene and xylenes is separated from the gaseous phase comprising hydrogen, ethane, and some benzene. The gaseous phase withdrawn from separator is cooled, typically about 10 ˚C and 14 bar, and introduced into a series of absorption towers with intermediate cooling to separate the hydrogen [22] and recycle it back to the isoformer, while the benzene and remaining ethane are removed from the rich-xylenes stream by distillation [1]. The benzene is recovered as distillate and is recycled back to the SEU for subsequent benzene recovery [23]. The bottoms stream from the distillation is sent to a deheptanizer to remove the C7+ components from the mixture, and the xylenes-rich stream recovered from this column is recycled back to the xylenes separation section to recover ortho- and para- xylene concentrates[6].
O58: LEGENDS
O59: FS- Feedstock/Raw material
O60: PS- Product
O61: WS-Waste
G97: Figure 1. Process Flow Diagram- Aromatics Production
B99: Mass Balances
B102: Raw materials | I102: Products | P102: Balance check
B103: Stream | C103: Stream Name | D103: Composition (% mass) | E103: Flow kt/y | F103: Temp (˚C) | G103: Pressure (bar) | I103: Stream | J103: Stream Name | K103: Composition (% mass) | L103: Flow kt/y | M103: Temp (˚C) | N103: Pressure (bar) | P103: Total inputs/outputs
B104: Reformate | C104: FS-REFM | D104: Reported below | E104: 1866.2497 | F104: 25 | G104: 1.02 | I104: Benzene product | J104: PS-BENZ | K104: Benzene (99.99%) | L104: 891.73724 | M104: 40 | N104: 1.02 | P104: Raw materials (FS) | Q104: =SUM(E104:E112) -> 4753.8973
B105: Pygas | C105: FS-PYGAS | D105: Reported below | E105: 2220.7035 | F105: 25 | G105: 1.02 | I105: O-xylene product | J105: PS-OXYL | K105: o-xylene (99.54%), m-xylene (0.02%), p-xylene (0.41%), cumene (0.02%) | L105: 185.68273 | M105: 40.1 | N105: 1.02 | P105: Products (PS) | Q105: =SUM(L104:L106) -> 1831.5265
B106: C7+ stream/Pygas tail | C106: FS-C7+ | D106: Benzene (0.2%), Toluene (40.3%), o-Xylene (5.5%), m-Xylene (8.5%), Water (2%), Naphth (3.3%), Styrene (10.6%), EB (6.6%), 2-MEHX (10.9%), 3-MEHP (10.9%), Cumene (1.2%) | E106: 381.5588 | F106: 180.3 | G106: 5 | I106: P-xylene product | J106: PS-PXYL | K106: o-xylene (0.11%), p-xylene (99.78%), EB (0.11%) | L106: 754.10652 | M106: 22.337442 | N106: 1.02 | P106: Waste Streams (WS) | Q106: =SUM(L112:L128) -> 2922.6508
B107: H2 for hydrofining | C107: FS-H2 | D107: H2 (99.87%), N2 (0.13%) | E107: 23.632905 | F107: 30 | G107: 16
B108: H2 for desulphurization | C108: FS-H2IN | D108: H2 (99.87%), N2 (0.13%) | E108: 0.4843956 | F108: 30 | G108: 16 | P108: Balance check | Q108: =Q104-Q105-Q106 -> -0.27991442
B109: H2 for Toluene disproportionation | C109: FS-H2TOL | D109: H2 (99.87%), N2 (0.13%) | E109: 0.17595939 | F109: 30 | G109: 16 | P109: Percent error (%) | Q109: =(Q108/Q104)*100 -> -0.0058881041
B110: H2 for Isoformer unit | C110: FS-HYDRO | D110: H2 (99.87%), N2 (0.13%) | E110: 4.9174463 | F110: 30 | G110: 16 | I110: Waste streams
B111: Water for wash | C111: FS-WAT | D111: Water (100%) | E111: 129.71002 | F111: 15 | G111: 1.02 | I111: Stream | J111: Stream Name | K111: Composition (mass) | L111: Flowrate - ktonne/y | M111: Temp (˚C) | N111: Pressure (bar)
B112: Solvent | C112: FS-SULFO | D112: Sulfonale (99%), Water (1%) | E112: 126.46465 | F112: 40 | G112: 1.02 | I112: Remaining heavy components C9+ | J112: WS-2C9+ | K112: o-xylene (8.87%), m-xylene (0.93%), p-xylene (1.03%), SL (0.73%), NAPH (0.01%), DCYPD (17.81%), EB (0.15%), TMB (61.88%), Cumene (8.58%) | L112: 45.100113 | M112: 40 | N112: 1.02
I113: Heavy components C9+ | J113: WS-C9+ | K113: o-xylene (0.10%), NAPH (23.15%), DCYPD (12.18%), Styrene (0.12%), TMB (64.00%), BZAC (0.34%), Cumene (0.11%) | L113: 605.35449 | M113: 40 | N113: 1.02
I114: Ethane by-product | J114: WS-ETHAN | K114: H2 (0.07%), N2 (0.01%), N-C2A (99.92%) | L114: 47.390966 | M114: -53.888889 | N114: 14
I115: Aromatics removed from Hydrogen | J115: WS-HEAVY | K115: BZ (42.83%), TOL (0.63), o-xylene (2.24%), m-xylene (37.58%), p-xylene (15.21%), EB (1.50%) | L115: 20.197886 | M115: 40 | N115: 1.02
I116: C7 components | J116: WS-HEPT | K116: BZ (5.82%), TOL (18.37), m-xylene (49.88%), p-xylene (23.29%), EB (2.64%) | L116: 30.152652 | M116: 40 | N116: 1.02
I117: Benzene/Hydrogen | J117: WS-OFFG | K117: BZ (92.46%), H2 (7.53%) | L117: 1.8230708 | M117: 40 | N117: 1.02
I118: C1-C5 Hydrocarbons | J118: WS-OFFGA | K118: H2O (0.72%), H2 (0.11%), H2S (0.07%), N-C4A (3.54%), N-C1A (0.03%), I-C5A (81.83%), CYPD (0.03%), N-C5A (11.36%), I-C4A (2.32%) | L118: 1066.3188 | M118: 46.328784 | N118: 2
I119: Hydrogen purge (desulfurization) | J119: WS-PRG | K119: BZ (0.06%), H2O (0.04%), H2 (87.86%), N2 (0.21%), H2S (0.47%), N-C4A (1.56%), N-C1A (2.82%), CYHEX (0.02%), MCP (0.06%), I-C5A (4.88%), N-C5A (0.38%), I-C4A (1.83%) | L119: 12.14104 | M119: -35.770789 | N119: 5
I120: Sulfonale purge | J120: WS-PRG1 | K120: SL (99.13%), H2O (0.87%) | L120: 125.9312 | M120: 40 | N120: 2
I121: Benzene purge | J121: WS-PRG4 | K121: BZ (98.77%), TOL (0.03%), N-C2A (1.20%) | L121: 0.82328502 | M121: 30.000002 | N121: 1.02
I122: Hydrogen purge (isomerization) | J122: WS-PRG5 | K122: H2 (98.52%), N-C2A (1.48%) | L122: 0.0064124144 | M122: 40.270644 | N122: 5
I123: Hydrogen purge (disproportionation) | J123: WS-PRG6 | K123: BZ (4.85%), TOL (3.02%), m-xylene (0.01%), p-xylene (0.47%), H2 (91.57%), N2 (0.07%) | L123: 0.04034801 | M123: 25.703824 | N123: 5
I124: Non-aromatics | J124: WS-RAFF | K124: BZ (0.07%), H2O (14.7%), CYHEX (27.22%), MCP (50.34%), I-C5A (0.04%), DMP (2.52%), MEHX (4.72%), MEHP (0.09%), N-C5A (0.08%), N-C2A (0.23%) | L124: 844.33448 | M124: 40 | N124: 2
... I128: Non-aromatics 2 | J128: WS-NONAR | K128: SL (0.05%), H2O (0.06%) CYHEX (0.17%), MCP (0.28%), DMP (46.23%), MEHX (2.20%), MEHP (50.96%), N-C2A (0.05%) | L128: 80.158428 | M128: 40 | N128: 2
B129: Energy Balances
G130: in | H130: out
B131: Utility type | C131: Input - TJ/y | D131: Input - kt/y | E131: Output - TJ/y | F131: Output - kt/y | G131: Net - TJ/y | H131: Net - kt/y | I131: Remark | K131: Utility process conditions
B132: Very low pressure steam | C132: 7504.0597 | D132: 3514.174 | E132: -7281.2864 | F132: -3409.856 | G132: 222.77335 | H132: =D132+F132 -> 104.31797 | K132: Utility type | L132: Inlet temperature ( °C ) | M132: Outlet temperature ( °C ) | N132: Inlet pressure (bar) | O132: Outlet pressure (bar) | P132: Heat capacity/latent heat/lower heating value | Q132: Unit
B133: Low pressure steam | C133: 5535.4183 | D133: 2556.207 | E133: -1623.104 | F133: -774.552 | G133: 3912.3143 | H133: =D133+F133 -> 1781.655 | K133: Very Low pressure steam | L133: 142.7 | M133: 142.7 | N133: 3.9 | O133: 3.9 | P133: 2135.3671 | Q133: KJ/kg
B134: Mid pressure steam | C134: 14760.128 | D134: 7860.03 | E134: 0 | F134: 0 | G134: 14760.128 | H134: =D134+F134 -> 7860.03 | K134: Low pressure steam | L134: 155 | M134: 155 | N134: 5.5 | O134: 5.5 | P134: 2096.7716 | Q134: KJ/kg
B135: High pressure steam | C135: 5636.928 | D135: 3453.27 | E135: 0 | F135: 0 | G135: =C135 -> 5636.928 | H135: =D135+F135 -> 3453.27 | K135: Mid pressure steam | L135: 214 | M135: 214 | N135: 21 | O135: 21 | P135: 1879.6128 | Q135: KJ/kg
B136: Cooling water | C136: 26185.029 | D136: 418368.16 | E136: 0 | F136: 0 | G136: =C136 -> 26185.029 | H136: =D136+F136 -> 418368.16 | K136: High pressure steam | L136: 265 | M136: 265 | N136: 51 | O136: 51 | P136: 1632.4494 | Q136: KJ/kg
B137: Chilled water | C137: 332.27456 | D137: 34929.46 | E137: 0 | F137: 0 | G137: =C137 -> 332.27456 | H137: =D137+F137 -> 34929.46 | K137: Chilled water | L137: 5 | M137: 7.5 | N137: 1.02 | O137: 1.02 | P137: 0.0094336803 | Q137: MJ/kg
B138: Electricity | C138: 530.63895 | D138: 18424,94 | E138: 0 | F138: 0 | G138: =C138 -> 530.63895 | H138: 18424,94 | I138: kt/y value is kW | K138: Cooling water | L138: 25 | M138: 40 | N138: 1.02 | O138: 1.02 | P138: =62.74243314036/(M138-L138) -> 4.1828289 | Q138: KJ/kg.K
G139: =SUM(G132:G138) -> 51580.086 | H139: =SUM(H132:H138) -> 466496.9
B140: Energy Balances - SCALED | C140: Normalization factor | D140: 891.74 | E140: Scaling factor | F140: 0.264166 | G140: h/y | H140: 8765.82
B142: Utility type | C142: Input - TJ/y | D142: Input - kt/y | E142: Output - TJ/y | F142: Output - kt/y | G142: Net - TJ/y | H142: Net - kt/y | I142: Remark
B143: Very low pressure steam | C143: =C132*$F$140 -> 1982.3174 | D143: =D132*$F$140 -> 928.32528 | E143: =E132*$F$140 -> -1923.4683 | F143: =F132*$F$140 -> -900.76802 | G143: =C143+E143 -> 58.849144 | H143: =D143+F143 -> 27.557262
B144: Low pressure steam | C144: =C133*$F$140 -> 1462.2693 | D144: =D133*$F$140 -> 675.26298 | E144: =E133*$F$140 -> -428.76889 | F144: =F133*$F$140 -> -204.6103 | G144: =C144+E144 -> 1033.5004 | H144: =D144+F144 -> 470.65267
B145: Mid pressure steam | C145: =C134*$F$140 -> 3899.124 | D145: =D134*$F$140 -> 2076.3527 | E145: =E134*$F$140 -> 0 | F145: =F134*$F$140 -> 0 | G145: =C145+E145 -> 3899.124 | H145: =D145+F145 -> 2076.3527
B146: High pressure steam | C146: =C135*$F$140 -> 1489.0847 | D146: =D135*$F$140 -> 912.23652 | E146: =E135*$F$140 -> 0 | F146: =F135*$F$140 -> 0 | G146: =C146+E146 -> 1489.0847 | H146: =D146+F146 -> 912.23652
B147: Cooling water | C147: =C136*$F$140 -> 6917.1944 | D147: =D136*$F$140 -> 110518.64 | E147: =E136*$F$140 -> 0 | F147: =F136*$F$140 -> 0 | G147: =C147+E147 -> 6917.1944 | H147: =D147+F147 -> 110518.64
B148: Chilled water | C148: =C137*$F$140 -> 87.775641 | D148: =D137*$F$140 -> 9227.1757 | E148: =E137*$F$140 -> 0 | F148: =F137*$F$140 -> 0 | G148: =C148+E148 -> 87.775641 | H148: =D148+F148 -> 9227.1757
B149: Electricity | C149: =C138*$F$140 -> 140.17677 | D149: =D138*$F$140 -> 4867.2427 | E149: =E138*$F$140 -> 0 | F149: =F138*$F$140 -> 0 | G149: =C149+E149 -> 140.17677 | H149: =D149+F149 -> 4867.2427 | I149: kt/y value is kW
G150: =SUM(G143:G149) -> 13625.705 | H150: =SUM(H143:H149) -> 128099.86
C151: =SUM(C143:C149) -> 15977.942 | E151: =SUM(E143:E149) -> -2352.2372
D152: =SUM(D147:D148) -> 119745.82
B153: Electricity - kWh/y | D153: =D149*H140 -> 42665373 | F153: =F149*H140 -> 0 | H153: =D153+F153 -> 42665373
B158: Breakdown of requirements
B159: Low pressure steam | I159: Med pressure steam
B160: Unit | C160: Duty MJ/h | D160: Energy - TJ/y | E160: Mass - ktonne/y | F160: Remark | I160: Unit | J160: Duty MJ/h | K160: Energy - TJ/y | L160: Mass - ktonne/y | M160: Remark
B161: A1-E1 | C161: 246811.83 | D161: =C161*8000/1000000 -> 1974.4947 | E161: 999.886 | I161: A1-T1 | J161: 576642 | K161: =J161*8000/1000000 -> 4613.136 | L161: 2456.58
B162: A1-E7 | C162: 2070.6125 | D162: =C162*8000/1000000 -> 16.5649 | E162: 8.12695 | I162: A1-T4 | J162: 336403 | K162: =J162*8000/1000000 -> 2691.224 | L162: 1433.12
B163: A1-E11 | C163: 30705.863 | D163: =C163*8000/1000000 -> 245.64691 | E163: 111.568 | I163: A1-T11 | J163: 931971 | K163: =J163*8000/1000000 -> 7455.768 | L163: 3970.33
B164: A1-E50 | C164: 2191.39 | D164: =C164*8000/1000000 -> 17.53112 | E164: 8.36594
B165: A1-T2 | C165: 20873.784 | D165: =C165*8000/1000000 -> 166.99027 | E165: 77.6901
B166: A1-T10 | C166: 275688.95 | D166: =C166*8000/1000000 -> 2205.5116 | E166: 967.006
B167: A1-T12 | C167: 70062.6 | D167: =C167*8000/1000000 -> 560.5008 | E167: 233.192
B168: A1-T13 | C168: 43522.256 | D168: =C168*8000/1000000 -> 348.17805 | E168: 150.372 | I168: Electricity
B169: A1-E9 | C169: -202888 | D169: =C169*8000/1000000 -> -1623.104 | E169: -774.552 | F169: Generation | I169: Unit | J169: Energy GWh/y | K169: Energy - TJ/y | L169: Usage (kW) | M169: Remark
I170: A1-P3 | J170: 3.23199 | K170: =J170*8000/1000000 -> 0.02585592 | L170: 0.897775
B171: High pressure steam | I171: A1-P4 | J171: 248.766 | K171: =J171*8000/1000000 -> 1.990128 | L171: 69.1016
B172: Unit | C172: Duty MJ/h | D172: Energy - TJ/y | E172: Mass - ktonne/y | F172: Remark | I172: A1-P5 | J172: 287.815 | K172: =J172*8000/1000000 -> 2.30252 | L172: 79.9485
B173: A1-T6 | C173: 325379 | D173: =C173*8000/1000000 -> 2603.032 | E173: 1594.66 | I173: A1-P6 | J173: 0.996658 | K173: =J173*8000/1000000 -> 0.007973264 | L173: 0.276849
B174: A1-R1 | C174: 379237 | D174: =C174*8000/1000000 -> 3033.896 | E174: 1858.61 | I174: A1-P7 | J174: 369.237 | K174: =J174*8000/1000000 -> 2.953896 | L174: 102.566
I175: A1-P8 | J175: 12.5639 | K175: =J175*8000/1000000 -> 0.1005112 | L175: 3.48998
I176: A1-P9 | J176: 129.333 | K176: =J176*8000/1000000 -> 1.034664 | L176: 35.9258
B177: Very high pressure steam | I177: A1-P10 | J177: 238.562 | K177: =J177*8000/1000000 -> 1.908496 | L177: 66.2671
B178: Unit | C178: Duty MJ/h | D178: Energy - TJ/y | E178: Mass - ktonne/y | F178: Remark | I178: A1-P11 | J178: 96.294 | K178: =J178*8000/1000000 -> 0.770352 | L178: 26.7483
B179: A1-E26 | C179: 76106.9 | D179: =C179*8000/1000000 -> 608.8552 | E179: 309.594 | I179: A1-P12 | J179: 1.69414 | K179: =J179*8000/1000000 -> 0.01355312 | L179: 0.470593
B180: A1-E35 | C180: 29832.6 | D180: =C180*8000/1000000 -> 238.6608 | E180: 121.355 | I180: A1-P13 | J180: 10.5609 | K180: =J180*8000/1000000 -> 0.0844872 | L180: 2.93359
B181: A1-R3 | C181: 80387.3 | D181: =C181*8000/1000000 -> 643.0984 | E181: 327.006 | I181: A1-P14 | J181: 3.70516 | K181: =J181*8000/1000000 -> 0.02964128 | L181: 1.02921
I182: A1-P15 | J182: 2.72733 | K182: =J182*8000/1000000 -> 0.02181864 | L182: 0.757591
I183: A1-C1 | J183: 2646.34 | K183: =J183*8000/1000000 -> 21.17072 | L183: 735.095
I184: A1-C2 | J184: 1115.94 | K184: =J184*8000/1000000 -> 8.92752 | L184: 309.983
B185: Cooling water | I185: A1-C3 | J185: 24.9705 | K185: =J185*8000/1000000 -> 0.199764 | L185: 6.93626
B186: Unit | C186: Duty MJ/h | D186: Energy - TJ/y | E186: Mass - ktonne/y | F186: Remark | I186: A1-C4 | J186: 136.649 | K186: =J186*8000/1000000 -> 1.093192 | L186: 37.9581
B187: A1-E3 | C187: 382673 | D187: =C187*8000/1000000 -> 3061.384 | E187: 48912.8 | I187: A1-C5 | J187: 60945.2 | K187: =J187*8000/1000000 -> 487.5616 | L187: 16929.2
B188: A1-E4 | C188: 395771 | D188: =C188*8000/1000000 -> 3166.168 | E188: 50587.1 | I188: A1-C6 | J188: 55.2816 | K188: =J188*8000/1000000 -> 0.4422528 | L188: 15.356
B189: A1-E8 | C189: 53050.3 | D189: =C189*8000/1000000 -> 424.4024 | E189: 6780.84
B190: A1-E10 | C190: 168388 | D190: =C190*8000/1000000 -> 1347.104 | E190: 21523.2 | I190: Chilled water
B191: A1-E12 | C191: 50179.8 | D191: =C191*8000/1000000 -> 401.4384 | E191: 6413.93 | I191: Unit | J191: Duty MJ/h | K191: Energy - TJ/y | L191: Mass - ktonne/y | M191: Remark
B192: A1-E13 | C192: 27665.4 | D192: =C192*8000/1000000 -> 221.3232 | E192: 3536.17 | I192: A1-E20 | J192: 8531.67 | K192: =J192*8000/1000000 -> 68.25336 | L192: 7174.95
B193: A1-E14 | C193: 54033.7 | D193: =C193*8000/1000000 -> 432.2696 | E193: 6906.53 | I193: A1-E29 | J193: 8051.45 | K193: =J193*8000/1000000 -> 64.4116 | L193: 6771.1
B194: A1-E15 | C194: 1058.14 | D194: =C194*8000/1000000 -> 8.46512 | E194: 135.251 | I194: A1-E32 | J194: 3174.61 | K194: =J194*8000/1000000 -> 25.39688 | L194: 2669.78
B195: A1-E17 | C195: 7588.32 | D195: =C195*8000/1000000 -> 60.70656 | E195: 969.931 | I195: A1-E41 | J195: 2317.69 | K195: =J195*8000/1000000 -> 18.54152 | L195: 1949.13
...

Sheet Biogas Plant
B3: BIOGAS PLANT
B4: Process datasheet (Mass & Energy Balance)
B6: Production capacity | D6: 837 tons/y biogas
B7: Operating hours per year | D7: 8000 h/y
B9: Overall Process Description
B10: A biogas plant uses a process called anaerobic digestion to break down organic materials like manure, agricultural waste, and food scraps into biogas, which is a mixture of methane and carbon dioxide. The core components of each biogas plant consists of one or several storage tanks for organic material, a fermentation (digester) tank where microorganisms consume the feedstock in an oxygen-free environment, and a final storage tank for fully digested sludge. There are four processes involved in biogas production [1]. 1. Hydrolysis breaks complex organic structures open to make them accessible to the following processes. 2. Acidogenesis produces organic acids as well as hydrogen, CO2, different alcohols, and a small amount of acetic acid out of organic material. 3. Acetogenesis uses organic acids, hydrogen, and CO2 to produce acetic acid. 4. Methanogenesis produces CH4 from acetic acid and to a lesser extent from hydrogen and CO2.
B18: Process Diagram description
B19: Food waste generation in canteens typically ranges from 0.06 to 0.30 kg/person/day [2]. For this case study, a value of 0.17 kg/person/day has been adopted as a representative figure, calculated as the average of the reported range. Assuming an average of 51 kg/person/year, and considering a university population of 61,700 students and approximately 3,000 academic staff, the annual food waste generation is estimated to be around 3,300 tonnes. This calculation assumes that food waste is generated on 300 operational days per year. Pretreatment The collected food waste is transported to a biogas production facility for energy recovery. Before entering the anaerobic digestion stage, the waste undergoes pretreatment to ensure a uniform and stable feedstock. The pretreatment system consists of: • A grinder (10 kW) to reduce particle size and homogenize the material. • A pretreatment tank equipped with a mixer for thorough blending. • A storage tank of 100 m³, which allows for pH adjustment (to maintain conditions optimal for microbial activity, typically pH 6.5–7.5) and for buffering feedstock flow to the digesters. Anaerobic Digestion After pretreatment, the homogenized substrate is pumped to the anaerobic digestion (AD) system, which includes two digesters (primary and secondary), each with a working volume of 1,260 m³. The primary digester is where most of the biochemical decomposition occurs. Microorganisms convert the organic matter into biogas (mainly methane and carbon dioxide) under oxygen-free (anaerobic) conditions. The secondary digester serves as a post-digestion stage, allowing further biogas production and stabilization of the digestate. Each digester consists of membrane modules, a circulating pump, and associated piping and fittings to maintain continuous mixing and temperature control. The two main products of anaerobic digestion are: • Biogas, used for energy recovery, and • Digestate, which can be used as a soil amendment after appropriate treatment. Biogas Cleaning and Conditioning The raw biogas produced in the digesters typically contains impurities such as water vapor, hydrogen sulfide (H₂S), and trace compounds that must be removed before utilization. The biogas cleaning system includes: • A biogas dehydrator to remove moisture. • A desulfurization unit containing iron oxide (Fe₂O₃) pellets, which react with H₂S to form iron sulfide, reducing sulfur emissions and protecting downstream equipment. • A biogas pump and flow meter to regulate and monitor the gas flow. The cleaned biogas can then be used for combined heat and power (CHP) generation, upgraded to biomethane, or fed into a gas grid, depending on the system configuration. Digestate Treatment The residual material from the digesters, known as digestate, undergoes post-treatment to ensure it is safe and suitable for reuse. The digestate treatment system consists of: • A pump for transfer, • A solid–liquid separator to divide the digestate into liquid and solid fractions, and • A pasteurization unit, operating at 70°C for one hour, to eliminate pathogens and ensure compliance with hygiene standards before land application. The treated digestate can be used as a biofertilizer, contributing to nutrient recycling and reducing the need for chemical fertilizers [3].
G54: Figure 1. Process Flow Diagram- Biogas Plant [3]
B59: Mass Balances
B62: Raw materials | F62: Products | J62: Balance check
B63: Stream | C63: Composition (% mass) | D63: Flow t/y | F63: Stream | G63: Composition (% mass) | H63: Flow t/y | J63: Total inputs/outputs | K63: Flow t/y
B64: Food waste | C64: - | D64: 3300 | F64: Biogas line 1 | G64: 61.99% CH4, 37.5% CO2, 0.51% H2S | H64: 769 (673040 m3) | J64: Raw materials (FS) | K64: =SUM(D64:D67) -> 16820
B65: Dilution water | C65: 100% water | D65: 13520 | F65: Biogas line 2 | G65: 64% CH4, 35.67% CO2, 0.33% H2S | H65: 68 (61680 m3) | J65: Products (PS) | K65: =769+68 -> 837
F66: Cake | G66: - | H66: 1095 | J66: Waste Streams (WS) | K66: =H66+H67+H68 -> 15983
F67: Liquid effluent | G67: - | H67: 2205
F68: Dilution water | G68: 100% water | H68: 12683 | J68: Balance check | K68: =K64-K65-K66 -> 0
J69: Percent error (%) | K69: =(K68/K64)*100 -> 0
B73: Energy Balances | F73: normalisation factor | G73: 837
B75: Process section | C75: Input Electricity- kWe | D75: Input Heat- kWt
B76: Grinder | C76: 10 | D76: 0
B77: Anaerobic digester 1 | C77: 5 | D77: 33.5
B78: Anaerobic digester 2 | C78: 5 | D78: 33.5
B79: Dewatering unit | C79: 6 | D79: 0
B80: Pasteurizer | C80: 0 | D80: 27
C83: =SUM(C76:C80) -> 26 | D83: =SUM(D76:D80) -> 94
B85: Energy Balances - SCALED | C85: Normalization factor | D85: 837 | E85: Scaling factor | F85: 0.018182 | G85: h/y | H85: 8765.82
B87: Process section | C87: Input Electricity- kWe | D87: Input Heat- kWt
B88: Grinder | C88: =C76*$F$85 -> 0.18182 | D88: =D76*$F$85 -> 0
B89: Anaerobic digester 1 | C89: =C77*$F$85 -> 0.09091 | D89: =D77*$F$85 -> 0.609097
B90: Anaerobic digester 2 | C90: =C78*$F$85 -> 0.09091 | D90: =D78*$F$85 -> 0.609097
B91: Dewatering unit | C91: =C79*$F$85 -> 0.109092 | D91: =D79*$F$85 -> 0
B92: Pasteurizer | C92: =C80*$F$85 -> 0 | D92: =D80*$F$85 -> 0.490914
B95: Sum | C95: =SUM(C88:C92) -> 0.472732 | D95: =SUM(D88:D92) -> 1.709108
B96: kWh/y | C96: =C95*H85 -> 4143.8836 | D96: =D95*H85 -> 14981.733 | E96: =SUM(C96:D96) -> 19125.617
B99: No. | C99: References
B100: [1] | C100: Cigano, I., Todini, E., Di Piazza, G., & Morosanu, C. (2021). Valorization of food-waste-derived biomethane in a smart energy system. In Smart energy systems for a green future (pp. 65-88). Elsevier. https://doi.org/10.1016/B978-0-12-822718-3.00004-6
B101: [2] | C101: Liwei G, Shengkui C, Xiaochang C, Dan Z, Xiaojie L, Qi Q, et al. An overview of the resources and environmental issues from wasted food in urban catering across China. J Resour Ecol 2013;4(4):337–43.
B102: [3] | C102: Zeng, H., Yan, Y., Liberti, F., Bartocci, P., & Fantozzi, F. (2019). Technical and economic feasibility analysis of an anaerobic digestion plant fed with canteen food waste. Energy Conversion and Management, 180, 938-948.

Sheet Methanol Production Plant
B3: METHANOL PRODUCTION
B4: Process datasheet (Mass & Energy Balance)
B6: Production capacity | D6: 94 kt/y methanol
B7: Operating hours per year | D7: 8000 h/y
B9: Overall Process Description
B10: Methanol is industrially produced by the catalytic conversion of syngas. The industrial process can be described by the following three steps:_x000b_1) Syngas production_x000b_2) Methanol synthesis 3) Crude methanol purification_x000b_ Starting with the production of syngas from methane, there are two methods being used, Steam Methane Reforming (SMR) and Autothermal Reforming (ATR). ATR involves the partial combustion of methane in the reforming reactor to produce the required heat for the reforming of methane._x000b_SMR involves an external source for generating the required heat, but produces an increased amount of hydrogen per methane. For the synthesis of methanol a hydrogen to carbon ratio of two would be ideal. Thus a combination of SMR and ATR would be preferable and would allow the hydrogen to carbon ratio to be tuned accordingly. However, for a relatively small methanol production plant, a standalone SMR is predominantly used for the production of syngas for methanol synthesis [1]. In this spreadsheet, a single SMR is presented for the production of syngas, in which the steam and methane mixture is reformed per the following reactions: 〖𝐶𝐻〗_4+𝐻_2 𝑂→𝐶𝑂+〖3𝐻〗_2 𝐶𝑂+𝐻_2 𝑂→〖𝐶𝑂〗_2+𝐻_2 To reach the ideal hydrogen to carbon ratio, it was opted to add extra CO2 to the syngas. It is important to reach an ideal ratio because below two there is a reduction in methanol selectivity, while above two there will be an accumulation of hydrogen in the synthesis loop. For the production of methanol, the reaction is carried out in a quasi-isothermal tubular reactor, at a pressure of 69 bar and temperature of 255 °C over a Cu-ZnO-Al2O3 based catalyst per following reactions: 𝐶𝑂+𝐻_2→〖𝐶𝐻〗_3 𝑂𝐻 〖𝐶𝑂〗_2+〖3𝐻〗_2→〖𝐶𝐻〗_3 𝑂𝐻+𝐻_2 𝑂 〖𝐶𝑂〗_2+𝐻_2→𝐶𝑂+𝐻_2 𝑂 Additionally there are some unwanted side-products produced according to the following reactions: 2𝐶𝑂+4𝐻_2→〖𝐶𝐻〗_3 〖𝐶𝐻〗_2 𝑂𝐻+𝐻_2 𝑂 2𝐶𝑂+2𝐻_2→〖𝐻𝐶𝑂𝑂𝐶𝐻〗_3 3𝐶𝑂+6𝐻_2→𝐶_3 𝐻_7 𝑂𝐻+〖2𝐻〗_2 𝑂
B18: Process Diagram description
B19: First, methane is pressurized to 20 bar, mixed with steam and pre-heated by a heat exchanger. The methane and steam mixture is then reformed in the tubular reformer, where rows of reformer tubes are heated by the burning of natural gas. The steam required for the reforming process is produced from the excess heat of the fluegas from the furnace._x000b_ The produced syngas goes through a system of heat exchangers and then to a flash drum where the excess steam is removed as condensed water. The syngas is pressurized to 69,7 bar and injected with CO2 to reach an optimal hydrogen to carbon ratio of 2 for the synthesis of methanol. A ratio of 2 is ideal since below a hydrogen to carbon ratio of two, there is a reduction in methanol selectivity, while above two there will be an accumulation of hydrogen in the synthesis loop. Afterwards, the recycled syngas is mixed with fresh syngas. Methanol is produced in a quasi-isothermal tubular reactor, at a pressure of 69 bar and temperature of 255 °C. The reactions are exothermic, so the reactor is cooled with utility water resulting in boiling water outside of the tubes and thus, the production of steam. The conversion of carbon in a single pass is 50% to 80%, thus the unreacted syngas is recycled to the reactor. This is achieved by first condensing methanol and water and separating them with a flash drum. Part of the recycled syngas is purged to keep the methane fraction at the reactor inlet sufficiently low. Methanol is purified in a two stage distillation process, first the remaining light components (H2,CO, CO2 and CH4) are removed. In the second stage methanol is distilled into a 99,5 wt% methanol product.
L36: LEGENDS
L37: FS- Feedstock/Raw material
L38: PS- Product
L39: WS-Waste
G58: Figure 1. Process Flow Diagram- Methanol Production
B59: Mass Balances
B62: Raw materials | H62: Products | N62: Balance check
B63: Stream | C63: Composition (% mass) | D63: Flow kt/y | E63: Temperature ( °C ) | F63: Pressure (bar) | H63: Stream | I63: Composition (% mass) | J63: Flow kt/y | K63: Temperature ( °C ) | L63: Pressure (bar) | N63: Total inputs/outputs
B64: FS-AIR | C64: 23,29% O2, 76,71% N2 | D64: 827.76013 | E64: 20 | F64: 1.02 | H64: PS-CH3OH | I64: 99,96% CH3OH, 0,02% H2O, 0,02% Ethanol | J64: 93.716777 | K64: 40 | L64: 1.02 | N64: Raw materials (FS) | O64: =SUM(D64:D70) -> 1186.2159
N65: Products (PS) | O65: =J64+J67 -> 173.92127
B66: FS-BFW1 | C66: 100% H2O | D66: 80.20449 | E66: 204.346 | F66: 17 | N66: Waste Streams (WS) | O66: =SUM(K72:K91) -> 1012.2948
B67: FS-Methane | C67: 100% CH4 | D67: 50 | E67: 20 | F67: 1.02 | H67: PS-MPS | I67: 100% H2O | J67: 80.20449 | K67: 230 | L67: 17
B68: FS-Methane-2 | C68: 100% CH4 | D68: 32.220319 | E68: 20 | F68: 1.02 | N68: Balance check | O68: =O64-O65-O66 -> -0.00015761
B69: FS-CO2 | C69: 100% CO2 | D69: 38.817403 | E69: 20 | F69: 1.02 | N69: Percent error (%) | O69: =(O68/O64)*100 -> -1.3286789e-05
B70: FS-WATER | C70: 100% H2O | D70: 157.21355 | E70: 20 | F70: 1.02 | H70: Waste streams
H71: Stream | I71: Component | J71: Composition (% mass) | K71: Flow kt/y | L71: Temperature ( °C ) | M71: Pressure (bar)
H72: WS-FG | I72: H2O | J72: 8.4145943 | K72: 859.98045 | L72: 64.21834 | M72: 1.02
I73: CO2 | J73: 10.27807
I74: O2 | J74: 7.4730151
I75: N2 | J75: 73.834321
H76: WS-LIGHT | I76: CH4 | J76: 3.4850458 | K76: 7.0941017 | L76: 63.053544 | M76: 7
I77: H2O | J77: 0.035114488
I78: H2 | J78: 1.3047409
I79: CO | J79: 1.5399356
I80: CO2 | J80: 79.935519
I81: CH3OH | J81: 13.351856
I82: METFORM | J82: 0.34696669
H83: WS-PURGE | I83: CH4 | J83: 12.821746 | K83: 33.80106 | L83: 40.359253 | M83: 40
I84: H2O | J84: 0.15376957
I85: H2 | J85: 13.082183
I86: CO | J86: 10.845842
I87: CO2 | J87: 60.625002
I88: CH3OH | J88: 2.4702897
H89: WS-W1 | I89: H2O | J89: 99.989923 | K89: 88.970389 | L89: 40 | M89: 1.02
H90: WS-W2 | I90: H2O | J90: 99.581521 | K90: 22.448779 | L90: 40 | M90: 1.02
I91: CH3OH | J91: 0.41771441
B93: Energy Balances
B95: Utility type | C95: Input - TJ/y | D95: Input - kt/y | E95: Output - TJ/y | F95: Output - kt/y | G95: Net - TJ/y | H95: Net - kt/y | I95: Remark | K95: Utility process conditions
B96: Low pressure steam | C96: 117.80372 | D96: 53 | E96: -57.465038 | F96: -26 | G96: 60.33868 | H96: =D96+F96 -> 27 | K96: Utility type | L96: Inlet temperature ( °C ) | M96: Outlet temperature ( °C ) | N96: Inlet pressure (bar) | O96: Outlet pressure (bar) | P96: Heat capacity/latent heat/lower heating value | Q96: Unit
B97: Mid pressure steam | C97: 65.971331 | D97: 33 | E97: -209.56302 | F97: -104 | G97: -143.59168 | H97: =D97+F97 -> -71 | I97: Generation | K97: Very Low pressure steam | L97: - | M97: - | N97: - | O97: - | P97: - | Q97: -
B98: High pressure steam | C98: 0 | D98: 0 | E98: -221.42489 | F98: -118 | G98: -221.42489 | H98: =D98+F98 -> -118 | I98: Generation | K98: Low pressure steam | L98: 155 | M98: 155 | N98: 5.5 | O98: 5.5 | P98: 2096.7716 | Q98: KJ/kg
B99: Cooling water | C99: 1291.537 | D99: 20583.901 | E99: 0 | F99: 0 | G99: =C99 -> 1291.537 | H99: =D99+F99 -> 20583.901 | K99: Mid pressure steam | L99: 214 | M99: 214 | N99: 21 | O99: 21 | P99: 1879.6128 | Q99: KJ/kg
B100: Electricity | C100: 197.04456 | D100: 6842 | E100: 0 | F100: 0 | G100: =C100 -> 197.04456 | H100: =D100 -> 6842 | K100: High pressure steam | L100: 265 | M100: 265 | N100: 51 | O100: 51 | P100: 1632.4494 | Q100: KJ/kg
G101: =SUM(G96:G100) -> 1183.9037 | H101: =SUM(H96:H100) -> 27263.901 | K101: Cooling water | L101: 25 | M101: 40 | N101: 1.02 | O101: 1.02 | P101: =62.74243314036/(M101-L101) -> 4.1828289 | Q101: KJ/kg.K
B102: Energy Balances - SCALED | C102: Normalization factor | D102: 94 | E102: Scaling factor | F102: 3.201134 | G102: h/y | H102: 8765.82
B104: Utility type | C104: Input - TJ/y | D104: Input - kt/y | E104: Output - TJ/y | F104: Output - kt/y | G104: Net - TJ/y | H104: Net - kt/y | I104: Remark
B105: Low pressure steam | C105: =C96*$F$102 -> 377.10549 | D105: =D96*$F$102 -> 169.6601 | E105: =E96*$F$102 -> -183.95329 | F105: =F96*$F$102 -> -83.229484 | G105: =C105+E105 -> 193.1522 | H105: =D105+F105 -> 86.430618
B106: Mid pressure steam | C106: =C97*$F$102 -> 211.18307 | D106: =D97*$F$102 -> 105.63742 | E106: =E97*$F$102 -> -670.83929 | F106: =F97*$F$102 -> -332.91794 | G106: =C106+E106 -> -459.65622 | H106: =D106+F106 -> -227.28051 | I106: Generation
B107: High pressure steam | C107: =C98*$F$102 -> 0 | D107: =D98*$F$102 -> 0 | E107: =E98*$F$102 -> -708.81075 | F107: =F98*$F$102 -> -377.73381 | G107: =C107+E107 -> -708.81075 | H107: =D107+F107 -> -377.73381 | I107: Generation
B108: Cooling water | C108: =C99*$F$102 -> 4134.383 | D108: =D99*$F$102 -> 65891.824 | E108: =E99*$F$102 -> 0 | F108: =F99*$F$102 -> 0 | G108: =C108+E108 -> 4134.383 | H108: =D108+F108 -> 65891.824
B109: Electricity | C109: =C100*$F$102 -> 630.76604 | D109: =D100*$F$102 -> 21902.159 | E109: =E100*$F$102 -> 0 | F109: =F100*$F$102 -> 0 | G109: =C109+E109 -> 630.76604 | H109: =D109+F109 -> 21902.159 | I109: kt/y is kW
G110: =SUM(G105:G109) -> 3789.8343 | H110: =SUM(H105:H109) -> 87275.4
C111: =SUM(C105:C109) -> 5353.4376 | E111: =SUM(E105:E109) -> -1563.6033
B113: Electricity - kWh/y | D113: =D109*H102 -> 1.9199038e+08 | F113: =F109*H102 -> 0
B115: Breakdown of requirements | M115: Methanol production
B116: LLP steam | I116: Electricity
B117: Unit name | C117: Unit description | D117: Duty - MJ/hr | E117: Duty - TJ/y | F117: Mass - ktonne/y | G117: Remark | I117: Unit name | J117: Unit description | K117: Power - KW | L117: Energy- GWh/y | M117: Energy- TJ/y | N117: Remark
B118: M1-T02 | C118: Methanol column | D118: 35803.533 | E118: 286 | F118: 128.88628 | G118: - | I118: M1-C01 | J118: CH4 compressor | K118: 1250.404 | L118: 10.003232 | M118: 36.011635 | N118: -
I119: M1-C02 | J119: Syngas compressor | K119: 2357.0696 | L119: 18.856557 | M119: 67.883606 | N119: -
I120: M1-C03 | J120: CO2 compressor | K120: 486.28418 | L120: 3.8902735 | M120: 14.004984
B121: Low pressure steam | I121: M1-C04 | J121: Recycle syngas compressor | K121: 2727.9654 | L121: 21.823723 | M121: 78.565402 | N121: -
B122: Unit name | C122: Unit description | D122: Duty - MJ/hr | E122: Duty - TJ/y | F122: Mass - ktonne/y | G122: Remark | I122: P-101 | J122: Water pump | K122: 20.101786 | L122: 0.16081429 | M122: 0.57893143
B123: M1-T01 | C123: Lights column | D123: 14725.465 | E123: 118 | F123: 52.729905 | K123: =SUM(K118:K122) -> 6841.825
B124: M1-E03 | C124: LPS boiler | D124: -7183.1298 | E124: -57 | F124: -25.721819 | I124: Natural gas
I125: Unit name | J125: Unit description | K125: Duty - MJ/hr | L125: Duty - TJ/y | M125: Mass - ktonne/y | N125: Remark
F126: =SUM(F123:F124) -> 27.008085
B127: Mid pressure steam | I127: COMB-101 | J127: Tubular reformer | K127: - | L127: =((N98*60*60)*(M127*1000*1000))/(10^9) -> 633.27211 | M127: 31.98344 | N127: -
B128: Unit name | C128: Unit description | D128: Duty - MJ/hr | E128: Duty - TJ/y | F128: Mass - ktonne/y | G128: Remark | I128: - | J128: - | K128: - | L128: - | M128: - | N128: -
B129: M1-E05 | D129: 8246.4164 | E129: 65.971331 | F129: 33.114197 | I129: - | J129: - | K129: - | L129: - | M129: - | N129: -
B130: M1-E09 | D130: -5907.8147 | E130: -47.262518 | F130: -23.72334
B131: M1-E14 | D131: -20287.562 | E131: -162.3005 | F131: -80.16652 | I131: Cooling water
F132: =SUM(F129:F131) -> -70.775663 | I132: Unit name | J132: Unit description | K132: Duty - MJ/hr | L132: Duty - TJ/y | M132: Mass - ktonne/y | N132: Remark
B133: High pressure steam | I133: M1-C01 | J133: Methane compressor | K133: 3134.5999 | L133: 25.076799 | M133: 399.66157 | N133: -
B134: Unit name | C134: Unit description | D134: Duty - MJ/hr | E134: Duty - TJ/y | F134: Mass - ktonne/y | G134: Remark | I134: M1-C02 | J134: Syngas compressor | K134: 4621.4544 | L134: 36.971635 | M134: 589.23557 | N134: -
B135: E-102 | C135: HPS boiler | D135: =-27678.1114 -> -27678.111 | E135: =D135*'[5]Inputs and assumptions'!$E$13/1000000 -> #REF! | F135: -118.25417 | G135: - | I135: M1-C03 | J135: CO2 compressor | K135: 1475.4726 | L135: 11.803781 | M135: 188.1228
B136: - | C136: - | D136: - | E136: - | F136: - | G136: - | I136: M1-E06 | J136: Excess steam condenser | K136: 39542.814 | L136: 316.34251 | M136: 5041.7098 | N136: -
I137: M1-E07 | J137: Methanol condenser | K137: 45965.64 | L137: 367.72512 | M137: 5860.6203 | N137: -
B138: Refrigerant | I138: M1-E10 | J138: Wastewater 1 cooler | K138: 1094.9779 | L138: 8.759823 | M138: 139.60971 | N138: -
B139: Unit name | C139: Unit description | D139: Duty - MJ/hr | E139: Duty - TJ/y | F139: Mass - ktonne/y | G139: Remark | I139: M1-E11 | J139: Wastewater 2 cooler | K139: 713.14815 | L139: 5.7051852 | M139: 90.926408
B140: M1-T01 | C140: Lights column | D140: 4633.5898 | E140: 37 | F140: 26.12146 | G140: - | I140: M1-E12 | J140: Fluegas cooler | K140: 38921.395 | L140: 311.37116 | M140: 4962.479 | N140: -
I141: M1-T02 | J141: Methanol column | K141: -25972.822 | L141: 207.78099 | M141: 3311.5355 | N141: -
M142: =SUM(M133:M141) -> 20583.901
M143: =SUM(M97:M101) -> 674
B146: Disclaimer
B147: This process datasheet is part of the "Unravelling the impacts of using alternative raw materials in industrial clusters"
B148: Project Leader: Prof. dr. ir. Andrea Ramirez Ramirez. Energy & Industry, Faculty of Technology, Policy and Management, Delft University of Technology, The Netherlands.
B149: The affiliation of the process modelers and reviewers is: Energy & Industry, Faculty of Technology, Policy and Management, Delft University of Technology, The Netherlands.
B154: No. | C154: References
B155: [1] | C155: Rainer Reimert, Friedemann Marschner, Hans-Joachim Renner, Walter Boll, Emil Supp, Miron Brejc, Waldemar Liebner and George Schaub: "Gas Production, 2. Processes", Ullmann's Encyclopedia of Industrial Chemistry, Electronic Release, Wiley-VCH, Weinheim September 2012.
B156: [2] | C156: Rainer Reimert, Christopher Higman, Wolfgang Hilsebein, Veronika Gronemann, Uwe Zwiefelhofer and Johannes Albrecht: "Gas Production, 5. Examples of Complex Gas Production Plants" , Ullmann's Encyclopedia of Industrial Chemistry, Electronic Release, Wiley-VCH, Weinheim September 2012.
B157: [3] | C157: Jörg Ott, Veronika Gronemann, Florian Pontzen, Eckhard Fiedler, Georg Grossman, D. Burkhard Kersebohm, Günter Weiss and Claus Witte: "Methanol", Ullmann's Encyclopedia of Industrial Chemistry, Electronic Release, Wiley-VCH, Weinheim September 2012.
B158: [4] | C158: Lei Chen, Qingzhe Jiang, Zhaozheng Song and Dusko Porasac Optimization of methanol yield from Lurgi reactor. Chemical engineering & technology, 34(5):817–822, 2011.
...

Sheet DME Plant
B3: DIMETHYL ETHER (DME) PRODUCTION
B4: Process datasheet (Mass & Energy Balance)
B6: Production capacity | D6: 67 kt/y DME
B7: Operating hours per year | D7: 8000 h/y
B9: Overall Process Description
B10: Currently there are two possible pathways to DME from syngas (CO+H2), indirect and direct synthesis. Indirect synthesis, involves first the production of methanol followed by the production of DME. Direct synthesis, involves the direct production of DME from syngas. Currently, DME is only produced on an industrial scale through indirect synthesis. Dimethyl ether(DME) is industrially produced by the catalytic dehydration of methanol. Methanol is the only raw material being used by the process and DME is the only product.
B18: Process Diagram description
B19: Dimethyl ether is produced by the catalytic dehydration of methanol. The gaseous methanol is first pressurized to 10 bar and fed to a packed bed reactor containing γ-Al2O3 as a catalyst [2,3], where DME is produced by dehydration of methanol. The reaction is exothermic, so the reactor temperature is kept at 250 ° C by producing LPS. DME is purified in a two stage rectification process, consisting of two distillation columns. Pure DME is distilled as the top product in the first column, while methanol and water are separated in the second column. The remaining methanol is recycled to the dehydration reactor, while the wastewater is sent to wastewater treatment. A small fraction of the methanol recycle stream is purged to prevent the build-up of ethanol in the system.
L36: LEGENDS
L37: FS- Feedstock/Raw material
L38: PS- Product
L39: WS-Waste
G58: Figure 1. Process Flow Diagram- Methanol Production
B59: Mass Balances
B62: Raw materials | H62: Products | N62: Balance check
B63: Stream | C63: Composition (% mass) | D63: Flow kt/y | E63: Temperature ( °C ) | F63: Pressure (bar) | H63: Stream | I63: Composition (% mass) | J63: Flow kt/y | K63: Temperature ( °C ) | L63: Pressure (bar) | N63: Total inputs/outputs
B64: FS-CH3OH (Methanol) | C64: H2O 0,023% | D64: 93.716777 | E64: 64.21834 | F64: 1.02 | H64: PS-DME | I64: CH3OH 0,018 %, DME 99,98% | J64: 67.3 | K64: 40 | L64: 10 | N64: Raw materials (FS) | O64: =SUM(D64:D70) -> 93.716777
C65: CH3OH 99,96% | N65: Products (PS) | O65: =J64+J67 -> 67.3
C66: ETHANOL 0,017 % | N66: Waste Streams (WS) | O66: =SUM(I72:I78) -> 0
N68: Balance check | O68: =O64-O65-O66 -> 26.416777
N69: Percent error (%) | O69: =(O68/O64)*100 -> 28.187885
H70: Waste streams
H71: Stream | I71: Component | J71: Composition (% mass) | K71: Flow kt/y | L71: Temperature ( °C ) | M71: Pressure (bar)
H72: WS-PRG1 | I72: H2O | J72: 0.19833614 | K72: 0.13281943 | L72: 137.11957 | M72: 10
I73: CH3OH | J73: 90.008185
I74: ETHANOL | J74: 9.2864319
I75: DME | J75: 0.50667706
H76: WS-WATER | I76: H2O | J76: 99.941726 | K76: 26.331856 | L76: 40 | M76: 1
I77: CH3OH | J77: 0.04544634
I78: ETHANOL | J78: 0.012786375
B84: Energy Balances
B86: Utility type | C86: Input - TJ/y | D86: Input - kt/y | E86: Output - TJ/y | F86: Output - kt/y | G86: Net - TJ/y | H86: Net - kt/y | I86: Remark | K86: Utility process conditions
B87: Very low pressure steam | C87: 0 | D87: 0 | E87: -25.027728 | F87: -11.315466 | G87: =C87+E87 -> -25.027728 | H87: =D87+F87 -> -11.315466 | I87: Generation | K87: Utility type | L87: Inlet temperature ( °C ) | M87: Outlet temperature ( °C ) | N87: Inlet pressure (bar) | O87: Outlet pressure (bar) | P87: Heat capacity/latent heat/lower heating value | Q87: Unit
B88: Low pressure steam | C88: 0 | D88: 0 | E88: -30.750974 | F88: -13.764387 | G88: =C88+E88 -> -30.750974 | H88: =D88+F88 -> -13.764387 | I88: Generation | K88: Very Low pressure steam | L88: - | M88: - | N88: - | O88: - | P88: - | Q88: -
B89: Mid pressure steam | C89: 213.95742 | D89: 107.39556 | E89: 0 | F89: 0 | G89: =C89+E89 -> 213.95742 | H89: =D89+F89 -> 107.39556 | K89: Low pressure steam | L89: 155 | M89: 155 | N89: 5.5 | O89: 5.5 | P89: 2096.7716 | Q89: KJ/kg
B90: High pressure steam | C90: 0 | D90: 0 | E90: 0 | F90: 0 | G90: =C90+E90 -> 0 | H90: =D90+F90 -> 0 | K90: Mid pressure steam | L90: 214 | M90: 214 | N90: 21 | O90: 21 | P90: 1879.6128 | Q90: KJ/kg
B91: Cooling water | C91: 316.95542 | D91: 5051.4781 | E91: 0 | F91: 0 | G91: =C91+E91 -> 316.95542 | H91: =D91+F91 -> 5051.4781 | K91: High pressure steam | L91: 265 | M91: 265 | N91: 51 | O91: 51 | P91: 1632.4494 | Q91: KJ/kg
B92: Electricity | C92: 30.682347 | D92: 1065.36 | E92: 0 | F92: 0 | G92: =C92+E92 -> 30.682347 | H92: 1065.36 | I92: kt/y is kW | K92: Cooling water | L92: 25 | M92: 40 | N92: 1.02 | O92: 1.02 | P92: =62.74243314036/(M92-L92) -> 4.1828289 | Q92: KJ/kg.K
B94: Energy Balances - SCALED | C94: Normalization factor | D94: 67.3 | E94: Scaling factor | F94: 2.080238 | G94: h/y | H94: 8765.82
B96: Utility type | C96: Input - TJ/y | D96: Input - kt/y | E96: Output - TJ/y | F96: Output - kt/y | G96: Net - TJ/y | H96: Net - kt/y | I96: Remark
B97: Very low pressure steam | C97: =C87*$F$94 -> 0 | D97: =D87*$F$94 -> 0 | E97: =E87*$F$94 -> -52.06363 | F97: =F87*$F$94 -> -23.538862 | G97: =C97+E97 -> -52.06363 | H97: =D97+F97 -> -23.538862 | I97: Generation
B98: Low pressure steam | C98: =C88*$F$94 -> 0 | D98: =D88*$F$94 -> 0 | E98: =E88*$F$94 -> -63.969345 | F98: =F88*$F$94 -> -28.6332 | G98: =C98+E98 -> -63.969345 | H98: =D98+F98 -> -28.6332 | I98: Generation
B99: Mid pressure steam | C99: =C89*$F$94 -> 445.08236 | D99: =D89*$F$94 -> 223.40833 | E99: =E89*$F$94 -> 0 | F99: =F89*$F$94 -> 0 | G99: =C99+E99 -> 445.08236 | H99: =D99+F99 -> 223.40833
B100: High pressure steam | C100: =C90*$F$94 -> 0 | D100: =D90*$F$94 -> 0 | E100: =E90*$F$94 -> 0 | F100: =F90*$F$94 -> 0 | G100: =C100+E100 -> 0 | H100: =D100+F100 -> 0
B101: Cooling water | C101: =C91*$F$94 -> 659.34272 | D101: =D91*$F$94 -> 10508.277 | E101: =E91*$F$94 -> 0 | F101: =F91*$F$94 -> 0 | G101: =C101+E101 -> 659.34272 | H101: =D101+F101 -> 10508.277
B102: Electricity | C102: =C92*$F$94 -> 63.826584 | D102: =D92*$F$94 -> 2216.2024 | E102: =E92*$F$94 -> 0 | F102: =F92*$F$94 -> 0 | G102: =C102+E102 -> 63.826584 | H102: =D102+F102 -> 2216.2024 | I102: kt/y is kW
C104: =SUM(C98:C102) -> 1168.2517 | E104: =SUM(E97:E102) -> -116.03298
B106: Electricity - kWh/y | D106: =D102*H94 -> 19426831 | F106: =F102*H94 -> 0
B108: Breakdown of requirements | M108: DME Production
B109: LLP steam | I109: Electricity
B110: Unit name | C110: Unit description | D110: Duty - MJ/hr | E110: Duty - TJ/y | F110: Mass - ktonne/y | G110: Remark | I110: Unit name | J110: Unit description | K110: Power - KW | L110: Energy- GWh/y | M110: Energy- TJ/y | N110: Remark
B111: M1-T02 | C111: Methanol column | D111: -3128.4659 | E111: -25 | F111: -11.315466 | G111: - | I111: M4-C01 | J111: Methanol compressor | K111: 1065.3593 | L111: 8.5228742 | M111: 30.682347 | N111: -
B114: Low pressure steam
B115: Unit name | C115: Unit description | D115: Duty - MJ/hr | E115: Duty - TJ/y | F115: Mass - ktonne/y | G115: Remark
B116: M4-R01 | C116: Dehydration reactor | D116: -3843.8718 | E116: -31 | F116: -13.764387 | I116: Natural gas
B117: - | C117: - | D117: - | E117: - | F117: - | G117: - | I117: Unit name | J117: Unit description | K117: Duty - MJ/hr | L117: Duty - TJ/y | M117: Mass - ktonne/y | N117: Remark
I118: - | J118: - | K118: - | L118: - | M118: - | N118: -
B119: Mid pressure steam | I119: - | J119: - | K119: - | L119: - | M119: - | N119: -
B120: Unit name | C120: Unit description | D120: Duty - MJ/hr | E120: Duty - TJ/y | F120: Mass - ktonne/y | G120: Remark | I120: - | J120: - | K120: - | L120: - | M120: - | N120: -
B121: M4-T01 | C121: DME column | D121: 3718.2379 | E121: =D121*'[7]Inputs and assumptions'!$E$13/1000000 -> #REF! | F121: 14.930905 | G121: -
B122: M4-T02 | C122: Methanol column | D122: 23026.44 | E122: =D122*'[7]Inputs and assumptions'!$E$13/1000000 -> #REF! | F122: 92.464658 | G122: - | I122: Cooling water
B123: - | C123: - | D123: - | E123: - | F123: - | G123: - | I123: Unit name | J123: Unit description | K123: Duty - MJ/hr | L123: Duty - TJ/y | M123: Mass - ktonne/y | N123: Remark
F124: =SUM(F121:F122) -> 107.39556 | I124: M4-C01 | J124: Methanol compressor | K124: 715.63069 | L124: 5.7250455 | M124: 91.242932
B125: High pressure steam | I125: M4-E03 | J125: Cooler | K125: 2088.5178 | L125: 16.708142 | M125: 266.28607
B126: Unit name | C126: Unit description | D126: Duty - MJ/hr | E126: Duty - TJ/y | F126: Mass - ktonne/y | G126: Remark | I126: M4-E04 | J126: DME cooler | K126: 98.772944 | L126: 0.79018355 | M126: 12.593553
B127: - | C127: - | D127: - | E127: - | F127: - | G127: - | I127: M4-T01 | J127: DME column | K127: 15523.64 | L127: 124.18912 | M127: 1979.2645
B128: - | C128: - | D128: - | E128: - | F128: - | G128: - | I128: M4-T02 | J128: Methanol column | K128: 21192.867 | L128: 169.54294 | M128: 2702.0911
B130: Refrigerant
B131: Unit name | C131: Unit description | D131: Duty - MJ/hr | E131: Duty - TJ/y | F131: Mass - ktonne/y | G131: Remark | M131: =SUM(M124:M129) -> 5051.4781
B132: - | C132: - | D132: - | E132: - | F132: - | G132: -
B133: - | C133: - | D133: - | E133: - | F133: - | G133: -
B134: - | C134: - | D134: - | E134: - | F134: - | G134: -
B137: Disclaimer
B138: This process datasheet is part of the "Unravelling the impacts of using alternative raw materials in industrial clusters"
B139: Project Leader: Prof. dr. ir. Andrea Ramirez Ramirez. Energy & Industry, Faculty of Technology, Policy and Management, Delft University of Technology, The Netherlands.
B140: The affiliation of the process modelers and reviewers is: Energy & Industry, Faculty of Technology, Policy and Management, Delft University of Technology, The Netherlands.
B145: No. | C145: References
B146: [1] | C146: Manfred Müller, Ute Hübsch: "Dimethyl Ether", Ullmann's Encyclopedia of Industrial Chemistry, Electronic Release, Wiley-VCH, Weinheim September 2012.
B147: [2] | C147: M. Rashid Khan, Advances In Clean Hydrocarbon Fuel Processing: Science And Technology. Woodhead Publishing, 2011
B148: [3] | C148: Eric C.D. Tan, Michael Talmadge, Abhijit Dutta, Jesse Hensley, Josh Schaidle, and Mary Biddy., David Humbird., Lesley J. Snowden-Swan., Jeff Ross, Danielle Sexton, Raymond Yap, and John Lukas.,"Process Design and Economics for the Conversion of Lignocellulosic Biomass to Hydrocarbons via Indirect Liquefaction: Thermochemical Research Pathway to High-Octane Gasoline Blendstock Through Methanol/Dimethyl Ether Intermediates", National Renewable Energy Lab, United States, 2015, Web. doi:10.2172/1215006

Sheet Assignment Requirements
C1: The development of the following chapters requires an evaluation of the production plants listed in this datasheet.
C3: CHAPTER 3. PROJECT SCOPE 3.1. Project scope- Case Study: [Name of Industrial Park] This section should Introduce and define the industrial park (IP) by providing: • Name of the Industrial Park: Choose a unique and relevant name. • Location: Specify the geographic location. From the provided Excel spreadsheet “Industrial Park Data_2026”, select at least 6 production plants/companies. For each company, the following details should be provided: • Companies and Activities: Briefly describe the company’s operations, including main inputs, processes, products, and production capacities. CHAPTER 4. MATERIALS ANALYSIS 4.1 Mass balance analysis: Students should perform a mass balance and component balance (carbon, chlorine, etc.) for each company based on a selected production capacity. This analysis should quantify all material inputs, outputs, and flows through the production process, providing a clear understanding of resource consumption and waste generation. Moreover for water flows, students should identify: • Sources (e.g., municipal water, groundwater, surface water)- Assumptions are allowed • Process uses (washing, quenching, reagent, etc.) • Water types, quality and main impurities A block diagram with overall mass balance per company should be included. 4.2 Performance evaluation: Assess key performance indicators (KPIs) for each company to assess operational efficiency, resource management, waste generation, and environmental performance. (For detailed calculation methods, refer to the slides from lecture “Tutorial: Materials”) 4.3 Identification of Industrial Symbiosis Opportunities In this section, students should identify and evaluate potential industrial symbiosis opportunities within the industrial park by analyzing cross-company resource flows. The objective is to propose a feasible material symbiosis network that enhances resource efficiency and circularity. For this: • Perform a systematic analysis to identify possible exchanges of materials between companies. Consider potential material exchanges, including the use of waste streams or by-products from one company as inputs for another. Consider opportunities such as reuse of treated wastewater/waste or shared water/waste treatment systems. • Document all identified matches in a supply–demand matrix. For each proposed synergy, provide a brief justification based on technical feasibility, process compatibility, and expected benefits (e.g., reduced waste, resource savings, or emissions reduction). • Graphical Representation of the Network. Create a graphical representation of the proposed materials symbiosis network using Linny-r. This visualization should clearly illustrate all identified exchanges and interconnections between companies. • Include a Sankey diagram to clearly illustrate the component flows within the network. 4.4 Selection of companies for further assessment and intervention design: Based on the mass balance and performance evaluation, select three companies for in-depth analysis. For these companies, students should include: • Significance of study: explain why analyzing the selected companies is important from a material perspective, use indicators to support your decision. • Challenges and problems: identify the main material-related issues associated with their current industrial practices. These may include: operational inefficiencies, resource management challenges, water consumption, environmental impacts due to waste, by-products, or emissions. 4.5 Proposed Interventions: Propose and describe at least two potential interventions for each of the selected companies to enhance their operational and environmental performance. For each measure, discuss the key drivers that could facilitate its implementation, as well as the potential barriers or challenges that may need to be addressed. Interventions may include: • Adoption of new technologies • Process optimization strategies • Other solutions aimed at enhancing sustainability and material efficiency Moreover, identify the most suitable treatment methods for the waste streams generated by these companies and propose either a wastewater treatment plant (WWTP), or a waste processor for other types of waste, and describe the appropriate treatment stages and process steps involved (you can refer to the Best Available Techniques (BAT)). Specify whether a centralized treatment plant will be shared among the companies, or if individual on-site treatment systems are required. CHAPTER 5. ENERGY ANALYSIS 5.1 Energy balance analysis: Students should perform an energy balance for each company based on a selected production capacity. This analysis should quantify all energy inputs, outputs, and internal flows throughout the production process, providing a clear understanding of energy consumption, losses, and efficiency. A block diagram illustrating the overall energy balance per company should be included. 5.2 Performance evaluation: Assess key performance indicators (KPIs) for each company to evaluate energy efficiency, energy consumption, losses, and environmental performance. (For detailed calculation methods, refer to the slides from lecture “Tutorial: Energy”.) 5.3 Identification of Industrial Symbiosis Opportunities In this section, students should identify and evaluate potential industrial symbiosis opportunities within the industrial park by analyzing cross-company resource flows. The objective is to propose a feasible energy symbiosis network that enhances overall energy efficiency and supports decarbonization efforts. For this: • Perform a systematic analysis to identify possible exchanges of energy between companies. Consider opportunities such as waste heat recovery, shared utility systems, steam or hot water cascades. • Document all identified matches in a supply–demand matrix. For each proposed synergy, provide a brief justification based on technical feasibility, process compatibility, and expected benefits (e.g., energy savings or emissions reduction). • Graphical Representation of the Network. Create a graphical representation of the proposed energy symbiosis network using Linny-r. This visualization should clearly illustrate all identified exchanges and interconnections between companies. (This task will be completed during the Linny-r Workshop.) 5.4 Selection of companies for further assessment and intervention design: Based on the energy balance and performance evaluation, select three companies for in-depth assessment. For these companies, students should include: • Significance of study: explain why analyzing the selected companies is important from an energy perspective, use energy-related indicators to support your decision. • Challenges and problems: identify the main energy-related issues associated with their current industrial practices. These may include: high energy consumption or poor energy efficiency, significant energy losses in processes or heat recovery, environmental impacts associated with energy use, such as GHG emissions or carbon intensity. 5.5 Proposed Interventions: Propose and describe at least two potential measures for each of the two selected companies to enhance their operational and environmental performance. For each measure, discuss the key drivers that could facilitate its implementation, as well as the potential barriers or challenges that may need to be addressed. Interventions may include: • Adoption of new technologies • Process optimization strategies • Other solutions aimed at enhancing sustainability and energy efficiency (use of renewable or low-carbon energy sources)

Sheet Materials Nomenclature
A1: Chemical | B1: Abbreviation | C1: CAS Number | D1: Molecular weight | E1: Carbon Atoms
A2: 1,1,1,2-Tetrachloroethane | B2: TECE | C2: 630-20-6 | D2: =167.85 -> 167.85 | E2: 2
A3: 1,1,1,2-Tetrafluoroethane | B3: TEFE | C3: 811-97-2 | D3: 102.03 | E3: 2
A4: 1,1,2-Trichloroethane | B4: TCE | C4: 79-00-5 | D4: 133.4 | E4: 2
A5: 1,2,3-Trichloropropane | B5: TCP | C5: 96-18-4 | D5: 147.43 | E5: 3
A6: 1,2,4-Trimethylbenzene | B6: TMB | C6: 95-63-6 | D6: 120.19 | E6: 9
A7: 1,2-Butadiene | B7: BDI-12 | C7: 590-19-2 | D7: 54.09 | E7: 4
A8: 1,3,5-Triethylbenzene | B8: TEB | C8: 102-25-0 | D8: 162.27 | E8: 12
A9: 1,3-Butadiene | B9: BDI-13 | C9: 106-99-0 | D9: 54.09 | E9: 4
A10: 1,3-Benzenedicarbonitrile | B10: DCB-13 | C10: 626-17-5 | D10: 128.1308 | E10: 8
A11: 1,4-Diethylbenzene | B11: DEB | C11: 105-05-5 | D11: 134.22 | E11: 10
A12: 1,4-Dioxane | B12: DIOX | C12: 123-91-1 | D12: 88.11 | E12: 4
A13: 1-Butene | B13: C4E | C13: 106-98-9 | D13: 56.11 | E13: 4
A14: 1-Pentene | B14: C5E | C14: 109-67-1 | D14: 70.13 | E14: 5
... A25: 4,4′-Methylene dianiline | B25: MDA | C25: 101-77-9 | D25: 198.26 | E25: 13
A26: 4,4′-Methylene dianiline (Polymer) | B26: PMDA | E26: 13
A27: 4,4′-Methylene dianiline (Segment) | B27: SMDA | E27: 13
A28: 4,4-Methylene diphenyl diisocyanate | B28: MDI | C28: 101-68-8 | D28: 250.25 | E28: 15
A29: 4,4-Methylene diphenyl diisocyanate (Polymer) | B29: PMDI | C29: 9016-87-9 | E29: 15
A30: 4,4-Methylene diphenyl diisocyanate (Segment) | B30: SMDI | E30: 15
A31: 4-Carboxybenzaldehyde | B31: CBA | C31: 619-66-9 | D31: 150.13 | E31: 8
A32: 4-Carboxybenzaldehyde (solid) | B32: CBA-S | C32: 619-66-9 | D32: 150.13 | E32: 8
A33: 4-Formylmorpholine | B33: NFM | C33: 4394-85-8 | D33: 115.13 | E33: 5
A34: Acetaldehyde | B34: MECHO | C34: 75-07-0 | D34: 44.05 | E34: 2
A35: Acetic acid | B35: HOAC | C35: 64-19-7 | D35: 60.05 | E35: 2
A36: Acetone | B36: ACE | C36: 67-64-1 | D36: 58.08 | E36: 3
A37: Acetophenone | B37: ACP | C37: 98-86-2 | D37: 120.15 | E37: 8
A38: Acetylene | B38: ACET | C38: 74-86-2 | D38: 26.04 | E38: 2
A39: alpha-Linolenic acid | B39: ALA | C39: 463-40-1 | D39: 278.43 | E39: 18
A40: Aluminium oxide | B40: AL2O3 | E40: 0
A41: Ammonia | B41: NH3 | C41: 7664-41-7 | D41: 17.03 | E41: 0
A42: Ammonium | B42: NH4+ | C42: 14798-03-9 | D42: 18.039 | E42: 0
A43: Ammonium carbamate | B43: AMBIC | C43: 1111-78-0 | D43: 78.07 | E43: 3
A44: Ammonium sulfate | B44: AMS | C44: 7783-20-2 | D44: 132.14 | E44: 0
A45: Aniline | B45: PHNH2 | C45: 62-53-3 | D45: 93.13 | E45: 6
A46: Argon | B46: AR | C46: 7440-37-1 | D46: 39.95 | E46: 0
A47: Benzaldehyde | B47: BZA | C47: 100-52-7 | D47: 106.12 | E47: 7
A48: Benzene | B48: BZ | C48: 71-43-2 | D48: 78.11 | E48: 6
A49: Benzoic acid | B49: BZAC | C49: 65-85-0 | D49: 122.12 | E49: 7
A50: Bibenzyl | B50: BIBZ | C50: 103-29-7 | D50: 182.26 | E50: 14
A51: Bicarbonate | B51: HCO3- | C51: 71-52-3 | D51: 84.01 | E51: 1
A52: Bis(2-Hydroxyethyl) terephthalate | B52: BHET | C52: 959-26-2 | D52: 254.24 | E52: 12
A53: Butyl acetate | B53: BUAC | C53: 123-86-4 | D53: 116.16 | E53: 6
A54: Calcium oxide | B54: CAO | E54: 0
A55: Carbon black | B55: CABB | C55: 1333-86-4 | E55: 1
A56: Carbon dioxide | B56: CO2 | C56: 124-38-9 | D56: 44.01 | E56: 1
A57: Carbon monoxide | B57: CO | C57: 630-08-0 | D57: 28.1 | E57: 1
A58: Carbonate | B58: CO3-- | C58: 3812-32-6 | D58: 60.01 | E58: 1
A59: Catalytic cracked oil | B59: CCOIL | E59: 50
A60: Char | B60: CHAR | E60: 1
A61: Chloride ion | B61: CL- | C61: 16887-00-6 | D61: 35.45 | E61: 0
A62: Chlorine | B62: CL2 | C62: 7782-50-5 | D62: 70.91 | E62: 0
A63: Chlorobenzene | B63: CLBZ | C63: 108-90-7 | D63: 112.56 | E63: 6
A64: Chloroform | B64: CHCL3 | C64: 67-66-3 | D64: 119.38 | E64: 1
A65: cis-2-Butene | B65: CIS-2C4E | C65: 590-18-1 | D65: 56.11 | E65: 4
A66: Cobalt(II) bromide | B66: COBR2 | C66: 7789-43-7 | D66: 218.74 | E66: 0
A67: Cumene | B67: CUMENE | C67: 98-82-8 | D67: 120.19 | E67: 9
A68: Cyclohexane | B68: CYHEX | C68: 110-82-7 | D68: 84.16 | E68: 6
A69: Cyclopentadiene | B69: CYPD | C69: 542-92-7 | D69: 66.1 | E69: 5
A70: Dicyclopentadiene | B70: DCYPD | C70: 77-73-6 | D70: 132.2 | E70: 10
A71: Di-ethanolamine | B71: DEA | C71: 141-43-5 | D71: 61.08 | E71: 2
A72: Diethylene glycol | B72: DEG | C72: 111-46-6 | D72: 106.12 | E72: 4
... A76: Dimethyl ether | B76: DME | C76: 115-10-6 | D76: 46.07 | E76: 2
A77: Diphosphorus pentaoxide | B77: P2O5 | E77: 0
A78: Dipropylene glycol methyl ether | B78: DPGME | E78: 7
A79: Epichlorohydrin | B79: ECH | C79: 106-89-8 | D79: 95.52 | E79: 3
A80: Ethane | B80: N-C2A | C80: 74-84-0 | D80: 30.07 | E80: 2
A81: Ethanol | B81: ETOH | C81: 64-17-5 | D81: 46.07 | E81: 2
A82: Ethyl chloride | B82: EC | C82: 75-00-3 | D82: 64.51 | E82: 2
A83: Ethylbenzene | B83: EB | C83: 100-41-4 | D83: 106.17 | E83: 8
A84: Ethylbenzene hydroperoxide | B84: EBHP | C84: 3071-32-7 | D84: 138.16 | E84: 8
A85: Ethylene | B85: C2E | C85: 74-85-1 | D85: 28.05 | E85: 2
A86: Ethylene dichloride | B86: EDC | C86: 107-06-2 | D86: 98.96 | E86: 2
A87: Ethylene glycol | B87: MEG | C87: 107-21-1 | D87: 62.07 | E87: 2
A88: Ethylene oxide | B88: EO | C88: 75-21-8 | D88: 44.05 | E88: 2
A89: Ferric chloride | B89: FECL3 | C89: 7705-08-0 | D89: 162.2 | E89: 0
A90: Fluoromethane | B90: CH3F | C90: 593-53-3 | D90: 34.03 | E90: 1
... A93: Glycerol | B93: GLY | C93: 56-81-5 | D93: 92.09 | E93: 3
A94: Hematite | B94: FE2O3 | E94: 0
A95: Hydrogen | B95: H2 | C95: 1333-74-0 | D95: 2.02 | E95: 0
A96: Hydrogen chloride | B96: HCL | C96: 7647-01-0 | D96: 36.49 | E96: 0
A97: Hydrogen ion | B97: H+ | C97: 12408-02-5 | E97: 0
A98: Hydrogen sulfate | B98: HSO4- | C98: 14996-02-2 | E98: 0
A99: Hydrogen sulfide | B99: H2S | C99: 7783-06-4 | D99: 34.08 | E99: 0
A100: Hydronium | B100: H3O+ | C100: 13968-08-6 | E100: 0
A101: Hydroxide | B101: OH- | C101: 14280-30-9 | E101: 0
A102: Isobutane | B102: I-C4A | C102: 75-28-5 | D102: 58.12 | E102: 4
A103: Isobutylene | B103: I-C4E | C103: 115-11-7 | D103: 56.11 | E103: 4
A104: Isopentane | B104: I-C5A | C104: 78-78-4 | D104: 72.15 | E104: 5
A105: Isophthalonitrile | B105: IPN | C105: 626-17-5 | D105: 128.13 | E105: 8
A106: Isoprene | B106: IPE | C106: 78-79-5 | D106: 68.12 | E106: 5
A107: Isopropyl alcohol | B107: IPA | C107: 67-63-0 | D107: 60.1 | E107: 3
A108: Lauroyl peroxide | B108: LPO | C108: 105-74-8 | D108: 398.62 | E108: 24
A109: Linolenic Acid | B109: ALA | C109: 463-40-1 | D109: 278.43 | E109: 18
A110: Magnesium oxide | B110: MGO | E110: 0
A111: Manganese(II) bromide | B111: MNBR2 | C111: 13446-03-2 | D111: 214.746 | E111: 0
A112: Methane | B112: CH4 | C112: 74-82-8 | D112: 16.04 | E112: 1
A113: Methanol | B113: MEOH | C113: 67-56-1 | D113: 32.04 | E113: 1
A114: Methyl acetate | B114: MEOAC | C114: 79-20-9 | D114: 74.08 | E114: 3
A115: Methyl acetylene | B115: MEAC | C115: 74-99-7 | D115: 40.06 | E115: 3
...

Sheet Hydrogen Plant
B3: HYDROGEN PLANT
B4: Process datasheet (Mass & Energy Balance)
B6: Production capacity | D6: 1 kt hydrogen | E6: Note: You can scale up to desired H2 production
B7: Operating hours per year | D7: 8000 h/y
B9: Overall Process Description
B10: Hydrogen has become more popular due to its applications as a fuel as well as commodity chemical. Though claimed as the most abundant element in the universe, hydrogen is not available in its pure form, but rather has to be obtained from hydrocarbons by cracking or from water electrolysis . On an industrial scale, hydrogen is produced by cracking of hydrocarbons via a process called Steam Methane Reforming (SMR), which is used to produce 96% of the global hydrogen demands. In this conventional process, low molecular hydrocarbons, majorly methane, are cracked to obtain hydrogen and other gases, followed by a separation train to obtain >99 wt% purity. An SMR process includes 2 significant steps- a high temperature reforming step with Ni/Al2O3 catalyst and an exothermic shift reaction to produce more hydrogen from shifting CO to CO2 in an iron oxide-based catalyst. The reforming reaction is represented as follows, CH4 + H2O ⇌ CO + 3 H2 (ΔHr= 206 kJ/mol) This reaction is highly endothermic and takes place at 850˚C and 19 bar. The heating requirements are provided by burning natural gas in a furnace. On the other hand, the water gas shift reaction is as follows, CO + H2O ⇌ CO2 + H2 (ΔHr= -41 kJ/mol) This reaction is mildly exothermic and takes place at > 400˚C and 17 bar. In conventional SMR plants, the process gas is further purified using amine absorption to remove CO2 and cryogenic separation to obtain hydrogen with >95 wt.% purity. In most modern plants, instead of amine absorption, several Pressure Swing Adsorption (PSA) units are used to obtain hydrogen with high purity (>99 wt.%.) .The tail gas from PSA units has unreacted methane, which can be combined with natural gas to be used as a furnace fuel.
B18: Process Diagram description
B19: In the modern steam reforming process, natural gas at 20˚C, and 20 bar, enters the reformer and is mixed with steam at 215˚C, 21 bar and a partial recycle of hydrogen product. The Steam/Carbon ratio is maintained at 2.5 [1]. The feed stream is then pre-heated to 520˚C using the heat from a natural gas furnace and sent to the reformers. The reformer vessel is essentially a furnace with natural gas fired in the radiation section. This is done to mantain a high heating temperature, which is then required for the endothermic steam methane reforming process. The convection section has tubular reactive zones or reformers where the reaction takes place at 14-20 bar and 850˚C in presence of Ni/Al2O3 catalysts [1]. The reformer outlet is cooled down to 350˚C before entering the shift reactor. Along the way, high and medium pressure steam are generated through boiling feed water. In the shift reactor, CO and H2O react and the residual CO is converted to CO2 and more hydrogen is produced [1]. The conversion in this reactor is between 80-95% [2]. Since, the reaction is mildly exothermic, the outlet of the shift reactor is at a slightly elevated temperature. Thus, the process gas is then cooled to 30˚C before it is sent to a flash to remove wastewater, and then the hydrogen is separated in the Pressure Swing Adsorption (PSA). Likewise, in this cooling process, medium and low pressure steam are generated. In the PSA units, operating at ~16bar, hydrogen is selectively separated from the rest gases to obtain a 99,9 wt.% pure product composition. A small part of the product gas (~1,5%) is compressed and recycled back to the reformer tubes to avoid coking. On the other hand, the recovered tail gas from the PSA units is sent to the natural gas furnace, to be used as fuel. The natural gas furnace is an important utility source, which provides the heat required for conditioning of the feed and the reformer. In this section, 10% excess air is fed to the furnace after compression at 3 bar [1]. Extremely high temperature is obtained in the furnace, which is used as an utility and then is used to produce high, medium and low pressure steam. The waste flue gas can be potentially used in other processes (In this model its use has not been considered)
L36: LEGENDS
L37: FS- Feedstock/Raw material
L38: PS- Product
L39: WS-Waste
G57: Figure 1. Process Flow Diagram- Hydrogen Production
B59: Mass Balances
B62: Raw materials
B63: Stream | C63: Composition (% mass) | D63: Flow kt/kt hydrogen | E63: Temp (C) | F63: Pressure (bar) | H63: Products | N63: Balance check
B64: FS-NG | C64: 70.5% CH4, 2.38% CO2, 21.78 N2, 4.88% N-C2A, 0.47% NC3-A | D64: 3.342041 | E64: 20 | F64: 20 | H64: Stream | I64: Composition (% mass) | J64: Flow kt/kt hydrogen | K64: Temp (C) | L64: Pressure (bar) | N64: Total inputs/outputs
B65: FS-STEAM | C65: 100% water | D65: 6.6145921 | E65: 215 | F65: 21 | H65: PS-HYDRO | I65: 99.93% H2, 0.07% N2 | J65: 1 | K65: 40 | L65: 15 | N65: Raw materials (FS) | O65: =SUM(D64:D67) -> 38.150212
B66: FS-AIR | C66: 0.045% CO2, 0.27% H2O, 75.27 % N2, 23.13% O2, 1.28% AR | D66: 27.094167 | E66: 15 | F66: 1.02 | H66: WS-FLUE | I66: 61.05% N2, 26.9% CO2, 8.8% Water, 2.4% O2, 0.99% Ar | J66: 34.98 | K66: 180 | L66: 3 | N66: Products (PS) | O66: =J65 -> 1
B67: FS-UCH4 | C67: 70.5% CH4, 2.38% CO2, 21.78 N2, 4.88% N-C2A, 0.47% NC3-A | D67: 1.0994116 | E67: 15 | F67: 1.02 | H67: WS-WW | I67: 99.95 %water, 0.05% CO2 | J67: 2.16 | K67: 40 | L67: 1.02 | N67: Waste Streams (WS) | O67: =SUM(J66:J67) -> 37.14
N68: Balance check | O68: =O65-O66-O67 -> 0.010211749
N69: Percent error (%) | O69: =(O68/O65)*100 -> 0.026767214
B73: Energy Balances
B75: Utility type | C75: Input - TJ/kt hydrogen | D75: Input - kt/kt hydrogen | E75: Output - TJ/kt hydrogen | F75: Output - kt/kt hydrogen | G75: Net - TJ/kt hydrogen | H75: Net - kt/kt hydrogen | I75: Remark | K75: Utility process conditions
B76: Low pressure steam | C76: 0 | D76: 0 | E76: =-461.8352/99.8 -> -4.6276072 | F76: =-220.3/99.8 -> -2.2074148 | G76: =E76-C76 -> -4.6276072 | H76: =F76-D76 -> -2.2074148 | I76: Net Generation | K76: Utility type | L76: Inlet temperature ( °C ) | M76: Outlet temperature ( °C ) | N76: Inlet pressure (bar) | O76: Outlet pressure (bar) | P76: Heat capacity/latent heat/lower heating value | Q76: Unit
B77: Mid pressure steam | C77: 0 | D77: 0 | E77: =-462.2928/99.8 -> -4.6321924 | F77: =-246/99.8 -> -2.4649299 | G77: =E77-C77 -> -4.6321924 | H77: =F77-D77 -> -2.4649299 | I77: Net Generation | K77: Very Low pressure steam | L77: - | M77: - | N77: - | O77: - | P77: - | Q77: -
B78: High pressure steam | C78: 0 | D78: 0 | E78: =-3439.064/99.8 -> -34.459559 | F78: =-2106.7/99.8 -> -21.109218 | G78: =E78-C78 -> -34.459559 | H78: =F78-D78 -> -21.109218 | I78: Net Generation | K78: Low pressure steam | L78: 155 | M78: 155 | N78: 5.5 | O78: 5.5 | P78: 2096.7716 | Q78: KJ/kg
B79: Cooling water | C79: =915.912/99.8 -> 9.177475 | D79: =14598/99.8 -> 146.27255 | E79: 0 | F79: 0 | G79: =C79 -> 9.177475 | H79: =D79 -> 146.27255 | K79: Mid pressure steam | L79: 214 | M79: 214 | N79: 21 | O79: 21 | P79: 1879.6128 | Q79: KJ/kg
B80: Electricity | C80: =407.21368/99.8 -> 4.0802974 | D80: 14139,4 KW* | E80: 0 | F80: 0 | G80: =C80 -> 4.0802974 | H80: 14139,4 KW* | K80: High pressure steam | L80: 265 | M80: 265 | N80: 51 | O80: 51 | P80: 1632.4494 | Q80: KJ/kg
K81: Cooling water | L81: 25 | M81: 40 | N81: 1.02 | O81: 1.02 | P81: =62.74243314036/(M81-L81) -> 4.1828289 | Q81: KJ/kg.K
B84: Low pressure steam | H84: Mid pressure steam
B85: Unit | C85: Energy - TJ/y | D85: Mass - ktonne/y | E85: Remark | H85: Unit | I85: Energy - TJ/y | J85: Mass - ktonne/y | K85: Remark
B86: U1-E7 | C86: =-23638.9*0.008/99.8 -> -1.8949018 | D86: =-90.1916/99.8 -> -0.90372345 | E86: Generation | H86: U1-E6 | I86: =-33036.4*0.008/99.8 -> -2.6482084 | J86: =-140.609/99.8 -> -1.4089078 | K86: Generation
B87: U1-E13 | C87: =-34090.5*0.008/99.8 -> -2.7327054 | D87: =-130.069/99.8 -> -1.3032966 | H87: U1-E12 | I87: =-24750.2*0.008/99.8 -> -1.983984 | J87: =-105.342/99.8 -> -1.0555311
B91: High pressure steam | H91: Electricity
B92: Unit | C92: Energy - TJ/y | D92: Mass - ktonne/y | E92: Remark | H92: Unit | I92: Energy - TJ/y | J92: Energy-kW | K92: Remark
B93: U1-E3 | C93: =-178482*0.008/99.8 -> -14.307174 | D93: =-874.672/99.8 -> -8.7642485 | E93: Generation | H93: U1-AD1 | I93: =1674.86*0.008/99.8 -> 0.13425731 | J93: =465.24/99.8 -> 4.6617234
B94: U1-E11 | C94: =-251401*0.008/99.8 -> -20.152385 | D94: =-1232.02/99.8 -> -12.34489 | H94: U1-C1 | I94: =49125.6*0.008/99.8 -> 3.9379238 | J94: =13646/99.8 -> 136.73347
H95: U1-C2 | I95: =101.25*0.008/99.8 -> 0.0081162325 | J95: =28.125/99.8 -> 0.28181363
B97: Cooling water | H97: Natural Gas | I97: Furnace
B98: Unit | C98: Energy - TJ/y | D98: Mass - ktonne/y | E98: Remark | H98: Unit | I98: Energy - TJ/y | J98: Mass - ktonne/y | K98: Remark
B99: U1-E8 | C99: =114489*0.008/99.8 -> 9.177475 | D99: =14598/99.8 -> 146.27255 | H99: U1-E2 | I99: =54346.5697779/99.8 *0.008 -> 4.3564385 | J99: =I99/53.4 -> 0.081581245 | K99: The feed methane is separate from the utility
H100: U1-R1 | I100: =3086.0843588/99.8 -> 30.922689 | J100: =I100/53.4 -> 0.57907657
B104: Disclaimer
B105: This process datasheet is part of the "Unravelling the impacts of using alternative raw materials in industrial clusters"
B106: Project Leader: Prof. dr. ir. Andrea Ramirez Ramirez. Energy & Industry, Faculty of Technology, Policy and Management, Delft University of Technology, The Netherlands.
B107: The affiliation of the process modelers and reviewers is: Energy & Industry, Faculty of Technology, Policy and Management, Delft University of Technology, The Netherlands.
B113: No. | C113: References
B114: [1] | C114: Häussinger, Peter; Lohmuller, Reiner;Watson, M. A. (2012). Hydrogen,6. Uses. Ullmann’s Encyclopedia of Industrial Chemistry, 353–390. https://doi.org/10.1002/14356007.o13
B115: [2] | C115: Giwa, A., & Giwa, S. O. (2013). Simulation, Sensitivity Analysis and Optimization of Hydrogen Production by Steam Reforming of Methane Using Aspen Plus. International Journal of Engineering Research & Technology, 2(7), 1719–1729.
B116: [3] | C116: Air Liquide Adding Major New H2 Production Unit for Neste NExBTL Plant in Rotterdam. (2020). Retrieved 28 July 2020, from https://www.greencarcongress.com/2008/06/air-liquide-add.html
B117: [4] | C117: Corso, F. Del. (2019). Technology status of hydrogen production from fossil fuels w / CCS. Workshop on Hydrogen Production with CCS organised by CSLF, IEAGHG, IEA Hydrogen TCP and Equinor. November 6th, Paris, France.
B118: [5] | C118: Steam reforming. (2020). Retrieved 28 July 2020, from https://en.wikipedia.org/wiki/Steam_reforming#cite_note-10
B119: [6] | C119: Pressure Swing Adsorption Design And Construction Psa Equipment - Buy Pressure Swing Adsorption Design,Psa,Psa Equipment Product on Alibaba.com. (2020). Retrieved 9 October 2020, from https://www.alibaba.com/product-detail/Pressure-Swing-Adsorption-Design-and-Construction_60728246607.html?spm=a2700.7724857.normalList.142.5c027934q1K9M1

Sheet Ethylene Oxide-Ethylene Glycol
B3: ETHYLENE OXIDE AND ETHYLENE GLYCOL PRODUCTION
B4: Process datasheet (Mass & Energy Balance)
B6: Production capacity | D6: 198 kt/y ethylene oxide & 135 kt/y monoethylene glycol
B7: Operating hours per year | D7: 8000
B9: Overall Process Description
B10: Ethylene oxide is an important chemical intermediate used in the production of ethylene glycols and also used for detergent ethoxylates, ethanolamines, glycol ethers and polyols [1]. Ethylene oxide is produced by the oxidation of ethylene. Most of the plants in Europe use oxygen for the oxidation purpose to reduce the purge gas emissions. Although ethylene oxide (EO) and ethylene glycol (EG) can be produced separately, nearly all European installations produce a mix of products in integrated plants [1]. Integrated plants are common because EO production is mainly exothermic and EG production requires a lot of energy for subsequent product distillations steps, hence, the integrated plants utilise the excess heat which makes this configuration highly desirable. Ethylene glycol is produced by reacting ethylene oxide with water. Ethylene glycol is a collective term that refers to monoethylene glycol (MEG), diethylene glycol (DEG) and triethylene glycol (TEG)[1]. MEG is mainly used as anti-freeze in cooling systems, for the manufacture of polyester fibres and polyethylene terephthalate (PET). DEG is used mainly for production of unsaturated polyester resins and in polyurethane systems and TEG is mainly used in the production of polybutylene terephthalate foils, for drying, etc [4].
B18: Process Diagram description
B19: The main feedstocks required for the production of ethylene oxide are; Ethylene and oxygen, and the main feedstocks required for ethylene glycol production are ethylene oxide and water [2]. In a solid-silver containing catalyst bed, 99.5% pure ethylene and 99% pure oxygen are reacted at 200-300 °C and 15-25 bar pressure to produce ethylene oxide[2][3]. The reaction is exothermic and the selectivity of the reaction is 75-90 wt% with an ethylene conversion of 8-10% [2].The overall reactions are as follows: Ethylene + 0,5 Oxygen → Ethylene oxide; main reaction Ethylene + 3 Oxygen → 2 CO2 + 2 H2O; side reaction As the ethylene oxygen mixture is highly explosive in the given conditions, a diluent is generally used to safe guard the process, and methane is generally used for this purpose. Hence, the concentration at the reactor inlet is maintained as follows [2]: Ethylene= 15-40 vol% Oxygen= 5-9 vol% CO2= 5-15 vol% Ethane= 0.2 vol% Argon= 5-15 vol% Methane= 1-60 vol% As the ethylene oxide reaction is exothermic, excess steam is produced from the process. The reactor outlet is then subsequently cooled to near atmospheric temperature followed by scrubbing the ethylene oxide using water in an ethylene scrubber. The gases from the ethylene oxide scrubber contain most of the unreacted reactants, by-products like CO2, diluent and impurities like ethane, argon and nitrogen. This gas stream is splitted into three streams: one is recycled to the oxidation reaction, a purge stream of about 0,1-0,2 wt% is taken to maintain the impurities level and another part is separately scrubbed using potassium carbonate solution to remove the excess CO2 from the recycle stream. The CO2 scrubbing loop includes mainly the absorber column and the CO2 desorber column, which are needed to regenerate the absorbent liquid. The CO2 rich stream obtained along with the purge gas are generally incinerated to safely discharge the off-gas, and to produce excess steam. On the other hand, the liquid from the ethylene oxide scrubber is sent to an ethylene oxide desorber to regenerate the scrubbing water and separate the ethylene oxide product. The ethylene oxide product is further subjected to steam stripping to remove other light ends from the product. The ethylene oxide is then subjected to distillation to obtain pure ethylene oxide[2]. These downstream purification steps generally occur at a pressure of 3-5 bar [3]. The water concentration of the final ethylene oxide stream recovered at the bottom of the ethylene oxide distillation column can be maintained since this mixture can be further processed directly in the ethylene glycol unit [2]. In the ethylene glycol section, the bottom of the ethylene distillation unit which contains mainly ethylene oxide and water is further processed to obtain ethylene glycol. This mixture should contain about 10-20 folds molar excess water at reactor inlet [4] or 80% water mass fraction at reactor outlet [3] to avoid ethylene glycol polymerization. The reaction occurs at a temperature of 200 °C and a pressure of 10-40 bar[1,3]. The glycol distribution is essentially unaffected by change in pressure and temperature in the given range [5] and the pressure is maintained so as to ensure liquid phase reaction conditions[4]. The reaction at the given conditions is spontaneous and the reactions are as follows[4]: Ethylene oxide + Water → Monoethylene glycol (MEG) Monoethylene glycol + Ethylene oxide → Diethylene glycol (DEG) Diethylene glycol + Ethylene oxide → Triethylene glycol (TEG) The excess water after the reactor is separated at lower pressure or atmospheric conditions in drying columns, and the water is recycled back together with the purge to maintain the purity of the recycled water. The crude glycol from the drying column bottom contains about 87% MEG, 12% DEG and 1% TEG [3]. This crude glycol is then further subjected to vacuum distillation to separate the MEG, DEG and TEG products[6]. This is done in order to maintain a temperature below 220 °C to avoid thermal degradation[6]. The main products of the process are Ethylene oxide and crude ethylene glycol (or MEG, DEG and TEG) and the main by-products of the overall process are effluent water and off-gas.
K36: LEGENDS
K37: FS- Feedstock/Raw material
K38: PS- Product
K39: WS-Waste
F72: Figure 1. Process Flow Diagram- Ethylene Oxide and Ethylene Glycol Production
B76: Mass Balances
B79: Raw materials | H79: Products | N79: Balance check
B80: Stream | C80: Composition (% mass) | D80: Flow kt/y | E80: Temperature ( °C ) | F80: Pressure (bar) | H80: Stream | I80: Composition (% mass) | J80: Flow kt/y | K80: Temperature ( °C ) | L80: Pressure (bar) | N80: Total inputs/outputs
B81: Oxygen | C81: 99% O2, 0,5% N2, 0,5% AR | D81: 305.842 | E81: 20 | F81: 1.02 | H81: Ethylene oxide | I81: 99,14% EO, 0,86% CO2 | J81: 197.76 | K81: 41 | L81: 3 | N81: Raw materials (FS) | O81: =SUM(D81:D92) -> 1691.3972
B82: Ethylene | C82: 99,5% Ethylene, 0,5% Ethane | D82: 269.406 | E82: 20 | F82: 1.02 | H82: Mono Ethylene glycol | I82: 99,97% MEG, 0,03% water | J82: 134.971 | K82: 40 | L82: 2 | N82: Products (PS) | O82: =SUM(J81:J87) -> 355.71739
B83: Diluent | C83: 100% Methane | D83: 33.4038 | E83: 40 | F83: 1.02 | H83: Di Ethylene glycol | I83: 99,% DEG, 0,37% MEG, 0,1% TEG | J83: 18.7039 | K83: 40 | L83: 2 | N83: Waste Streams (WS) | O83: =SUM(H90:H94) -> 0
B84: Combustion air | C84: 21 mol% O2, 79 mol% N2 | D84: 1065.16 | E84: 20 | F84: 1.02 | H84: Tri Ethylene glycol | I84: 98,95% TEG, 1% DEG, 0,05% TEEG | J84: 2.75827 | K84: 40 | L84: 2
B85: Stripping steam | C85: 100% water | D85: 16 | E85: 180 | F85: 5 | H85: Tetra Ethylene glycol | I85: 99,83% TEEG, 0,17% TEG | J85: 1.52422 | K85: 40 | L85: 2 | N85: Balance check | O85: =O81-O82-O83 -> 1335.6798
B86: Make-up water | C86: 100% water | D86: 1.58535 | E86: 20 | F86: 1.02 | N86: Percent error (%) | O86: =(O85/O81)*100 -> 78.96902
H88: Waste streams
H89: Stream | I89: Concentration (wt %) | J89: Flow kt/y | K89: Temperature ( °C ) | L89: Pressure (bar)
H90: Effluent water | I90: 100% water | J90: 1.59298 | K90: 40 | L90: 5
H91: Purge water | I91: 99,75% water, 0,25% MEG | J91: 35.0097 | K91: 40 | L91: 2
H92: Flue gas | I92: 66% N2, 20% CO2, 9% water, 5% O2 | J92: 1240.46 | K92: 200 | L92: 1.02
H93: Purge potassium carbonate solution (calculated) | I93: 98% CO2, 2% EO | J93: =57.3426+1.15653 -> 58.49913 | K93: 40 | L93: 5
B96: Energy Balances
B98: Utility type | C98: Input - TJ/y | D98: Input - kt/y | E98: Output - TJ/y | F98: Output - kt/y | G98: Net - TJ/y | H98: Net - kt/y | I98: Remark | K98: Utility process conditions
B99: Low pressure steam | C99: 3362.6961 | D99: 1548.9839 | E99: -1561.2079 | F99: -719.14778 | G99: =C99+E99 -> 1801.4882 | H99: =D99+F99 -> 829.83615 | K99: Utility type | L99: Inlet temperature ( °C ) | M99: Outlet temperature ( °C ) | N99: Inlet pressure (bar) | O99: Outlet pressure (bar) | P99: Heat capacity/latent heat/lower heating value | Q99: Unit
B100: Mid pressure steam | C100: 7204.5344 | D100: 3649.5949 | E100: -3266.7641 | F100: -1654.8419 | G100: =C100+E100 -> 3937.7703 | H100: =D100+F100 -> 1994.753 | K100: Low pressure steam | L100: 155 | M100: 155 | N100: 5.5 | O100: 5.5 | P100: 2096.7716 | Q100: KJ/kg
B101: High pressure steam | C101: 2773.9243 | D101: 1365.1618 | E101: -2106.231 | F101: -1036.5626 | G101: =C101+E101 -> 667.69327 | H101: =D101+F101 -> 328.59921 | K101: Mid pressure steam | L101: 214 | M101: 214 | N101: 21 | O101: 21 | P101: 1879.6128 | Q101: KJ/kg
B102: Cooling water | C102: 12297.492 | D102: 196204.69 | E102: 0 | F102: 0 | G102: =C102+E102 -> 12297.492 | H102: =D102+F102 -> 196204.69 | K102: High pressure steam | L102: 265 | M102: 265 | N102: 51 | O102: 51 | P102: 1632.4494 | Q102: KJ/kg
B103: Electricity | C103: 248.5221 | D103: 8629,24 kW* | E103: 0 | F103: 0 | G103: =C103+E103 -> 248.5221 | H103: 8629,24 kW* | K103: Very High pressure steam | L103: 500 | M103: 311 | N103: 100 | O103: 100 | P103: 1967 | Q103: KJ/kg
B104: Very High pressure steam | K104: Cooling water | L104: 25 | M104: 40 | N104: 1.02 | O104: 1.02 | P104: =62.74243314036/(M104-L104) -> 4.1828289 | Q104: KJ/kg.K
B108: Breakdown of requirements
B109: Very Low pressure steam | I109: Electricity
B110: Unit name | C110: Unit description | D110: Duty - MJ/hr | E110: Duty - TJ/y | F110: Mass - ktonne/y | G110: Remark | I110: Unit name | J110: Unit description | K110: Power - KW | L110: Energy- GWh/y | M110: Energy- TJ/y | N110: Remark
B111: - | C111: - | D111: - | E111: - | F111: - | G111: - | I111: E1-P3 | J111: Potassium carbonate solution feed pump | K111: 95.264413 | L111: =K111*'[2]Inputs and assumptions'!$E$19/1000000 -> #REF! | M111: =L111*60*60/1000 -> #REF! | N111: -
I112: E3-P3 | J112: MEG product pump | K112: 1.9987013 | L112: =K112*'[2]Inputs and assumptions'!$E$19/1000000 -> #REF! | M112: =L112*60*60/1000 -> #REF! | N112: -
B113: Low pressure steam | I113: E3-P4 | J113: DEG product pump | K113: 0.49105722 | L113: =K113*'[2]Inputs and assumptions'!$E$19/1000000 -> #REF! | M113: =L113*60*60/1000 -> #REF! | N113: -
B114: Unit name | C114: Unit description | D114: Duty - MJ/hr | E114: Duty - TJ/y | F114: Mass - ktonne/y | G114: Remark | I114: E3-P5 | J114: TEG product pump | K114: 0.081639286 | L114: =K114*'[2]Inputs and assumptions'!$E$19/1000000 -> #REF! | M114: =L114*60*60/1000 -> #REF! | N114: -
B115: E1-E2 | C115: Ethylene oxide cooler-1 | D115: -177601.13 | E115: =D115*'[2]Inputs and assumptions'!$E$19/1000000 -> #REF! | F115: -654.47507 | G115: - | I115: E3-P1 | J115: Ethylene glycol feed pump | K115: 145.37769 | L115: =K115*'[2]Inputs and assumptions'!$E$19/1000000 -> #REF! | M115: =L115*60*60/1000 -> #REF! | N115: -
B116: E1-E6 | C116: Flue-gas cooler-2 | D116: -17547.965 | E116: =D116*'[2]Inputs and assumptions'!$E$19/1000000 -> #REF! | F116: -64.665726 | G116: - | I116: E3-P2 | J116: Recycle feed pump | K116: 9.0173934 | L116: =K116*'[2]Inputs and assumptions'!$E$19/1000000 -> #REF! | M116: =L116*60*60/1000 -> #REF! | N116: -
B117: E3-E6 | C117: TEEG product cooler-1 | D117: -1.8939378 | E117: =D117*'[2]Inputs and assumptions'!$E$19/1000000 -> #REF! | F117: -0.0069793198 | G117: - | I117: E1-P1 | J117: Ethylene oxide scrubber water pump | K117: 454.81226 | L117: =K117*'[2]Inputs and assumptions'!$E$19/1000000 -> #REF! | M117: =L117*60*60/1000 -> #REF! | N117: -
B118: E1-T6 | C118: CO2 desorber | D118: 38029.241 | E118: =D118*'[2]Inputs and assumptions'!$E$19/1000000 -> #REF! | F118: 140.14095 | G118: - | I118: E1-P2 | J118: Make-up water pump | K118: 0.098667139 | L118: =K118*'[2]Inputs and assumptions'!$E$19/1000000 -> #REF! | M118: =L118*60*60/1000 -> #REF! | N118: -
B119: E1-E8 | C119: Recycle gas heater | D119: 322826.22 | E119: =D119*'[2]Inputs and assumptions'!$E$19/1000000 -> #REF! | F119: 1189.6417 | G119: - | I119: E1-C1 | J119: Oxygen feed compressor | K119: 3620.3518 | L119: =K119*'[2]Inputs and assumptions'!$E$19/1000000 -> #REF! | M119: =L119*60*60/1000 -> #REF! | N119: -
B120: E1-T4 | C120: Ethylene oxide distillation | D120: 55141.549 | E120: =D120*'[2]Inputs and assumptions'!$E$19/1000000 -> #REF! | F120: 203.20124 | G120: - | I120: E1-C2 | J120: Ethylene feed compressor | K120: 3520.4404 | L120: =K120*'[2]Inputs and assumptions'!$E$19/1000000 -> #REF! | M120: =L120*60*60/1000 -> #REF! | N120: -
B121: E1-T3 | C121: Steam stripper | D121: - | E121: 34.72 | F121: 16 | G121: Duty value calculated from mass flow | I121: E1-C3 | J121: Diluent compressor | K121: 781.25904 | L121: =K121*'[2]Inputs and assumptions'!$E$19/1000000 -> #REF! | M121: =L121*60*60/1000 -> #REF! | N121: -
I122: E3-P6 | J122: TEEG product pump | K122: 0.046434401 | L122: =K122*'[2]Inputs and assumptions'!$E$19/1000000 -> #REF! | M122: =L122*60*60/1000 -> #REF! | N122: -
I124: Cooling water
B125: Mid pressure steam | I125: Unit name | J125: Unit description | K125: Duty - MJ/hr | L125: Duty - TJ/y | M125: Mass - ktonne/y | N125: Remark
B126: Unit name | C126: Unit description | D126: Duty - MJ/hr | E126: Duty - TJ/y | F126: Mass - ktonne/y | G126: Remark | I126: E1-E7 | J126: Recycle potassium carbonate solution cooler | K126: 48105.899 | L126: =K126*'[2]Inputs and assumptions'!$E$19/1000000 -> #REF! | M126: 6140.1807 | N126: -
B127: E1-E5 | C127: Flue-gas cooler-1 | D127: -17963.407 | E127: =D127*'[2]Inputs and assumptions'!$E$19/1000000 -> #REF! | F127: -72.797665 | G127: - | I127: E3-E3 | J127: MEG product cooler | K127: 4811.476 | L127: =K127*'[2]Inputs and assumptions'!$E$19/1000000 -> #REF! | M127: 614.13117 | N127: -
B128: E1-R1 | C128: Ethylene oxide reactor | D128: -390382.1 | E128: =D128*'[2]Inputs and assumptions'!$E$19/1000000 -> #REF! | F128: -1582.0443 | G128: - | I128: E3-E4 | J128: DEG product cooler | K128: 207.19059 | L128: =K128*'[2]Inputs and assumptions'!$E$19/1000000 -> #REF! | M128: 26.445565 | N128: -
B129: E3-E1 | C129: Ethylene glycol feed heater | D129: 67045.823 | E129: =D129*'[2]Inputs and assumptions'!$E$19/1000000 -> #REF! | F129: 271.70677 | G129: - | I129: E3-E5 | J129: TEG column | K129: 103.26155 | L129: =K129*'[2]Inputs and assumptions'!$E$19/1000000 -> #REF! | M129: 13.180184 | N129: -
B130: E3-T1 | C130: Drying column | D130: 134356.04 | E130: =D130*'[2]Inputs and assumptions'!$E$19/1000000 -> #REF! | F130: 544.485 | G130: - | I130: E3-E2 | J130: Recycle cooler | K130: 219667.69 | L130: =K130*'[2]Inputs and assumptions'!$E$19/1000000 -> #REF! | M130: 28038.128 | N130: -
B131: E3-T2 | C131: MEG column | D131: 14374.107 | E131: =D131*'[2]Inputs and assumptions'!$E$19/1000000 -> #REF! | F131: 58.251836 | G131: - | I131: E3-T1 | J131: Drying column | K131: 5630.0778 | L131: =K131*'[2]Inputs and assumptions'!$E$19/1000000 -> #REF! | M131: 718.61655 | N131: -
B132: E3-T3 | C132: DEG column | D132: 2478.4153 | E132: =D132*'[2]Inputs and assumptions'!$E$19/1000000 -> #REF! | F132: 10.04391 | G132: - | I132: E3-T2 | J132: MEG column | K132: 17652.9 | L132: =K132*'[2]Inputs and assumptions'!$E$19/1000000 -> #REF! | M132: 2253.1955 | N132: -
B133: E3-T4 | C133: TEG column | D133: 218.62656 | E133: =D133*'[2]Inputs and assumptions'!$E$19/1000000 -> #REF! | F133: 0.88599577 | G133: - | I133: E3-T3 | J133: DEG column | K133: 2698.2172 | L133: =K133*'[2]Inputs and assumptions'!$E$19/1000000 -> #REF! | M133: 344.39729 | N133: -
B134: E1-T2 | C134: Ethylene oxide desorber | D134: 682093.79 | E134: =D134*'[2]Inputs and assumptions'!$E$19/1000000 -> #REF! | F134: 2764.2214 | G134: - | I134: E1-E3 | J134: Ethylene oxide cooler-2 | K134: 531555.18 | L134: =K134*'[2]Inputs and assumptions'!$E$19/1000000 -> #REF! | M134: 67847.082 | N134: -
I135: E1-E4 | J135: Water recycle cooler | K135: 490956.68 | L135: =K135*'[2]Inputs and assumptions'!$E$19/1000000 -> #REF! | M135: 62665.137 | N135: -
B136: High pressure steam | I136: E1-T2 | J136: Ethylene oxide desorber | K136: 159292.96 | L136: =K136*'[2]Inputs and assumptions'!$E$19/1000000 -> #REF! | M136: 20331.967 | N136: -
B137: Unit name | C137: Unit description | D137: Duty - MJ/hr | E137: Duty - TJ/y | F137: Mass - ktonne/y | G137: Remark | I137: E1-T4 | J137: Ethylene oxide distillation | K137: 40539.837 | L137: =K137*'[2]Inputs and assumptions'!$E$19/1000000 -> #REF! | M137: 5174.4574 | N137: -
B138: E1-FU1B | C138: Incinerator radiative section | D138: -263278.88 | E138: =D138*'[2]Inputs and assumptions'!$E$19/10^6 -> #REF! | F138: -1036.5626 | G138: - | I138: E1-C1 | J138: Oxygen feed compressor | K138: 8447.0805 | L138: =K138*'[2]Inputs and assumptions'!$E$19/1000000 -> #REF! | M138: 1078.1755 | N138: -
B139: E1-E1 | C139: Feed heater | D139: 346740.54 | E139: =D139*'[2]Inputs and assumptions'!$E$19/10^6 -> #REF! | F139: 1365.1618 | G139: - | I139: E1-C2 | J139: Ethylene feed compressor | K139: 5283.3726 | L139: =K139*'[2]Inputs and assumptions'!$E$19/1000000 -> #REF! | M139: 674.3635 | N139: -
I140: E1-C3 | J140: Diluent compressor | K140: 1932.2329 | L140: =K140*'[2]Inputs and assumptions'!$E$19/1000000 -> #REF! | M140: 246.62794 | N140: -
B141: Air | I141: E3-E7 | J141: TEEG product cooler-2 | K141: 58.695371 | L141: =K141*'[2]Inputs and assumptions'!$E$19/1000000 -> #REF! | M141: 7.4918086 | N141: -
B142: Unit name | C142: Unit description | D142: Duty - MJ/hr | E142: Duty - TJ/y | F142: Mass - ktonne/y | G142: Remark | I142: E3-T4 | J142: TEG column | K142: 243.72557 | L142: =K142*'[2]Inputs and assumptions'!$E$19/1000000 -> #REF! | M142: 31.108846 | N142: -
B143: - | C143: - | D143: 0 | E143: =D143*'[2]Inputs and assumptions'!$E$19/10^6 -> #REF! | F143: 0 | G143: -
I144: Refrigerant
B145: Natural gas | I145: Unit name | J145: Unit description | K145: Duty - MJ/hr | L145: Duty - TJ/y | M145: Mass - ktonne/y | N145: Remark
B146: Unit name | C146: Unit description | D146: Duty - MJ/hr | E146: Duty - TJ/y | F146: Mass - ktonne/y | G146: Remark | I146: E1-T3 | J146: Steam stripper | K146: 49150.679 | L146: =K146*'[2]Inputs and assumptions'!$E$19/1000000 -> #REF! | M146: 806.29186 | N146: -
B147: - | C147: - | D147: - | E147: - | F147: - | G147: - | I147: - | J147: - | K147: 0 | L147: =K147*'[2]Inputs and assumptions'!$E$19/1000000 -> #REF! | M147: - | N147: -
B155: Disclaimer
B156: This process datasheet is part of the "Unravelling the impacts of using alternative raw materials in industrial clusters"
B157: Project Leader: Prof. dr. ir. Andrea Ramirez Ramirez. Energy & Industry, Faculty of Technology, Policy and Management, Delft University of Technology, The Netherlands.
B158: The affiliation of the process modelers and reviewers is: Energy & Industry, Faculty of Technology, Policy and Management, Delft University of Technology, The Netherlands.
B166: No. | C166: References
B167: [1] | C167: Heino Falcke, Simon Holbrook, Iain Clenahan, Alfredo Lopez Carretero, Teoman Sanalan, Thomas Brinkmann, Joze Roth, Benoit Zerger Serge Roudier and Luis Delgado Sancho, "Best Available Techniques (BAT) Reference Document for the Production of Large Volume Organic Chemicals," JRC, European Commission, 2017.
B168: [2] | C168: Siegfried Rebsdat and Dieter Mayer, "Ethylene Oxide," in Ullmann's Encyclopaedia of Industrial Chemistry, Wiley-VCH Verlag GmbH & Co. KGaA, Weinheim, 2012, pp. 547-572.
B169: [3] | C169: Ineos NV, "MER voor de capaciteitsuitbreiding en hervergunning bij Ineos te Zwijndrecht," Ineos NV, 2007.
B170: [4] | C170: Siegfried Rebsdat and Dieter Mayer, "Ethylene Glycol," in Ullmann's Encyclopaedia of Industrial Chemistry, Wiley-VCH Verlag GmbH & Co. KGaA, Weinheim, 2012, pp. 531-546.
B171: [5] | C171: Emaad T. Bakir, Ethylene glycol production.

Sheet Biodiesel Production
B3: BIODIESEL PRODUCTION
B4: Process datasheet (Mass & Energy Balance)
B6: Production capacity | D6: 374 kt/y Biodiesel
B7: Operating hours per year | D7: 8000 h/y
B9: Overall Process Description
B10: Biodiesel is produced using vegetable oils from rapeseed, sunflower and soybean [2]. Most of the biodiesel is currently produced using base catalysed transesterification processes, with a yield efficency of about 98% [1]. It is most economical process route and uses moderate temperature and pressure conditions [1]. Lurgi’s transesterification process is widely used in large capacity plants [4]. The Lurgi process begins with intensive mixing of oil and methanol, in presence of a catalyst (preferably a base) and reaction occuring in a settling tank for about 90min at 60˚C [3]. A second stage reactor maximizes the biodiesel yield and quality [3]. The reactors promote separation of the lighter methyl ester and oil phase from the heavier glycerol and methanol in water [3]. The vegetable oils used in this process might contain Free Fatty Acids (FFAs) and thus a pretreatment with NaOH is needed. In cases where FFA content of the oil is above 1%, difficulties arise due to the formation of soap, which promotes emulsification during the water washing stage [3]. In the current sheet, rapeseed oil is used as a feedstock, composed of the following significant triglycerides- Trioleic acid (67,9%), Trilinoleic acid (23,5%), Trilinolenic acid (8,6%) excluding the small amounts of stearic, palmitic and other minority acids [5]. The reaction of triglycerides with methanol to give methyl esters and glycerine is presented below: The transesterification process uses a homogenous alkali catalyst like sodium methoxide (NAOCH3) [2]. The reaction product is washed with water in an extractor to recover methanol and glycerol from the stream. Methanol is separated from this stream and recycled back to the reactor, and the glycerine is further purified in another column to obtain glycerine with a purity of 80- 85 wt% [2]. This stream can be further processed to obtain a pharmaceutical grade glycerine [3, 6]. The transesterification process is used with a closed loop water wash to minimize the production of waste water [7]. The main product is a mixture of fatty acid methyl esters which is dried in a vacuum dryer to obtain a water-free product.
B18: Process Diagram description
B19: The current sheet is designed to produce ~375 kton/yr biodiesel (mixture of fatty acid methyl esters or FAME) from a similar amount of rapeseed oil with a composition of triglycerides as- Trioleic acid (67,9%), Trilinoleic acid (23,5%) and Trilinolenic acid (8,6%) (excluding minority acids) [3]. The feedstock oil is assumed to have no free fatty acids. Thus, a sodium hydroxide pretreatment is not modeled here. A high purity methanol is used for transesterification of the triglycerides, which is mixed with sodium methoxide, as a homogenous alkali catalyst, before inlet to the reactor. The flowsheet begins with an intense mixing of the oil and methanol at ambient conditions and the mix feed is inlet to the reactor. In large scale production plants (>4 mn lt/yr), CSTRs and Plug flow reactors are used instead of a batch transesterification process [8]. The reactor is a settling tank which operates at 60˚C and ambient pressures for 90min and allows the lighter methyl esters and oils to be separated from the water-methanol phase [2,4]. The heavy stream containing water, methanol and glycerol is sent to a recovery column where most of the methanol is recovered and recycled back to the first reactor. A second reactor in series increases the yield and quality of the product [3]. The water-methanol phase recovered from the second reactor is sent back to the first reactor. The product stream from this reactor goes to a water washer (an extraction column), where the methanol-glycerol from the product is recovered and sent to the methanol recovery column. The purified FAME stream is then sent to a vacuum dryer to remove the excess water. The product- FAME is treated to storage conditions. The bottoms of the methanol recovery column is sent to a neutralisation chamber to remove sodium methoxide catalyst from the glycerol-concentrated stream, and the recovered methanol at the top is recycled back to the first reactor. After the neutralisation, further vacuum evaporators remove water and methanol traces from the glycerol-rich stream [9] and the solid catalyst is removed from the liquid using centrifuge separator. The stream is further sent to a glycerol unit, where a crude glycerol product is produced. This bottom glycerine product in this column is 80-85 wt% pure and can be further purified for pharmaceutical requirements [7]. The water recovered from the glycerol column is recycled back to the water washing column.
L36: LEGENDS
L37: FS- Feedstock/Raw material
L38: PS- Product
L39: WS-Waste
G57: Figure 1. Process Flow Diagram- Biodiesel Production
B59: Mass Balances
B62: Raw materials | H62: Products | N62: Balance check
B63: Stream | C63: Composition (% mass) | D63: Flow kt/y | E63: Temp (C) | F63: Pressure (bar) | H63: Stream | I63: Composition (% mass) | J63: Flow kt/y | K63: Temp (C) | L63: Pressure (bar) | N63: Total inputs/outputs
B64: S-TRIGLY (Rapeseed oil) | C64: TRIOLEIN (67,9%), TRILINOL (23,5%), Trilinolenin (8,6%) | D64: 380 | E64: 25 | F64: 1.02 | H64: S-FAME (Biodiesel) | I64: METHY-01 (67,2%), METHY-02 (23,2%), METHY-03 (8,5%), WATER (0,2%) | J64: 373.993 | K64: 30 | L64: 1.02 | N64: Raw materials (FS) | O64: =SUM(D64:D68) -> 1307.6736
B65: S-METHANOL | C65: METHANOL (100%) | D65: 44.8796 | E65: 25 | F65: 1.02 | H65: S-GLYCEROL | I65: GLYC (83%), METHY-01 (8,1%), METHY-02 (2,7%) WATER (2,9%), H2SO4 (1,5%), METHY-03 (1,1%) | J65: 46.2257 | K65: 30 | L65: 1.02 | N65: Products (PS) | O65: =J64+J65 -> 420.2187
B66: S-NAOCH3 | C66: NAOCH3 (100%) | D66: 6 | E66: 25 | F66: 1.02 | H66: *METHY-# refers to Fatty Acid Methyl Esters (FAME) | N66: Waste Streams (WS) | O66: =SUM(J70:J76) -> 887.4566
B67: S-H2SO4 | C67: H2SO4 (98%) | D67: 5.765 | E67: 25 | F67: 1.02
B68: S-WASH | C68: H2O (100%) | D68: 871.029 | E68: 25 | F68: 1.02 | H68: Waste streams | N68: Balance check | O68: =O64-O65-O66 -> -0.0017
H69: Stream | I69: Composition (% mass) | J69: Flow kt/y | K69: Temp (C) | L69: Pressure (bar) | N69: Percent error (%) | O69: =(O68/O64)*100 -> -0.00013000186
H70: S-WW1 | I70: H2O (99,4%), METHY-01 (0,2%), METHY-02 (0,1%) | J70: 165.518 | K70: 30 | L70: 1.02
H71: S-WW2 | I71: H2O (99,3%) | J71: 1.272 | K71: 30 | L71: 1.02
H72: S-WW3 | I72: METHANOL (99,1%) | J72: 1.289 | K72: 30 | L72: 1.02
H73: S-WW4 | I73: H2O (98,8%), METHANOL (0,9%), METHY-01 (0,1%) | J73: 638.75 | K73: 40 | L73: 1.02
H74: S-WW5 | I74: H2O (99,2%), NAOCH3 (0,8%) | J74: 72.3276 | K74: 40 | L74: 1.02
H75: S-SOLCAT | I75: NA2SO4 (100%) | J75: 7.1 | K75: 110 | L75: 1.02
H76: S-PURG | I76: GLYCEROL (65%), WATER (23,7%) | J76: 1.2 | K76: 40 | L76: 1.02
B77: Energy Balances
B79: Utility type | C79: Input - TJ/y | D79: Input - kt/y | E79: Output - TJ/y | F79: Output - kt/y | G79: Net - TJ/y | H79: Net - kt/y | I79: Remark | K79: Utility process conditions
B80: Low pressure steam | C80: 2002.018 | D80: 922.2389 | E80: 0 | F80: 0 | G80: 2002.018 | H80: =D80 -> 922.2389 | K80: Utility type | L80: Inlet temperature ( °C ) | M80: Outlet temperature ( °C ) | N80: Inlet pressure (bar) | O80: Outlet pressure (bar) | P80: Heat capacity/latent heat/lower heating value | Q80: Unit
B81: Mid pressure steam | C81: 407.568 | D81: 205.89033 | E81: 0 | F81: 0 | G81: 407.568 | H81: =D81 -> 205.89033 | K81: Very Low pressure steam | L81: - | M81: - | N81: - | O81: - | P81: - | Q81: -
B82: High pressure steam | C82: 0 | D82: 0 | E82: 0 | F82: 0 | G82: 0 | H82: =D82 -> 0 | K82: Low pressure steam | L82: 155 | M82: 155 | N82: 5.5 | O82: 5.5 | P82: 2096.7716 | Q82: KJ/kg
B83: Cooling water | C83: 2456.3924 | D83: 117667.2 | E83: 0 | F83: 0 | G83: 2456.3924 | H83: =D83 -> 117667.2 | K83: Mid pressure steam | L83: 214 | M83: 214 | N83: 21 | O83: 21 | P83: 1879.6128 | Q83: KJ/kg
B84: Electricity | C84: 0.10514848 | D84: 3,65 kW* | E84: 0 | F84: 0 | G84: 0.10514848 | H84: =D84 -> 3,65 kW* | K84: High pressure steam | L84: 265 | M84: 265 | N84: 51 | O84: 51 | P84: 1632.4494 | Q84: KJ/kg
K85: Cooling water | L85: 25 | M85: 40 | N85: 1.02 | O85: 1.02 | P85: =62.74243314036/(M85-L85) -> 4.1828289 | Q85: KJ/kg.K
B86: Breakdown of requirements
B87: Low pressure steam | H87: Mid pressure steam
B88: Unit | C88: Energy - TJ/y | D88: Mass - ktonne/y | E88: Remark | H88: Unit | I88: Energy - TJ/y | J88: Mass - ktonne/y | K88: Remark
B89: B1-E7 | C89: 265.99316 | D89: 122.53098 | H89: B1-E1 | I89: =50946*0.008 -> 407.568 | J89: 205.89033
B90: B1-D4 | C90: 1330.399 | D90: 612.85448
B91: B1-D5 | C91: 80.041466 | D91: 36.871473
B92: B1-T2 | C92: 325.58439 | D92: 149.98196
B95: High pressure steam | H95: Electricity
B96: Unit | C96: Energy - TJ/y | D96: Mass - ktonne/y | E96: Remark | H96: Unit | I96: Energy - TJ/y | J96: Usage (kW) | K96: Remark
H97: B1-P1 | I97: 0.019058188 | J97: 0.66174265
H98: B1-P2 | I98: 0.040582851 | J98: 1.4091268
H99: B1-P3 | I99: 0.0050320326 | J99: 0.17472336
H100: B1-P4 | I100: 0.0025283899 | J100: 0.087791317
H101: B1-P5 | I101: 0.037947021 | J101: 1.3176049
B104: Cooling water
B105: Unit | C105: Energy - TJ/y | D105: Mass - ktonne/y | E105: Remark
B106: B1-E2 | C106: 427.28986 | D106: 20468.229
B107: B1-E3 | C107: =8602.86897708191*0.008 -> 68.822952 | D107: 3296.7877
B108: B1-E4 | C108: 2.7764853 | D108: 133.00043
B109: B1-E5 | C109: 0.36050079 | D109: 17.268869
B110: B1-E6 | C110: 18.695963 | D110: 895.58235
B111: B1-E8 | C111: 1588.1565 | D111: 76076.582
B112: B1-E9 | C112: 0.22862749 | D112: 10.951816
B113: B1-E10 | C113: 15.603069 | D113: 747.42513
B114: B1-T2 | C114: 294.35942 | D114: 14100.536
B115: B1-T3 | C115: 31.647839 | D115: 1516.0089
B116: B1-R1 | C116: 6.3568329 | D116: 304.50784
B117: B1-R2 | C117: 2.0942948 | D117: 100.32184
B121: Disclaimer
B122: This process datasheet is part of the "Unravelling the impacts of using alternative raw materials in industrial clusters"
B123: Project Leader: Prof. dr. ir. Andrea Ramirez Ramirez. Energy & Industry, Faculty of Technology, Policy and Management, Delft University of Technology, The Netherlands.
B124: The affiliation of the process modelers and reviewers is: Energy & Industry, Faculty of Technology, Policy and Management, Delft University of Technology, The Netherlands.
B126: No. | C126: References
B127: 1 | C127: Achten, W.M.J., Verchot, L., Franken, Y.J., Mathijs, E., Singh, V.P., Aerts, R., Muys, B., 2008. Jatropha bio-diesel production and use, a review. Biomass Bioenergy 32, 1063-1084
B128: 2 | C128: Khandelwal, M., van Dril, T. (2020). Decarbonisation options for the Dutch biofuels industry | PBL Planbureau voor de Leefomgeving. The Hague, 2020, PBL Publication Number: 3887, April, 67.
B129: 3 | C129: Luna, D., Calero, J., Sancho, E. D., Luna, C., Posadillo, A., Bautista, F. M., Romero, A. A., Berbel, J., & Verdugo, C. (2014). Technological challenges for the production of biodiesel in arid lands. Journal of Arid Environments, 102, 127–138. https://doi.org/10.1016/j.jaridenv.2013.11.014
B130: 4 | C130: Lurgi, 2004a. “Life Science: Brochures.” Lurgi Life Science. (Online). Available: http://www.lurgi-lifescience.com/lurgi_ls/english/nbsp/menu/media/brochures/ biodiesel_en.pdf [Mar. 27, 2004a]
B131: 5 | C131: Encinar, J. M., Pardal, A., Sánchez, N., & Nogales, S. (2018). Biodiesel by transesterification of rapeseed oil using ultrasound: A kinetic study of base-catalysed reactions. Energies, 11(9). https://doi.org/10.3390/en11092229
B132: 6 | C132: Georgogianni, K. G., Katsoulidis, A. K., Pomonis, P. J., Manos, G., & Kontominas, M. G. (2009). Transesterification of rapeseed oil for the production of biodiesel using homogeneous and heterogeneous catalysis. Fuel Processing Technology, 90(7–8), 1016–1022. https://doi.org/10.1016/J.FUPROC.2009.03.002
B133: 7 | C133: Air Liquide. (2017). BIODIESEL ULTRA LOW IN PRECIPITATES. Retrieved from https://www.engineering-airliquide.com/sites/activity_eandc/files/2017/11/22/air-liquide-e-c-biodiesel-september-2017.pdf
B134: 8 | C134: https://farm-energy.extension.org/commercial-and-large-scale-biodiesel-production-systems/
B135: 9 | C135: Stevens, R., & Scouting, V. P. T. Decarbonize. "Separation method of sodium sulfate salt and glycerol in 12-hydroxytearic acid production waste liquid", 2009
B136: 10 | C136: Dhar, B. R., & Kirtania, K. (2009). Excess Methanol Recovery in Biodiesel Production Process Using a Distillation Column: A Simulation Study. Chemical Engineering Research Bulletin, 13(2). https://doi.org/10.3329/cerb.v13i2.3538

Sheet PET Production Plant
B3: PET PLANT
B4: Process datasheet (Mass & Energy Balance)
B6: Production capacity | D6: 1 kt PTA and 1 kt PET | E6: Note: You can scale up to desired PTA and PET production
B7: Operating hours per year | D7: 8000 h/y
B9: Overall Process Description
B10: Purified Terephthalic Acid (PTA) Production Terephthalic acid is used mainly to make saturated polyesters with aliphatic diols as co-monomers. Terephthalic acid is produced by the oxidation of methyl groups on the corresponding p-xylene. Most of the terephthalate feedstock used worldwide is produced with a catalytic system consisting of a soluble cobalt-manganese-bromine system. Acetic acid is generally used as the solvent and oxygen in compressed air as the oxidant [1]. The crude Terephthalic acid formed by this process is unsuitable as feedstock for polyester owing to the 4-formylbenzoic acid impurities. Hence, the crude Terephthalic acid undergoes a further hydrogenation purification step to form Purified Terephthalic acid [1]. The main raw materials required are p-xylene, hydrogen and acetic acid. PET Production Polyesters are polymers containing an ester group in the repeating unit of the main polymer chain and are formed by poly-condensation using step-growth reaction [2]. PET is a thermoplastic polyester resin used mainly for polyester fibres, food packaging and PET bottles [3]. PET is commercially produced from ethylene glycol and either dimethyl terephthalate (DMT) or Terephthalic acid (PTA) [3] by batch-wise or continuous processes [2] [4]. The process occurs at vacuum conditions to ensure complete condensation and recovery of ethylene glycol [2]. The polymer formed is further processed for crystallization generally using solid state post condensation techniques under inert conditions [4] [5]. In this datasheet, only the PTA route to form PET is considered. Hence, the main raw materials are PTA and ethylene glycol.
B18: Process Diagram description
B19: PTA Production The main feedstock required for the production of Purified Terephthalic Acid (PTA) are: p-xylene, acetic acid (solvent), hydrogen and oxygen (air) [1, 6]. Terephthalic Acid (TA) is produced by the air oxidation of p-xylene in the presence of cobalt-manganese-bromine catalyst system with acetic acid as solvent. The reaction occurs at 20 bar and 200 °C, as presented as follows [6]: p-xylene + 3 O2 → TA + 2 H2O The reaction yield of Terephthalic acid is about 95 mol% and the remaining p-xylene is converted to CO2 by complete oxidation and oxidation intermediates like 4-formyl benzoic acid (FBA) [1]. These side reactions are as follows: p-xylene + 2.5 O2 → FBA + 2 H2O p-xylene + 10.5 O2 → 8 CO2 + 5 H2O The acetic acid flow is maintained such that the solvent to p-xylene weight ratio at the reactor inlet is less than 5 [7]. A small part of the solvent reacts with oxygen to form methyl acetate as by-product, and the reaction is such that around 10-40g methyl acetate is formed per kg of p-xylene used. The methyl acetate production is according to the following reaction [8]: 2 Acetic acid + 0.5 O2 → Methyl acetate + H2O + CO2 The p-xylene oxidation reactor temperature is maintained at 200 °C through solvent evaporation and solvent recycle from the overhead condenser. The off-gas from the oxidation reactor is scrubbed in a high pressure absorber column using water. The recovered solvent-water mixture from the high pressure absorber is sent to a dehydration column. As the solvent (acetic acid)-water mixture is azeotropic, propyl acetate is used for extractive distillation technique with single phase reflux. Acetic acid is obtained as bottom product , water is obtained as top product from overhead separator and a mixture of methyl acetate- propyl acetate is obtained as organic phase from overhead separator. The methyl acetate-propyl acetate mixture is further distilled in the solvent recovery column to obtain propyl acetate as bottom product and methyl acetate as top product. The methyl acetate is sent to the incinerator and the propyl acetate is recycled back to the extractive distillation column with a make-up stream [6, 9]. The oxidation reactor bottom contains mainly TA, FBA and acetic acid and it is sent to a surge vessel to reduce the pressure and for crystallization of the terephthalic acid. The crystallised TA has a particle size distribution of D50% as 60 microns [10]. This stream is further processed in a centrifuge/dryer to remove liquid from the crystallised TA. The liquid from the centrifuge/dryer is sent to the dehydration column in which the acetic acid is recovered and sent back as solvent feed. The water from the top of the dehydration column is further distilled in a water recovery column to remove unwanted dissolved gases, and these gases are incinerated. The water from the bottom of the water recovery column is recycled back to the high pressure absorber and a part of it is purged out to remove excess water formed in the system [1, 6]. The crude terephthalic acid from the centrifuge has impurities like FBA, which makes it unsuitable for further applications, such as PET production. Hence, it is further purified in a hydrogenation section. The crude terephthalic acid is first mixed with water to produce a solution of 15 weight % Terephthalic acid [1], and then this mixture is hydrogenated over a palladium containing catalyst at about 232 °C [6]. The pressure of the hydrogenation reactor is maintained at very high values to minimize vaporization of water. In the hydrogenation reactor, FBA is converted to p-toluic acid, as presented as follows [1]: FBA + 2 H2 → p-Toluic acid + H2O p-Toluic acid is soluble in water compared to FBA and thus, it is easily removed from terephthalic acid after pressure reduction in a centrifuge [1]. The recovered water from the centrifuge is recycled back, and the off-gas from the depressurisation drum is incinerated. The outlet from the centrifuge is purified Terephthalic acid (PTA) which can be used for PET process. PET Production PET is commercially produced by the esterification of PTA with diols like Monoethylene glycol (MEG), which is followed by a polycondensation step. First, PTA in powder form is mixed with MEG to form a paste which is fed to the esterification reactor using gear pumps [3]. The esterification reaction occurs generally in two reactors in series at a pressure of 4 bar [3] and 250 °C [11], and 1 bar [3] and 260 °C [3], respectively. The reaction is as follows: PTA + 2 MEG → bis (2-hydroxyethyl) terephthalate + 2 H2O In the esterification reactor, at the inlet the MEG to PTA ratio is maintained at a molar ratio of less than 1.5 as it helps to suppress diethylene glycol formation. From the two esterification reactors in series, the bis (2-hydroxyethyl) terephthalate (BHET) formed is the monomer for PET. The BHET is pumped to the low polymerization reactor to produce low viscosity Poly-Ethylene Terephthalate (PET). The low polymerisation reactor operates at about 30 mmHg and 270 °C [3]. During the polymerization reaction, MEG is released and the reaction takes place as follows: BHET → PET + Ethylene glycol The recovered MEG is sent to a central glycol recovery unit to remove water, and the recovered glycol is recycled back to the process. The PET polymer formed from this process is amorphous PET solids. The product PET It is cooled and stored [4].
C66: Figure 1. Process Flow Diagram- PTA Production | K66: Figure 2. Process Flow Diagram- PET Production
B71: Mass Balances
B73: PTA Production | H73: Products
B74: Raw materials | H74: Stream | I74: Composition (% mass) | J74: kt/kt PTA | K74: Temperature ( °C ) | L74: Pressure (bar) | N74: Balance check
B75: Stream | C75: Composition (% mass) | D75: kt/kt PTA | E75: Temperature ( °C ) | F75: Pressure (bar) | H75: PTA | I75: 99.99% Terephthalic acid, 0.01% H2O | J75: =347.350538028326/347 -> 1.0010102 | K75: 80 | L75: 2 | N75: Total inputs/outputs
B76: p-Xylene | C76: 99.78% p-xylene, 0.11% EB, 0.11% o-xylene | D76: =231.444932/347 -> 0.66698828 | E76: 22 | F76: 1.02 | N76: Raw materials (FS) | O76: =SUM(D76:D81) -> 4.1689146
B77: Solvent | C77: 100% Acetic acid | D77: =13.6440636959997/347 -> 0.039320068 | E77: 15 | F77: 1.02 | H77: Waste streams | N77: Products (PS) | O77: =J75 -> 1.0010102
B78: Oxidation air | C78: 23.13% O2, 75.27% N2, 0.05% CO2, 0.27% H2O, 1.28% Argon | D78: =900.595674510858/347 -> 2.5953766 | E78: 15 | F78: 1.02 | H78: Stream | I78: Composition (% mass) | J78: kt/kt PTA | K78: Temperature ( °C ) | L78: Pressure (bar) | N78: Waste Streams (WS) | O78: =SUM(J79:J81) -> 3.1678951
B79: Solvent water | C79: 100% water | D79: =219.0436808934/347 -> 0.6312498 | E79: 15 | F79: 1.02 | H79: Excess water | I79: 83.82% water, 16.18% acetic acid | J79: =30.0133586017961/347 -> 0.086493829 | K79: 40 | L79: 20
B80: Hydrogen | C80: 99.93% H2, 0.07% N2 | D80: =0.178450329647011/347 -> 0.00051426608 | E80: 40 | F80: 15 | H80: Vent gas | I80: 0.51% P-xylene, 0.61% HOAC, 80.37% N2, 6.5% water, 0.21% CO2, 0.41% O2, 0.27% MEOAC, 9.69% NPAC, 1.37% Ar, 0.03% EB, 0.03% O-xylene | J80: =843.451574342191/347 -> 2.4306962 | K80: 46 | L80: 1.02 | N80: Balance check | O80: =O76-O77-O78 -> 9.2534951e-06
B81: Extractive distillation solvent | C81: 100% propyl acetate | D81: =81.7065600000001/347 -> 0.23546559 | E81: 40 | F81: 1.02 | H81: Wastewater | I81: 97.35% water, 2.65% PTA | J81: =225.794679494802/347 -> 0.65070513 | K81: 40 | L81: 2 | N81: Percent error (%) | O81: =(O80/O76)*100 -> 0.00022196413
B88: PET Production | H88: Products
B89: Raw materials | H89: Stream | I89: Composition (% mass) | J89: kt/kt PET | K89: Temperature ( °C ) | L89: Pressure (bar) | N89: Balance check
B90: Stream | C90: Composition (% mass) | D90: kt/kt PET | E90: Temperature ( °C ) | F90: Pressure (bar) | H90: PET | I90: 100% PET | J90: =231.322590889142/231.32 -> 1.0000112 | K90: 80 | L90: 1.02 | N90: Total inputs/outputs
B91: PTA feed | C91: 99.99% Terephthalic acid, 0.01% H2O | D91: =200/231.32 -> 0.86460315 | E91: 80 | F91: 2 | N91: Raw materials (FS) | O91: =SUM(D91:D96) -> 1.2928724
B92: MEG feed | C92: 99.953% MEG, 0.047% H2O | D92: =99.0672526704258/231.32 -> 0.42826929 | E92: 40 | F92: 2 | H92: Waste streams | N92: Products (PS) | O92: =J90 -> 1.0000112
H93: Stream | I93: Composition (% mass) | J93: kt/kt PET | K93: Temperature ( °C ) | L93: Pressure (bar) | N93: Waste Streams (WS) | O93: =SUM(J94:J96) -> 0.29286082
H94: Effluent | I94: 64% water, 36% MEG | J94: =67.7445659356224/231.32 -> 0.29286082 | K94: 61 | L94: 1.02
N95: Balance check | O95: =O91-O92-O93 -> 4.143423e-07
N96: Percent error (%) | O96: =(O95/O91)*100 -> 3.2048197e-05
B101: Energy Balances
B103: PTA Production
B104: Utility type | C104: Input - TJ/kt PTA | D104: Input - kt/kt PTA | E104: Output - TJ/kt PTA | F104: Output - kt/kt PTA | G104: Net - TJ/kt PTA | H104: Net - kt/kt PTA | I104: Remark | K104: Utility process conditions
